Workbook

Sheet Pricing Grille C
A1: PRICING DYNAMIQUE · GRILLE 3 COLONNES
A2: Les 3 produits en parallèle · 1 sélection Concentrate → Isolate & Recovery se recalculent
A4: HYPOTHÈSES PARTAGÉES
A5: TVA | B5: 0.055 | C5: Remise | D5: 0.18 | E5: PR Conc | F5: 21 | G5: PR Iso | H5: 25 | I5: PR Rec | J5: 12.15
A7: ▌ CONCENTRATE | F7: ▌ ISOLATE ⬅ cascade | K7: ▌ RECOVERY ⬅ cascade
A9: 🎯 Option sélectionnée | F9: 🎯 Option sélectionnée | K9: 🎯 Option sélectionnée
B10: 5 | G10: 5 | L10: 5
A12: → Prix retenu | F12: → Prix retenu | K12: → Prix retenu
B13: =INDEX($B$29:$B$38,$B10) | G13: =INDEX($G$29:$G$38,$G10) | L13: =INDEX($L$29:$L$38,$L10)
A14: Marge nette | B14: =IFERROR((B13*(1-$D$5)-$F$5)/(B13*(1-$D$5)),0) | F14: Marge nette | G14: =IFERROR((G13*(1-$D$5)-$H$5)/(G13*(1-$D$5)),0) | K14: Marge nette | L14: =IFERROR((L13*(1-$D$5)-$J$5)/(L13*(1-$D$5)),0)
A16: BENCHMARK MARCHÉ | F16: BENCHMARK MARCHÉ | K16: BENCHMARK MARCHÉ
A17: =AVERAGE('Synthèse prix'!H14,'Synthèse prix'!H15,'Synthèse prix'!H19,'Synthèse prix'!H20,'Synthèse prix'!H24,'Synthèse prix'!H25,'Synthèse prix'!H26,'Synthèse prix'!H31,'Synthèse prix'!H37,'Synthèse prix'!H50) | B17: =MEDIAN('Synthèse prix'!H14,'Synthèse prix'!H15,'Synthèse prix'!H19,'Synthèse prix'!H20,'Synthèse prix'!H24,'Synthèse prix'!H25,'Synthèse prix'!H26,'Synthèse prix'!H31,'Synthèse prix'!H37,'Synthèse prix'!H50) | C17: =MIN('Synthèse prix'!H14,'Synthèse prix'!H15,'Synthèse prix'!H19,'Synthèse prix'!H20,'Synthèse prix'!H24,'Synthèse prix'!H25,'Synthèse prix'!H26,'Synthèse prix'!H31,'Synthèse prix'!H37,'Synthèse prix'!H50) | D17: =MAX('Synthèse prix'!H14,'Synthèse prix'!H15,'Synthèse prix'!H19,'Synthèse prix'!H20,'Synthèse prix'!H24,'Synthèse prix'!H25,'Synthèse prix'!H26,'Synthèse prix'!H31,'Synthèse prix'!H37,'Synthèse prix'!H50) | F17: =AVERAGE('Synthèse prix'!H7,'Synthèse prix'!H10,'Synthèse prix'!H11,'Synthèse prix'!H18,'Synthèse prix'!H21,'Synthèse prix'!H22,'Synthèse prix'!H23,'Synthèse prix'!H29,'Synthèse prix'!H30,'Synthèse prix'!H35,'Synthèse prix'!H41,'Synthèse prix'!H47) | G17: =MEDIAN('Synthèse prix'!H7,'Synthèse prix'!H10,'Synthèse prix'!H11,'Synthèse prix'!H18,'Synthèse prix'!H21,'Synthèse prix'!H22,'Synthèse prix'!H23,'Synthèse prix'!H29,'Synthèse prix'!H30,'Synthèse prix'!H35,'Synthèse prix'!H41,'Synthèse prix'!H47) | H17: =MIN('Synthèse prix'!H7,'Synthèse prix'!H10,'Synthèse prix'!H11,'Synthèse prix'!H18,'Synthèse prix'!H21,'Synthèse prix'!H22,'Synthèse prix'!H23,'Synthèse prix'!H29,'Synthèse prix'!H30,'Synthèse prix'!H35,'Synthèse prix'!H41,'Synthèse prix'!H47) | I17: =MAX('Synthèse prix'!H7,'Synthèse prix'!H10,'Synthèse prix'!H11,'Synthèse prix'!H18,'Synthèse prix'!H21,'Synthèse prix'!H22,'Synthèse prix'!H23,'Synthèse prix'!H29,'Synthèse prix'!H30,'Synthèse prix'!H35,'Synthèse prix'!H41,'Synthèse prix'!H47) | K17: =AVERAGE('Synthèse prix'!H5,'Synthèse prix'!H6,'Synthèse prix'!H32) | L17: =MEDIAN('Synthèse prix'!H5,'Synthèse prix'!H6,'Synthèse prix'!H32) | M17: =MIN('Synthèse prix'!H5,'Synthèse prix'!H6,'Synthèse prix'!H32) | N17: =MAX('Synthèse prix'!H5,'Synthèse prix'!H6,'Synthèse prix'!H32)
A18: Moy | B18: Méd | C18: Min | D18: Max | F18: Moy | G18: Méd | H18: Min | I18: Max | K18: Moy | L18: Méd | M18: Min | N18: Max
F20: CALCUL AUTO — Algo Option C | K20: CALCUL AUTO — Algo Option C
F21: Plancher marge 38% | I21: =CEILING($H$5/(1-0.38)/(1-$D$5)+0.1,1)-0.1 | K21: Plancher marge 38% | N21: =CEILING($J$5/(1-0.38)/(1-$D$5)+0.1,1)-0.1
F22: Cible marge 40% | I22: =CEILING($H$5/(1-0.40)/(1-$D$5)+0.1,1)-0.1 | K22: Plancher C+5% | N22: =CEILING(B13*1.05+0.1,1)-0.1
F23: Anti-cannib (C×1,10) | I23: =CEILING(B13*1.10+0.1,1)-0.1 | K23: Plafond I−5% | N23: =CEILING(G13*0.95+0.1,1)-0.1
F24: Marché médiane | I24: =MEDIAN('Synthèse prix'!H7,'Synthèse prix'!H10,'Synthèse prix'!H11,'Synthèse prix'!H18,'Synthèse prix'!H21,'Synthèse prix'!H22,'Synthèse prix'!H23,'Synthèse prix'!H29,'Synthèse prix'!H30,'Synthèse prix'!H35,'Synthèse prix'!H41,'Synthèse prix'!H47) | K24: Marché réf (Impulse) | N24: ='Synthèse prix'!H5
F25: → PP OPTIMAL | I25: =MAX(I21,I23,MIN(I22,I24)) | K25: → PP OPTIMAL | N25: =MAX(N21,N22,MIN(N23,N24))
A27: # | B27: Prix | C27: Marge % | D27: Flag | F27: # | G27: Prix | H27: Marge % | I27: Flag | K27: # | L27: Prix | M27: Marge % | N27: Flag
A29: 1 | B29: 29.9 | C29: =IFERROR((B29*(1-$D$5)-$F$5)/(B29*(1-$D$5)),0) | D29: =IF(C29<0.30,"⚠️ Marge basse",IF(C29<0.35,"🟡 Limite",IF(C29<=0.42,"🎯 Optimal","🔵 Premium"))) | F29: 1 | G29: =CEILING(I25-4+0.1,1)-0.1 | H29: =IFERROR((G29*(1-$D$5)-$H$5)/(G29*(1-$D$5)),0) | I29: =IF(H29<0.30,"⚠️ Marge basse",IF(IFERROR((G29-B13)/B13,0)<0.1,"🚫 Cannibalisme",IF(H29<0.35,"🟡 Limite",IF(H29<=0.42,"🎯 Optimal","🔵 Premium")))) | K29: 1 | L29: =CEILING(N25-4+0.1,1)-0.1 | M29: =IFERROR((L29*(1-$D$5)-$J$5)/(L29*(1-$D$5)),0) | N29: =IF(M29<0.30,"⚠️ Marge basse",IF(IFERROR((L29-B13)/B13,0)<0.05,"🚫 Cannibalisme",IF(M29<0.35,"🟡 Limite",IF(M29<=0.42,"🎯 Optimal","🔵 Premium"))))
A30: 2 | B30: 31.9 | C30: =IFERROR((B30*(1-$D$5)-$F$5)/(B30*(1-$D$5)),0) | D30: =IF(C30<0.30,"⚠️ Marge basse",IF(C30<0.35,"🟡 Limite",IF(C30<=0.42,"🎯 Optimal","🔵 Premium"))) | F30: 2 | G30: =CEILING(I25-3+0.1,1)-0.1 | H30: =IFERROR((G30*(1-$D$5)-$H$5)/(G30*(1-$D$5)),0) | I30: =IF(H30<0.30,"⚠️ Marge basse",IF(IFERROR((G30-B13)/B13,0)<0.1,"🚫 Cannibalisme",IF(H30<0.35,"🟡 Limite",IF(H30<=0.42,"🎯 Optimal","🔵 Premium")))) | K30: 2 | L30: =CEILING(N25-3+0.1,1)-0.1 | M30: =IFERROR((L30*(1-$D$5)-$J$5)/(L30*(1-$D$5)),0) | N30: =IF(M30<0.30,"⚠️ Marge basse",IF(IFERROR((L30-B13)/B13,0)<0.05,"🚫 Cannibalisme",IF(M30<0.35,"🟡 Limite",IF(M30<=0.42,"🎯 Optimal","🔵 Premium"))))
A31: 3 | B31: 33.9 | C31: =IFERROR((B31*(1-$D$5)-$F$5)/(B31*(1-$D$5)),0) | D31: =IF(C31<0.30,"⚠️ Marge basse",IF(C31<0.35,"🟡 Limite",IF(C31<=0.42,"🎯 Optimal","🔵 Premium"))) | F31: 3 | G31: =CEILING(I25-2+0.1,1)-0.1 | H31: =IFERROR((G31*(1-$D$5)-$H$5)/(G31*(1-$D$5)),0) | I31: =IF(H31<0.30,"⚠️ Marge basse",IF(IFERROR((G31-B13)/B13,0)<0.1,"🚫 Cannibalisme",IF(H31<0.35,"🟡 Limite",IF(H31<=0.42,"🎯 Optimal","🔵 Premium")))) | K31: 3 | L31: =CEILING(N25-2+0.1,1)-0.1 | M31: =IFERROR((L31*(1-$D$5)-$J$5)/(L31*(1-$D$5)),0) | N31: =IF(M31<0.30,"⚠️ Marge basse",IF(IFERROR((L31-B13)/B13,0)<0.05,"🚫 Cannibalisme",IF(M31<0.35,"🟡 Limite",IF(M31<=0.42,"🎯 Optimal","🔵 Premium"))))
A32: 4 | B32: 34.9 | C32: =IFERROR((B32*(1-$D$5)-$F$5)/(B32*(1-$D$5)),0) | D32: =IF(C32<0.30,"⚠️ Marge basse",IF(C32<0.35,"🟡 Limite",IF(C32<=0.42,"🎯 Optimal","🔵 Premium"))) | F32: 4 | G32: =CEILING(I25-1+0.1,1)-0.1 | H32: =IFERROR((G32*(1-$D$5)-$H$5)/(G32*(1-$D$5)),0) | I32: =IF(H32<0.30,"⚠️ Marge basse",IF(IFERROR((G32-B13)/B13,0)<0.1,"🚫 Cannibalisme",IF(H32<0.35,"🟡 Limite",IF(H32<=0.42,"🎯 Optimal","🔵 Premium")))) | K32: 4 | L32: =CEILING(N25-1+0.1,1)-0.1 | M32: =IFERROR((L32*(1-$D$5)-$J$5)/(L32*(1-$D$5)),0) | N32: =IF(M32<0.30,"⚠️ Marge basse",IF(IFERROR((L32-B13)/B13,0)<0.05,"🚫 Cannibalisme",IF(M32<0.35,"🟡 Limite",IF(M32<=0.42,"🎯 Optimal","🔵 Premium"))))
A33: 5 | B33: 36.9 | C33: =IFERROR((B33*(1-$D$5)-$F$5)/(B33*(1-$D$5)),0) | D33: =IF(C33<0.30,"⚠️ Marge basse",IF(C33<0.35,"🟡 Limite",IF(C33<=0.42,"🎯 Optimal","🔵 Premium"))) | F33: 5 | G33: =CEILING(I25+0.1,1)-0.1 | H33: =IFERROR((G33*(1-$D$5)-$H$5)/(G33*(1-$D$5)),0) | I33: =IF(H33<0.30,"⚠️ Marge basse",IF(IFERROR((G33-B13)/B13,0)<0.1,"🚫 Cannibalisme",IF(H33<0.35,"🟡 Limite",IF(H33<=0.42,"🎯 Optimal","🔵 Premium")))) | K33: 5 | L33: =CEILING(N25+0.1,1)-0.1 | M33: =IFERROR((L33*(1-$D$5)-$J$5)/(L33*(1-$D$5)),0) | N33: =IF(M33<0.30,"⚠️ Marge basse",IF(IFERROR((L33-B13)/B13,0)<0.05,"🚫 Cannibalisme",IF(M33<0.35,"🟡 Limite",IF(M33<=0.42,"🎯 Optimal","🔵 Premium"))))
A34: 6 | B34: 37.9 | C34: =IFERROR((B34*(1-$D$5)-$F$5)/(B34*(1-$D$5)),0) | D34: =IF(C34<0.30,"⚠️ Marge basse",IF(C34<0.35,"🟡 Limite",IF(C34<=0.42,"🎯 Optimal","🔵 Premium"))) | F34: 6 | G34: =CEILING(I25+1+0.1,1)-0.1 | H34: =IFERROR((G34*(1-$D$5)-$H$5)/(G34*(1-$D$5)),0) | I34: =IF(H34<0.30,"⚠️ Marge basse",IF(IFERROR((G34-B13)/B13,0)<0.1,"🚫 Cannibalisme",IF(H34<0.35,"🟡 Limite",IF(H34<=0.42,"🎯 Optimal","🔵 Premium")))) | K34: 6 | L34: =CEILING(N25+1+0.1,1)-0.1 | M34: =IFERROR((L34*(1-$D$5)-$J$5)/(L34*(1-$D$5)),0) | N34: =IF(M34<0.30,"⚠️ Marge basse",IF(IFERROR((L34-B13)/B13,0)<0.05,"🚫 Cannibalisme",IF(M34<0.35,"🟡 Limite",IF(M34<=0.42,"🎯 Optimal","🔵 Premium"))))
A35: 7 | B35: 39.9 | C35: =IFERROR((B35*(1-$D$5)-$F$5)/(B35*(1-$D$5)),0) | D35: =IF(C35<0.30,"⚠️ Marge basse",IF(C35<0.35,"🟡 Limite",IF(C35<=0.42,"🎯 Optimal","🔵 Premium"))) | F35: 7 | G35: =CEILING(I25+2+0.1,1)-0.1 | H35: =IFERROR((G35*(1-$D$5)-$H$5)/(G35*(1-$D$5)),0) | I35: =IF(H35<0.30,"⚠️ Marge basse",IF(IFERROR((G35-B13)/B13,0)<0.1,"🚫 Cannibalisme",IF(H35<0.35,"🟡 Limite",IF(H35<=0.42,"🎯 Optimal","🔵 Premium")))) | K35: 7 | L35: =CEILING(N25+2+0.1,1)-0.1 | M35: =IFERROR((L35*(1-$D$5)-$J$5)/(L35*(1-$D$5)),0) | N35: =IF(M35<0.30,"⚠️ Marge basse",IF(IFERROR((L35-B13)/B13,0)<0.05,"🚫 Cannibalisme",IF(M35<0.35,"🟡 Limite",IF(M35<=0.42,"🎯 Optimal","🔵 Premium"))))
A36: 8 | B36: 41.9 | C36: =IFERROR((B36*(1-$D$5)-$F$5)/(B36*(1-$D$5)),0) | D36: =IF(C36<0.30,"⚠️ Marge basse",IF(C36<0.35,"🟡 Limite",IF(C36<=0.42,"🎯 Optimal","🔵 Premium"))) | F36: 8 | G36: =CEILING(I25+3+0.1,1)-0.1 | H36: =IFERROR((G36*(1-$D$5)-$H$5)/(G36*(1-$D$5)),0) | I36: =IF(H36<0.30,"⚠️ Marge basse",IF(IFERROR((G36-B13)/B13,0)<0.1,"🚫 Cannibalisme",IF(H36<0.35,"🟡 Limite",IF(H36<=0.42,"🎯 Optimal","🔵 Premium")))) | K36: 8 | L36: =CEILING(N25+3+0.1,1)-0.1 | M36: =IFERROR((L36*(1-$D$5)-$J$5)/(L36*(1-$D$5)),0) | N36: =IF(M36<0.30,"⚠️ Marge basse",IF(IFERROR((L36-B13)/B13,0)<0.05,"🚫 Cannibalisme",IF(M36<0.35,"🟡 Limite",IF(M36<=0.42,"🎯 Optimal","🔵 Premium"))))
A37: 9 | B37: 42.9 | C37: =IFERROR((B37*(1-$D$5)-$F$5)/(B37*(1-$D$5)),0) | D37: =IF(C37<0.30,"⚠️ Marge basse",IF(C37<0.35,"🟡 Limite",IF(C37<=0.42,"🎯 Optimal","🔵 Premium"))) | F37: 9 | G37: =CEILING(I25+5+0.1,1)-0.1 | H37: =IFERROR((G37*(1-$D$5)-$H$5)/(G37*(1-$D$5)),0) | I37: =IF(H37<0.30,"⚠️ Marge basse",IF(IFERROR((G37-B13)/B13,0)<0.1,"🚫 Cannibalisme",IF(H37<0.35,"🟡 Limite",IF(H37<=0.42,"🎯 Optimal","🔵 Premium")))) | K37: 9 | L37: =CEILING(N25+5+0.1,1)-0.1 | M37: =IFERROR((L37*(1-$D$5)-$J$5)/(L37*(1-$D$5)),0) | N37: =IF(M37<0.30,"⚠️ Marge basse",IF(IFERROR((L37-B13)/B13,0)<0.05,"🚫 Cannibalisme",IF(M37<0.35,"🟡 Limite",IF(M37<=0.42,"🎯 Optimal","🔵 Premium"))))
A38: 10 | B38: 44.9 | C38: =IFERROR((B38*(1-$D$5)-$F$5)/(B38*(1-$D$5)),0) | D38: =IF(C38<0.30,"⚠️ Marge basse",IF(C38<0.35,"🟡 Limite",IF(C38<=0.42,"🎯 Optimal","🔵 Premium"))) | F38: 10 | G38: =CEILING(I25+7+0.1,1)-0.1 | H38: =IFERROR((G38*(1-$D$5)-$H$5)/(G38*(1-$D$5)),0) | I38: =IF(H38<0.30,"⚠️ Marge basse",IF(IFERROR((G38-B13)/B13,0)<0.1,"🚫 Cannibalisme",IF(H38<0.35,"🟡 Limite",IF(H38<=0.42,"🎯 Optimal","🔵 Premium")))) | K38: 10 | L38: =CEILING(N25+7+0.1,1)-0.1 | M38: =IFERROR((L38*(1-$D$5)-$J$5)/(L38*(1-$D$5)),0) | N38: =IF(M38<0.30,"⚠️ Marge basse",IF(IFERROR((L38-B13)/B13,0)<0.05,"🚫 Cannibalisme",IF(M38<0.35,"🟡 Limite",IF(M38<=0.42,"🎯 Optimal","🔵 Premium"))))

Sheet Pricing Dashboard A
A1: PRICING DYNAMIQUE · DASHBOARD GAMME
A2: Vue gamme en header · tables stackées en dessous
A4: HYPOTHÈSES PARTAGÉES
A5: TVA (compléments alim.) | B5: 0.055
A6: Remise client moyenne | B6: 0.18
A7: PR Concentrate (€ HT) | B7: 21
A8: PR Isolate (€ HT) | B8: 25
A9: PR Recovery (€ HT) | B9: 12.15
A11: ▌ DASHBOARD GAMME
B12: CONCENTRATE | D12: ISOLATE | F12: RECOVERY | H12: ÉCART GAMME
A13: Prix retenu | B13: =$D$34 | D13: =$D$55 | F13: =$D$76 | H13: =IFERROR(($D$55-$D$34)/$D$34,0)
A14: Marge nette | B14: =IFERROR(($D$34*(1-$B$6)-$B$7)/($D$34*(1-$B$6)),0) | D14: =IFERROR(($D$55*(1-$B$6)-$B$8)/($D$55*(1-$B$6)),0) | F14: =IFERROR(($D$76*(1-$B$6)-$B$9)/($D$76*(1-$B$6)),0) | H14: =IFERROR(($D$76-$D$34)/$D$34,0)
A15: Recommandation | B15: =IF(IFERROR(($D$34*(1-$B$6)-$B$7)/($D$34*(1-$B$6)),0)<0.30,"⚠️ Marge basse",IF(IFERROR(($D$34*(1-$B$6)-$B$7)/($D$34*(1-$B$6)),0)<0.35,"🟡 Limite",IF(IFERROR(($D$34*(1-$B$6)-$B$7)/($D$34*(1-$B$6)),0)<=0.42,"🎯 Optimal","🔵 Premium"))) | D15: =IF(IFERROR(($D$55*(1-$B$6)-$B$8)/($D$55*(1-$B$6)),0)<0.30,"⚠️ Marge basse",IF(IFERROR(($D$55*(1-$B$6)-$B$8)/($D$55*(1-$B$6)),0)<0.35,"🟡 Limite",IF(IFERROR(($D$55*(1-$B$6)-$B$8)/($D$55*(1-$B$6)),0)<=0.42,"🎯 Optimal","🔵 Premium"))) | F15: =IF(IFERROR(($D$76*(1-$B$6)-$B$9)/($D$76*(1-$B$6)),0)<0.30,"⚠️ Marge basse",IF(IFERROR(($D$76*(1-$B$6)-$B$9)/($D$76*(1-$B$6)),0)<0.35,"🟡 Limite",IF(IFERROR(($D$76*(1-$B$6)-$B$9)/($D$76*(1-$B$6)),0)<=0.42,"🎯 Optimal","🔵 Premium")))
A18: ▌ TABLEAU 1 — CONCENTRATE
A20: Benchmark | B20: Moy | C20: =AVERAGE('Synthèse prix'!H14,'Synthèse prix'!H15,'Synthèse prix'!H19,'Synthèse prix'!H20,'Synthèse prix'!H24,'Synthèse prix'!H25,'Synthèse prix'!H26,'Synthèse prix'!H31,'Synthèse prix'!H37,'Synthèse prix'!H50) | D20: Méd | E20: =MEDIAN('Synthèse prix'!H14,'Synthèse prix'!H15,'Synthèse prix'!H19,'Synthèse prix'!H20,'Synthèse prix'!H24,'Synthèse prix'!H25,'Synthèse prix'!H26,'Synthèse prix'!H31,'Synthèse prix'!H37,'Synthèse prix'!H50) | F20: Min | G20: =MIN('Synthèse prix'!H14,'Synthèse prix'!H15,'Synthèse prix'!H19,'Synthèse prix'!H20,'Synthèse prix'!H24,'Synthèse prix'!H25,'Synthèse prix'!H26,'Synthèse prix'!H31,'Synthèse prix'!H37,'Synthèse prix'!H50) | H20: Max | I20: =MAX('Synthèse prix'!H14,'Synthèse prix'!H15,'Synthèse prix'!H19,'Synthèse prix'!H20,'Synthèse prix'!H24,'Synthèse prix'!H25,'Synthèse prix'!H26,'Synthèse prix'!H31,'Synthèse prix'!H37,'Synthèse prix'!H50)
A22: # | B22: PP TTC | C22: PP HT | D22: PVM net | E22: Marge € | F22: % Marge | G22: vs Médiane | H22: — | I22: Flag
A23: 1 | B23: 29.9 | C23: =B23/(1+$B$5) | D23: =B23*(1-$B$6) | E23: =D23-$B$7 | F23: =IFERROR(E23/D23,0) | G23: =IFERROR((B23-E20)/E20,0) | H23: — | I23: =IF(F23<0.30,"⚠️ Marge basse",IF(F23<0.35,"🟡 Limite",IF(F23<=0.42,"🎯 Optimal","🔵 Premium")))
A24: 2 | B24: 31.9 | C24: =B24/(1+$B$5) | D24: =B24*(1-$B$6) | E24: =D24-$B$7 | F24: =IFERROR(E24/D24,0) | G24: =IFERROR((B24-E20)/E20,0) | H24: — | I24: =IF(F24<0.30,"⚠️ Marge basse",IF(F24<0.35,"🟡 Limite",IF(F24<=0.42,"🎯 Optimal","🔵 Premium")))
A25: 3 | B25: 33.9 | C25: =B25/(1+$B$5) | D25: =B25*(1-$B$6) | E25: =D25-$B$7 | F25: =IFERROR(E25/D25,0) | G25: =IFERROR((B25-E20)/E20,0) | H25: — | I25: =IF(F25<0.30,"⚠️ Marge basse",IF(F25<0.35,"🟡 Limite",IF(F25<=0.42,"🎯 Optimal","🔵 Premium")))
A26: 4 | B26: 34.9 | C26: =B26/(1+$B$5) | D26: =B26*(1-$B$6) | E26: =D26-$B$7 | F26: =IFERROR(E26/D26,0) | G26: =IFERROR((B26-E20)/E20,0) | H26: — | I26: =IF(F26<0.30,"⚠️ Marge basse",IF(F26<0.35,"🟡 Limite",IF(F26<=0.42,"🎯 Optimal","🔵 Premium")))
A27: 5 | B27: 36.9 | C27: =B27/(1+$B$5) | D27: =B27*(1-$B$6) | E27: =D27-$B$7 | F27: =IFERROR(E27/D27,0) | G27: =IFERROR((B27-E20)/E20,0) | H27: — | I27: =IF(F27<0.30,"⚠️ Marge basse",IF(F27<0.35,"🟡 Limite",IF(F27<=0.42,"🎯 Optimal","🔵 Premium")))
A28: 6 | B28: 37.9 | C28: =B28/(1+$B$5) | D28: =B28*(1-$B$6) | E28: =D28-$B$7 | F28: =IFERROR(E28/D28,0) | G28: =IFERROR((B28-E20)/E20,0) | H28: — | I28: =IF(F28<0.30,"⚠️ Marge basse",IF(F28<0.35,"🟡 Limite",IF(F28<=0.42,"🎯 Optimal","🔵 Premium")))
A29: 7 | B29: 39.9 | C29: =B29/(1+$B$5) | D29: =B29*(1-$B$6) | E29: =D29-$B$7 | F29: =IFERROR(E29/D29,0) | G29: =IFERROR((B29-E20)/E20,0) | H29: — | I29: =IF(F29<0.30,"⚠️ Marge basse",IF(F29<0.35,"🟡 Limite",IF(F29<=0.42,"🎯 Optimal","🔵 Premium")))
A30: 8 | B30: 41.9 | C30: =B30/(1+$B$5) | D30: =B30*(1-$B$6) | E30: =D30-$B$7 | F30: =IFERROR(E30/D30,0) | G30: =IFERROR((B30-E20)/E20,0) | H30: — | I30: =IF(F30<0.30,"⚠️ Marge basse",IF(F30<0.35,"🟡 Limite",IF(F30<=0.42,"🎯 Optimal","🔵 Premium")))
A31: 9 | B31: 42.9 | C31: =B31/(1+$B$5) | D31: =B31*(1-$B$6) | E31: =D31-$B$7 | F31: =IFERROR(E31/D31,0) | G31: =IFERROR((B31-E20)/E20,0) | H31: — | I31: =IF(F31<0.30,"⚠️ Marge basse",IF(F31<0.35,"🟡 Limite",IF(F31<=0.42,"🎯 Optimal","🔵 Premium")))
A32: 10 | B32: 44.9 | C32: =B32/(1+$B$5) | D32: =B32*(1-$B$6) | E32: =D32-$B$7 | F32: =IFERROR(E32/D32,0) | G32: =IFERROR((B32-E20)/E20,0) | H32: — | I32: =IF(F32<0.30,"⚠️ Marge basse",IF(F32<0.35,"🟡 Limite",IF(F32<=0.42,"🎯 Optimal","🔵 Premium")))
A34: 🎯 Option sélectionnée | B34: 5 | C34: → Prix retenu | D34: =INDEX($B$23:$B$32,$B34) | E34: Marge | F34: =INDEX($F$23:$F$32,$B34)
A36: ▌ TABLEAU 2 — ISOLATE (cascade auto)
A38: Plancher 38% | C38: Cible 40% | E38: Anti-cannib | G38: Marché méd. | I38: → PP OPT
B39: =CEILING($B$8/(1-0.38)/(1-$B$6)+0.1,1)-0.1 | D39: =CEILING($B$8/(1-0.40)/(1-$B$6)+0.1,1)-0.1 | F39: =CEILING($D$34*1.10+0.1,1)-0.1 | H39: =MEDIAN('Synthèse prix'!H7,'Synthèse prix'!H10,'Synthèse prix'!H11,'Synthèse prix'!H18,'Synthèse prix'!H21,'Synthèse prix'!H22,'Synthèse prix'!H23,'Synthèse prix'!H29,'Synthèse prix'!H30,'Synthèse prix'!H35,'Synthèse prix'!H41,'Synthèse prix'!H47) | I39: =MAX(B39,F39,MIN(D39,H39))
A41: Benchmark | B41: Moy | C41: =AVERAGE('Synthèse prix'!H7,'Synthèse prix'!H10,'Synthèse prix'!H11,'Synthèse prix'!H18,'Synthèse prix'!H21,'Synthèse prix'!H22,'Synthèse prix'!H23,'Synthèse prix'!H29,'Synthèse prix'!H30,'Synthèse prix'!H35,'Synthèse prix'!H41,'Synthèse prix'!H47) | D41: Méd | E41: =MEDIAN('Synthèse prix'!H7,'Synthèse prix'!H10,'Synthèse prix'!H11,'Synthèse prix'!H18,'Synthèse prix'!H21,'Synthèse prix'!H22,'Synthèse prix'!H23,'Synthèse prix'!H29,'Synthèse prix'!H30,'Synthèse prix'!H35,'Synthèse prix'!H41,'Synthèse prix'!H47) | F41: Min | G41: =MIN('Synthèse prix'!H7,'Synthèse prix'!H10,'Synthèse prix'!H11,'Synthèse prix'!H18,'Synthèse prix'!H21,'Synthèse prix'!H22,'Synthèse prix'!H23,'Synthèse prix'!H29,'Synthèse prix'!H30,'Synthèse prix'!H35,'Synthèse prix'!H41,'Synthèse prix'!H47) | H41: Max | I41: =MAX('Synthèse prix'!H7,'Synthèse prix'!H10,'Synthèse prix'!H11,'Synthèse prix'!H18,'Synthèse prix'!H21,'Synthèse prix'!H22,'Synthèse prix'!H23,'Synthèse prix'!H29,'Synthèse prix'!H30,'Synthèse prix'!H35,'Synthèse prix'!H41,'Synthèse prix'!H47)
A43: # | B43: PP TTC | C43: PP HT | D43: PVM net | E43: Marge € | F43: % Marge | G43: vs Médiane | H43: vs Concentrate | I43: Flag
A44: 1 | B44: =CEILING(I39-4+0.1,1)-0.1 | C44: =B44/(1+$B$5) | D44: =B44*(1-$B$6) | E44: =D44-$B$8 | F44: =IFERROR(E44/D44,0) | G44: =IFERROR((B44-E41)/E41,0) | H44: =IFERROR((B44-$D$34)/$D$34,0) | I44: =IF(F44<0.30,"⚠️ Marge basse",IF(IFERROR((B44-$D$34)/$D$34,0)<0.1,"🚫 Cannibalisme",IF(F44<0.35,"🟡 Limite",IF(F44<=0.42,"🎯 Optimal","🔵 Premium"))))
A45: 2 | B45: =CEILING(I39-3+0.1,1)-0.1 | C45: =B45/(1+$B$5) | D45: =B45*(1-$B$6) | E45: =D45-$B$8 | F45: =IFERROR(E45/D45,0) | G45: =IFERROR((B45-E41)/E41,0) | H45: =IFERROR((B45-$D$34)/$D$34,0) | I45: =IF(F45<0.30,"⚠️ Marge basse",IF(IFERROR((B45-$D$34)/$D$34,0)<0.1,"🚫 Cannibalisme",IF(F45<0.35,"🟡 Limite",IF(F45<=0.42,"🎯 Optimal","🔵 Premium"))))
A46: 3 | B46: =CEILING(I39-2+0.1,1)-0.1 | C46: =B46/(1+$B$5) | D46: =B46*(1-$B$6) | E46: =D46-$B$8 | F46: =IFERROR(E46/D46,0) | G46: =IFERROR((B46-E41)/E41,0) | H46: =IFERROR((B46-$D$34)/$D$34,0) | I46: =IF(F46<0.30,"⚠️ Marge basse",IF(IFERROR((B46-$D$34)/$D$34,0)<0.1,"🚫 Cannibalisme",IF(F46<0.35,"🟡 Limite",IF(F46<=0.42,"🎯 Optimal","🔵 Premium"))))
A47: 4 | B47: =CEILING(I39-1+0.1,1)-0.1 | C47: =B47/(1+$B$5) | D47: =B47*(1-$B$6) | E47: =D47-$B$8 | F47: =IFERROR(E47/D47,0) | G47: =IFERROR((B47-E41)/E41,0) | H47: =IFERROR((B47-$D$34)/$D$34,0) | I47: =IF(F47<0.30,"⚠️ Marge basse",IF(IFERROR((B47-$D$34)/$D$34,0)<0.1,"🚫 Cannibalisme",IF(F47<0.35,"🟡 Limite",IF(F47<=0.42,"🎯 Optimal","🔵 Premium"))))
A48: 5 | B48: =CEILING(I39+0.1,1)-0.1 | C48: =B48/(1+$B$5) | D48: =B48*(1-$B$6) | E48: =D48-$B$8 | F48: =IFERROR(E48/D48,0) | G48: =IFERROR((B48-E41)/E41,0) | H48: =IFERROR((B48-$D$34)/$D$34,0) | I48: =IF(F48<0.30,"⚠️ Marge basse",IF(IFERROR((B48-$D$34)/$D$34,0)<0.1,"🚫 Cannibalisme",IF(F48<0.35,"🟡 Limite",IF(F48<=0.42,"🎯 Optimal","🔵 Premium"))))
A49: 6 | B49: =CEILING(I39+1+0.1,1)-0.1 | C49: =B49/(1+$B$5) | D49: =B49*(1-$B$6) | E49: =D49-$B$8 | F49: =IFERROR(E49/D49,0) | G49: =IFERROR((B49-E41)/E41,0) | H49: =IFERROR((B49-$D$34)/$D$34,0) | I49: =IF(F49<0.30,"⚠️ Marge basse",IF(IFERROR((B49-$D$34)/$D$34,0)<0.1,"🚫 Cannibalisme",IF(F49<0.35,"🟡 Limite",IF(F49<=0.42,"🎯 Optimal","🔵 Premium"))))
A50: 7 | B50: =CEILING(I39+2+0.1,1)-0.1 | C50: =B50/(1+$B$5) | D50: =B50*(1-$B$6) | E50: =D50-$B$8 | F50: =IFERROR(E50/D50,0) | G50: =IFERROR((B50-E41)/E41,0) | H50: =IFERROR((B50-$D$34)/$D$34,0) | I50: =IF(F50<0.30,"⚠️ Marge basse",IF(IFERROR((B50-$D$34)/$D$34,0)<0.1,"🚫 Cannibalisme",IF(F50<0.35,"🟡 Limite",IF(F50<=0.42,"🎯 Optimal","🔵 Premium"))))
A51: 8 | B51: =CEILING(I39+3+0.1,1)-0.1 | C51: =B51/(1+$B$5) | D51: =B51*(1-$B$6) | E51: =D51-$B$8 | F51: =IFERROR(E51/D51,0) | G51: =IFERROR((B51-E41)/E41,0) | H51: =IFERROR((B51-$D$34)/$D$34,0) | I51: =IF(F51<0.30,"⚠️ Marge basse",IF(IFERROR((B51-$D$34)/$D$34,0)<0.1,"🚫 Cannibalisme",IF(F51<0.35,"🟡 Limite",IF(F51<=0.42,"🎯 Optimal","🔵 Premium"))))
A52: 9 | B52: =CEILING(I39+5+0.1,1)-0.1 | C52: =B52/(1+$B$5) | D52: =B52*(1-$B$6) | E52: =D52-$B$8 | F52: =IFERROR(E52/D52,0) | G52: =IFERROR((B52-E41)/E41,0) | H52: =IFERROR((B52-$D$34)/$D$34,0) | I52: =IF(F52<0.30,"⚠️ Marge basse",IF(IFERROR((B52-$D$34)/$D$34,0)<0.1,"🚫 Cannibalisme",IF(F52<0.35,"🟡 Limite",IF(F52<=0.42,"🎯 Optimal","🔵 Premium"))))
A53: 10 | B53: =CEILING(I39+7+0.1,1)-0.1 | C53: =B53/(1+$B$5) | D53: =B53*(1-$B$6) | E53: =D53-$B$8 | F53: =IFERROR(E53/D53,0) | G53: =IFERROR((B53-E41)/E41,0) | H53: =IFERROR((B53-$D$34)/$D$34,0) | I53: =IF(F53<0.30,"⚠️ Marge basse",IF(IFERROR((B53-$D$34)/$D$34,0)<0.1,"🚫 Cannibalisme",IF(F53<0.35,"🟡 Limite",IF(F53<=0.42,"🎯 Optimal","🔵 Premium"))))
A55: 🎯 Option sélectionnée | B55: 5 | C55: → Prix retenu | D55: =INDEX($B$44:$B$53,$B55) | E55: Marge | F55: =INDEX($F$44:$F$53,$B55)
A57: ▌ TABLEAU 3 — RECOVERY (cascade auto)
A59: Plancher 38% | C59: Plancher C+5% | E59: Plafond I−5% | G59: Marché réf | I59: → PP OPT
B60: =CEILING($B$9/(1-0.38)/(1-$B$6)+0.1,1)-0.1 | D60: =CEILING($D$34*1.05+0.1,1)-0.1 | F60: =CEILING($D$55*0.95+0.1,1)-0.1 | H60: ='Synthèse prix'!H5 | I60: =MAX(B60,D60,MIN(F60,H60))
A62: Benchmark | B62: Moy | C62: =AVERAGE('Synthèse prix'!H5,'Synthèse prix'!H6,'Synthèse prix'!H32) | D62: Méd | E62: =MEDIAN('Synthèse prix'!H5,'Synthèse prix'!H6,'Synthèse prix'!H32) | F62: Min | G62: =MIN('Synthèse prix'!H5,'Synthèse prix'!H6,'Synthèse prix'!H32) | H62: Max | I62: =MAX('Synthèse prix'!H5,'Synthèse prix'!H6,'Synthèse prix'!H32)
A64: # | B64: PP TTC | C64: PP HT | D64: PVM net | E64: Marge € | F64: % Marge | G64: vs Médiane | H64: vs Concentrate | I64: Flag
A65: 1 | B65: =CEILING(I60-4+0.1,1)-0.1 | C65: =B65/(1+$B$5) | D65: =B65*(1-$B$6) | E65: =D65-$B$9 | F65: =IFERROR(E65/D65,0) | G65: =IFERROR((B65-E62)/E62,0) | H65: =IFERROR((B65-$D$34)/$D$34,0) | I65: =IF(F65<0.30,"⚠️ Marge basse",IF(IFERROR((B65-$D$34)/$D$34,0)<0.05,"🚫 Cannibalisme",IF(F65<0.35,"🟡 Limite",IF(F65<=0.42,"🎯 Optimal","🔵 Premium"))))
A66: 2 | B66: =CEILING(I60-3+0.1,1)-0.1 | C66: =B66/(1+$B$5) | D66: =B66*(1-$B$6) | E66: =D66-$B$9 | F66: =IFERROR(E66/D66,0) | G66: =IFERROR((B66-E62)/E62,0) | H66: =IFERROR((B66-$D$34)/$D$34,0) | I66: =IF(F66<0.30,"⚠️ Marge basse",IF(IFERROR((B66-$D$34)/$D$34,0)<0.05,"🚫 Cannibalisme",IF(F66<0.35,"🟡 Limite",IF(F66<=0.42,"🎯 Optimal","🔵 Premium"))))
A67: 3 | B67: =CEILING(I60-2+0.1,1)-0.1 | C67: =B67/(1+$B$5) | D67: =B67*(1-$B$6) | E67: =D67-$B$9 | F67: =IFERROR(E67/D67,0) | G67: =IFERROR((B67-E62)/E62,0) | H67: =IFERROR((B67-$D$34)/$D$34,0) | I67: =IF(F67<0.30,"⚠️ Marge basse",IF(IFERROR((B67-$D$34)/$D$34,0)<0.05,"🚫 Cannibalisme",IF(F67<0.35,"🟡 Limite",IF(F67<=0.42,"🎯 Optimal","🔵 Premium"))))
A68: 4 | B68: =CEILING(I60-1+0.1,1)-0.1 | C68: =B68/(1+$B$5) | D68: =B68*(1-$B$6) | E68: =D68-$B$9 | F68: =IFERROR(E68/D68,0) | G68: =IFERROR((B68-E62)/E62,0) | H68: =IFERROR((B68-$D$34)/$D$34,0) | I68: =IF(F68<0.30,"⚠️ Marge basse",IF(IFERROR((B68-$D$34)/$D$34,0)<0.05,"🚫 Cannibalisme",IF(F68<0.35,"🟡 Limite",IF(F68<=0.42,"🎯 Optimal","🔵 Premium"))))
A69: 5 | B69: =CEILING(I60+0.1,1)-0.1 | C69: =B69/(1+$B$5) | D69: =B69*(1-$B$6) | E69: =D69-$B$9 | F69: =IFERROR(E69/D69,0) | G69: =IFERROR((B69-E62)/E62,0) | H69: =IFERROR((B69-$D$34)/$D$34,0) | I69: =IF(F69<0.30,"⚠️ Marge basse",IF(IFERROR((B69-$D$34)/$D$34,0)<0.05,"🚫 Cannibalisme",IF(F69<0.35,"🟡 Limite",IF(F69<=0.42,"🎯 Optimal","🔵 Premium"))))
A70: 6 | B70: =CEILING(I60+1+0.1,1)-0.1 | C70: =B70/(1+$B$5) | D70: =B70*(1-$B$6) | E70: =D70-$B$9 | F70: =IFERROR(E70/D70,0) | G70: =IFERROR((B70-E62)/E62,0) | H70: =IFERROR((B70-$D$34)/$D$34,0) | I70: =IF(F70<0.30,"⚠️ Marge basse",IF(IFERROR((B70-$D$34)/$D$34,0)<0.05,"🚫 Cannibalisme",IF(F70<0.35,"🟡 Limite",IF(F70<=0.42,"🎯 Optimal","🔵 Premium"))))
A71: 7 | B71: =CEILING(I60+2+0.1,1)-0.1 | C71: =B71/(1+$B$5) | D71: =B71*(1-$B$6) | E71: =D71-$B$9 | F71: =IFERROR(E71/D71,0) | G71: =IFERROR((B71-E62)/E62,0) | H71: =IFERROR((B71-$D$34)/$D$34,0) | I71: =IF(F71<0.30,"⚠️ Marge basse",IF(IFERROR((B71-$D$34)/$D$34,0)<0.05,"🚫 Cannibalisme",IF(F71<0.35,"🟡 Limite",IF(F71<=0.42,"🎯 Optimal","🔵 Premium"))))
A72: 8 | B72: =CEILING(I60+3+0.1,1)-0.1 | C72: =B72/(1+$B$5) | D72: =B72*(1-$B$6) | E72: =D72-$B$9 | F72: =IFERROR(E72/D72,0) | G72: =IFERROR((B72-E62)/E62,0) | H72: =IFERROR((B72-$D$34)/$D$34,0) | I72: =IF(F72<0.30,"⚠️ Marge basse",IF(IFERROR((B72-$D$34)/$D$34,0)<0.05,"🚫 Cannibalisme",IF(F72<0.35,"🟡 Limite",IF(F72<=0.42,"🎯 Optimal","🔵 Premium"))))
A73: 9 | B73: =CEILING(I60+5+0.1,1)-0.1 | C73: =B73/(1+$B$5) | D73: =B73*(1-$B$6) | E73: =D73-$B$9 | F73: =IFERROR(E73/D73,0) | G73: =IFERROR((B73-E62)/E62,0) | H73: =IFERROR((B73-$D$34)/$D$34,0) | I73: =IF(F73<0.30,"⚠️ Marge basse",IF(IFERROR((B73-$D$34)/$D$34,0)<0.05,"🚫 Cannibalisme",IF(F73<0.35,"🟡 Limite",IF(F73<=0.42,"🎯 Optimal","🔵 Premium"))))
A74: 10 | B74: =CEILING(I60+7+0.1,1)-0.1 | C74: =B74/(1+$B$5) | D74: =B74*(1-$B$6) | E74: =D74-$B$9 | F74: =IFERROR(E74/D74,0) | G74: =IFERROR((B74-E62)/E62,0) | H74: =IFERROR((B74-$D$34)/$D$34,0) | I74: =IF(F74<0.30,"⚠️ Marge basse",IF(IFERROR((B74-$D$34)/$D$34,0)<0.05,"🚫 Cannibalisme",IF(F74<0.35,"🟡 Limite",IF(F74<=0.42,"🎯 Optimal","🔵 Premium"))))
A76: 🎯 Option sélectionnée | B76: 5 | C76: → Prix retenu | D76: =INDEX($B$65:$B$74,$B76) | E76: Marge | F76: =INDEX($F$65:$F$74,$B76)

Sheet Benchmark détaillé
A1: MARQUE / PRODUIT | B1: IMPULSE | C1: IMPULSE | D1: IMPULSE | E1: IMPULSE | F1: IMPULSE | G1: NUTRIPURE | H1: NUTRIPURE | I1: NUTRIPURE | J1: NUTRIMUSCLE | K1: NUTRIMUSCLE | L1: NUTRIMUSCLE | M1: NUTRIMUSCLE | N1: NUTRIMUSCLE | O1: NUTRIMUSCLE | P1: NUTRIMUSCLE | Q1: NUTRIMUSCLE | R1: NUTRI&CO | S1: NUTRI&CO | T1: AQEELAB | U1: ERIC FAVRE | V1: ERIC FAVRE | W1: ERIC FAVRE | X1: ERIC FAVRE | Y1: ERIC FAVRE | Z1: ERIC FAVRE | AA1: ERIC FAVRE | AB1: ERIC FAVRE | AC1: EAFIT | AD1: EAFIT | AE1: EAFIT | AF1: EAFIT | AG1: EAFIT | AH1: EAFIT | AI1: BULK | AJ1: BULK | AK1: BULK | AL1: BULK | AM1: BULK | AN1: BULK | AO1: MYPROTEIN | AP1: MYPROTEIN | AQ1: MYPROTEIN | AR1: MYPROTEIN | AS1: MYPROTEIN | AT1: MYPROTEIN | AU1: BIOTECHUSA | AV1: BIOTECHUSA | AW1: BIOTECHUSA | AX1: BIOTECHUSA | AY1: BIOTECHUSA
A2: RÉFÉRENCE | B2: Whey Isolate (750g chocolat) | C2: Whey Isolate (750g vanille) | D2: Whey Isolate (750g nature) | E2: Whey Recovery (525g chocolat) | F2: Whey Recovery (525g vanille) | G2: Whey Isolat Native 750g (750g chocolat) | H2: Whey Isolat Native 2kg (2kg chocolat) | I2: Whey Isolat Native 4kg (4kg chocolat) | J2: Whey Native Isolate 500g (500g chocolat) | K2: Whey Native Isolate (1kg chocolat) | L2: Whey Native Isolate 2,25kg (2.25kg chocolat) | M2: Whey Native Isolate 4kg (4kg chocolat) | N2: Whey Native Concentrat 500g (500g chocolat) | O2: Whey Native Concentrat (1kg chocolat) | P2: Whey Native Concentrat 2,25kg (2.25kg chocolat) | Q2: Whey Native Concentrat 4kg (4kg chocolat) | R2: Whey Isolate Native 900g (900g chocolat) | S2: Whey Concentrée Native 900g (900g chocolat) | T2: Whey Native 810g (810g chocolat) | U2: Iso Zero 100% Whey Protéine 500g (500g cookies cream) | V2: Iso Zero 100% Whey Protéine 1,5kg (1.5kg chocolat) | W2: Iso Zero 100% Whey Protéine 2kg (2kg chocotella) | X2: Whey Optimax Protein 500g (500g biscuit cookie) | Y2: Whey Optimax Protein 1,5kg (1.5kg chocolat) | Z2: Whey Zero Protéine 2kg (2kg chocolat) | AA2: Iso Fusion Protein Complex 750g (750g biscuit cookie) | AB2: Iso Fusion Protein Complex 2kg (2kg biscuit cookie) | AC2: Pure Isolate 750g (750g chocolat) | AD2: Pure Isolate Premium 750g (750g citron) | AE2: Pure Whey Protein 750g (750g double chocolat) | AF2: Mega Whey Creatine Complex 750g (750g chocolat) | AG2: Pure Whey Protein 850g (850g double chocolat) | AH2: Pure Whey Protein 2.2kg (2.2kg double chocolat) | AI2: Pure Whey Isolate 1kg (1kg chocolat) | AJ2: Pure Whey Isolate 2,5kg (2.5kg chocolat) | AK2: Pure Whey Protein 1kg (1kg chocolat) | AL2: Pure Whey Protein 2,5kg (2.5kg chocolat) | AM2: Pure Whey Protein 5kg (5kg chocolat) | AN2: Clear Whey Isolate 500g (500g fraise) | AO2: Impact Whey Isolate 1kg (1kg chocolat) | AP2: Impact Whey Isolate 2,5kg (2.5kg chocolat) | AQ2: Impact Whey Protein 1kg (1kg chocolat) | AR2: Impact Whey Protein 2,5kg (2.5kg chocolat) | AS2: Impact Whey Protein 5kg (Sans arôme) (5kg sans arôme) | AT2: Clear Whey Isolate 875g (875g fraise) | AU2: Iso Whey Zero 908g (908g chocolat) | AV2: Iso Whey Zero 1816g (1.816kg chocolat) | AW2: 100% Pure Whey 400g (400g chocolat) | AX2: 100% Pure Whey 1000g (1kg chocolat) | AY2: 100% Pure Whey 2000g (2kg chocolat)
A3: IDENTIFICATION
A4: Type de whey | B4: isolat natif (natif) | C4: isolat natif (natif) | D4: isolat natif (natif) | E4: concentrat fromagere | F4: concentrat fromagere | G4: isolat natif (natif) | H4: isolat natif (natif) | I4: isolat natif (natif) | J4: isolat natif (natif) | K4: isolat natif (natif) | L4: isolat natif (natif) | M4: isolat natif (natif) | N4: concentrat natif (natif) | O4: concentrat natif (natif) | P4: concentrat natif (natif) | Q4: concentrat natif (natif) | R4: isolat natif (natif) | S4: concentrat natif (natif) | T4: concentrat natif (natif) | U4: isolat fromagere | V4: isolat fromagere | W4: isolat fromagere | X4: concentrat fromagere | Y4: concentrat fromagere | Z4: concentrat fromagere | AA4: mix concentrat isolat | AB4: mix concentrat isolat | AC4: isolat fromagere | AD4: isolat fromagere | AE4: concentrat fromagere | AF4: concentrat fromagere | AG4: concentrat fromagere | AH4: concentrat fromagere | AI4: isolat fromagere | AJ4: isolat fromagere | AK4: concentrat fromagere | AL4: concentrat fromagere | AM4: concentrat fromagere | AN4: clear hydrolysat | AO4: isolat fromagere | AP4: isolat fromagere | AQ4: concentrat fromagere | AR4: concentrat fromagere | AS4: concentrat fromagere | AT4: clear hydrolysat | AU4: isolat fromagere | AV4: isolat fromagere | AW4: concentrat fromagere | AX4: concentrat fromagere | AY4: concentrat fromagere
A5: Poids net (g) | B5: 750 | C5: 750 | D5: 750 | E5: 525 | F5: 525 | G5: 750 | H5: 2000 | I5: 4000 | J5: 500 | K5: 1000 | L5: 2250 | M5: 4000 | N5: 500 | O5: 1000 | P5: 2250 | Q5: 4000 | R5: 900 | S5: 900 | T5: 810 | U5: 500 | V5: 1500 | W5: 2000 | X5: 500 | Y5: 1500 | Z5: 2000 | AA5: 750 | AB5: 2000 | AC5: 750 | AD5: 750 | AE5: 750 | AF5: 750 | AG5: 850 | AH5: 2200 | AI5: 1000 | AJ5: 2500 | AK5: 1000 | AL5: 2500 | AM5: 5000 | AN5: 500 | AO5: 1000 | AP5: 2500 | AQ5: 1000 | AR5: 2500 | AS5: 5000 | AT5: 875 | AU5: 908 | AV5: 1816 | AW5: 400 | AX5: 1000 | AY5: 2000
A6: Arôme pivot | B6: chocolat | C6: vanille | D6: nature | E6: chocolat | F6: vanille | G6: chocolat | H6: chocolat | I6: chocolat | J6: chocolat | K6: chocolat | L6: chocolat | M6: chocolat | N6: chocolat | O6: chocolat | P6: chocolat | Q6: chocolat | R6: chocolat | S6: chocolat | T6: chocolat | U6: cookies cream | V6: chocolat | W6: chocotella | X6: biscuit cookie | Y6: chocolat | Z6: chocolat | AA6: biscuit cookie | AB6: biscuit cookie | AC6: chocolat | AD6: citron | AE6: double chocolat | AF6: chocolat | AG6: double chocolat | AH6: double chocolat | AI6: chocolat | AJ6: chocolat | AK6: chocolat | AL6: chocolat | AM6: chocolat | AN6: fraise | AO6: chocolat | AP6: chocolat | AQ6: chocolat | AR6: chocolat | AS6: sans arôme | AT6: fraise | AU6: chocolat | AV6: chocolat | AW6: chocolat | AX6: chocolat | AY6: chocolat
A7: Arômes disponibles (sample) | B7: chocolat, vanille, nature | C7: chocolat, vanille, nature | D7: chocolat, vanille, nature | E7: chocolat, vanille | F7: chocolat, vanille | G7: Chocolat, Vanille, Neutre, Noisette, Fraise | H7: Chocolat, Vanille, Neutre, Noisette, Fraise | I7: chocolat, vanille, neutre, noisette, fraise | J7: chocolat, nature, vanille, choco cookie, fraise, banane | K7: Chocolat, Vanille, Neutre, Fraise | L7: chocolat, nature, vanille, choco cookie, fraise, banane | M7: chocolat, nature, vanille, choco cookie, fraise, banane | N7: chocolat, vanille, nature | O7: Chocolat, Vanille, Neutre, Fraise | P7: chocolat, vanille, nature | Q7: chocolat, vanille, nature | R7: chocolat, vanille, sans arôme | S7: chocolat, vanille | T7: chocolat, vanille | U7: chocolat, vanille, cookies cream, chocotella, pistache | V7: chocolat, vanille, cookies cream, chocotella, pistache, framboisier, café latte | W7: chocolat, vanille, cookies cream, chocotella, pistache, framboisier, café latte | X7: chocolat, vanille, biscuit cookie | Y7: chocolat, vanille, biscuit cookie, chocotella | Z7: chocolat, vanille, cookies cream | AA7: biscuit cookie, vanille, chocotella | AB7: biscuit cookie, vanille, chocotella | AC7: chocolat, vanille, fruits rouges | AD7: citron | AE7: double chocolat, café, chocolat noisette, vanille intense, caramel, fraise | AF7: chocolat, vanille | AG7: double chocolat, café, chocolat noisette, vanille intense, caramel | AH7: double chocolat, vanille intense, fraise, myrtille, chocolat noisette | AI7: Choco, Vanille, Fraise, Neutre | AJ7: Choco, Vanille, Fraise, Neutre | AK7: +20 saveurs (Choco, Vanille, Fraise, Neutre...) | AL7: +20 saveurs | AM7: +20 saveurs | AN7: Fraise, Pastèque, Pêche, Ananas... | AO7: +40 saveurs | AP7: +40 saveurs | AQ7: +40 saveurs (Choco Brownie, Vanille, Fraise, Neutre...) | AR7: +40 saveurs | AS7: sans arôme | AT7: Fraise, Pastèque, Limonade, Tropical... | AU7: chocolat, chocolat blanc, vanille, caramel catalan, banane, black biscuit | AV7: chocolat, chocolat blanc, vanille, caramel catalan, banane | AW7: chocolat, vanille bourbon, fraise, noisettes, beurre de cacahuète au chocolat, cookies & cream | AX7: chocolat, vanille bourbon, fraise, noisettes, cookies & cream | AY7: chocolat, vanille bourbon, fraise, noisettes, cookies & cream
A8: Origine lait | B8: France | C8: France | D8: France | E8: UE | F8: UE | G8: France (pâturages) | H8: France (pâturages) | I8: France (pâturages) | J8: France (Lactalis) | K8: France (Lactalis) | L8: France (Lactalis) | M8: France (Lactalis) | N8: France (Lactalis) | O8: France (Lactalis) | P8: France (Lactalis) | Q8: France (Lactalis) | R8: France | S8: France (pâturages) | T8: France | AI8: UE | AJ8: UE | AK8: UE | AL8: UE | AM8: UE | AN8: UE | AO8: UE | AP8: UE | AQ8: UE (UK, IE, NL...) | AR8: UE | AS8: UE | AT8: UE
A9: Certifications | E9: Creapure®, Peptan® | F9: Creapure®, Peptan® | G9: EN 17444 | H9: EN 17444 | I9: EN 17444 | J9: Certifié, lait Lactalis FR | K9: Certifié, lait Lactalis FR | L9: Certifié, lait Lactalis FR | M9: Certifié, lait Lactalis FR | N9: Certifié, lait Lactalis FR | O9: Certifié, lait Lactalis FR | P9: Certifié, lait Lactalis FR | Q9: Certifié, lait Lactalis FR | T9: Testée labo indépendant | U9: Nutricontrole | V9: Nutricontrole | W9: Nutricontrole | X9: Nutricontrole | Y9: Nutricontrole | Z9: Nutricontrole | AA9: Nutricontrole | AB9: Nutricontrole | AC9: Marque N°1 en pharmacie | AD9: Marque N°1 en pharmacie | AE9: Marque N°1 en pharmacie | AF9: Marque N°1 en pharmacie | AG9: Marque N°1 en pharmacie | AH9: Marque N°1 en pharmacie | AI9: Informed Sport | AJ9: Informed Sport | AK9: Informed Sport | AL9: Informed Sport | AM9: Informed Sport | AN9: Informed Sport | AO9: Informed Choice | AP9: Informed Choice | AQ9: Informed Choice | AR9: Informed Choice | AS9: Informed Choice | AT9: Informed Choice
A10: Native / Fromagère | B10: native | C10: native | D10: native | E10: fromagere | F10: fromagere | G10: native | H10: native | I10: native | J10: native | K10: native | L10: native | M10: native | N10: native | O10: native | P10: native | Q10: native | R10: native | S10: native | T10: native | U10: fromagere | V10: fromagere | W10: fromagere | X10: fromagere | Y10: fromagere | Z10: fromagere | AA10: fromagere | AB10: fromagere | AC10: fromagere | AD10: fromagere | AE10: fromagere | AF10: fromagere | AG10: fromagere | AH10: fromagere | AI10: fromagere | AJ10: fromagere | AK10: fromagere | AL10: fromagere | AM10: fromagere | AN10: fromagere | AO10: fromagere | AP10: fromagere | AQ10: fromagere | AR10: fromagere | AS10: fromagere | AT10: fromagere | AU10: fromagere | AV10: fromagere | AW10: fromagere | AX10: fromagere | AY10: fromagere
A11: FORMULE & NUTRITION
A12: % protéines / 100g | B12: 85 | C12: 85 | D12: 85 | E12: 60 | F12: 60 | G12: 94 | H12: 94 | I12: 85 | J12: 87 | K12: 85 | L12: 87 | M12: 87 | N12: 80 | O12: 80 | P12: 80 | Q12: 80 | R12: 94 | S12: 75 | T12: 94 | U12: 83 | V12: 83 | W12: 83 | X12: 73 | Y12: 73 | Z12: 75 | AA12: 81 | AB12: 81 | AC12: 81 | AD12: 79 | AE12: 77 | AF12: 73 | AG12: 77 | AH12: 77 | AI12: 90 | AJ12: 90 | AK12: 82 | AL12: 82 | AM12: 82 | AN12: 72 | AO12: 90 | AP12: 90 | AQ12: 82 | AR12: 82 | AS12: 82 | AT12: 68 | AU12: 84 | AV12: 84 | AW12: 76 | AX12: 76 | AY12: 76
A13: Protéines / portion (g) | B13: 25.5 | C13: 25.5 | D13: 25.5 | E13: 21 | F13: 21 | G13: 25 | H13: 25 | I13: 25 | J13: 25 | K13: 24 | L13: 25 | M13: 25 | N13: 24 | O13: 24 | P13: 24 | Q13: 24 | R13: 28 | S13: 22.1 | T13: 28.2 | U13: 25 | V13: 25 | W13: 25 | X13: 22 | Y13: 22 | Z13: 22.5 | AA13: 24.4 | AB13: 24.4 | AC13: 25 | AD13: 24 | AE13: 31 | AF13: 44 | AG13: 31 | AH13: 31 | AI13: 26 | AJ13: 26 | AK13: 22 | AL13: 22 | AM13: 22 | AN13: 20 | AO13: 25 | AP13: 25 | AQ13: 23 | AR13: 23 | AS13: 23 | AT13: 20 | AU13: 21 | AV13: 21 | AW13: 21 | AX13: 21 | AY13: 21
A14: Taille portion (g) | B14: 30 | C14: 30 | D14: 30 | E14: 35 | F14: 35 | G14: 30 | H14: 30 | I14: 30 | J14: 30 | K14: 30 | L14: 30 | M14: 30 | N14: 30 | O14: 30 | P14: 30 | Q14: 30 | R14: 30 | S14: 30 | T14: 30 | U14: 30 | V14: 30 | W14: 30 | X14: 30 | Y14: 30 | Z14: 30 | AA14: 30 | AB14: 30 | AC14: 30 | AD14: 30 | AE14: 40 | AF14: 60 | AG14: 40 | AH14: 40 | AI14: 30 | AJ14: 30 | AK14: 30 | AL14: 30 | AM14: 30 | AN14: 30 | AO14: 25 | AP14: 25 | AQ14: 25 | AR14: 25 | AS14: 25 | AT14: 25 | AU14: 25 | AV14: 25 | AW14: 30 | AX14: 30 | AY14: 30
A15: Nb portions / format | B15: 25 | C15: 25 | D15: 25 | E15: 15 | F15: 15 | G15: 25 | H15: 66 | I15: 133 | J15: 16 | K15: 33 | L15: 75 | M15: 133 | N15: 16 | O15: 33 | P15: 75 | Q15: 133 | R15: 30 | S15: 30 | T15: 27 | U15: 16 | V15: 50 | W15: 66 | X15: 16 | Y15: 50 | Z15: 66 | AA15: 25 | AB15: 66 | AC15: 25 | AD15: 25 | AE15: 19 | AF15: 12 | AG15: 21 | AH15: 55 | AI15: 33 | AJ15: 83 | AK15: 33 | AL15: 83 | AM15: 166 | AN15: 16 | AO15: 40 | AP15: 100 | AQ15: 40 | AR15: 100 | AS15: 200 | AT15: 35 | AU15: 36 | AV15: 72 | AW15: 13 | AX15: 33 | AY15: 66
A16: BCAA / portion (g) | B16: 5.3 | C16: 5.3 | D16: 5.3 | G16: 5 | H16: 5 | I16: 5 | J16: 6 | K16: 6 | L16: 6 | M16: 6 | N16: 5 | O16: 5 | P16: 5 | Q16: 5 | R16: 6.9 | S16: 5.1 | T16: 6.6 | U16: 5.66 | V16: 5.66 | W16: 5.66 | X16: 3.74 | Y16: 3.74 | AA16: 4.1 | AB16: 4.1 | AC16: 5.5 | AD16: 5.2 | AE16: 7 | AF16: 10 | AG16: 7 | AH16: 7 | AI16: 5.5 | AJ16: 5.5 | AK16: 5 | AL16: 5 | AM16: 5 | AN16: 4 | AO16: 5.5 | AP16: 5.5 | AQ16: 4.5 | AR16: 4.5 | AS16: 4.5 | AT16: 4 | AU16: 4.35 | AV16: 4.35
A17: Glucides / portion (g) | B17: 1 | C17: 1 | D17: 1 | G17: 0.3 | H17: 0.3 | I17: 0.3 | J17: 1.5 | K17: 1.5 | L17: 1.5 | M17: 1.5 | N17: 3.5 | O17: 3.5 | P17: 3.5 | Q17: 3.5 | R17: 0.9 | S17: 4 | T17: 0.5 | U17: 0.5 | V17: 0.5 | W17: 0.5 | Z17: 3 | AA17: 1.4 | AB17: 1.4 | AC17: 1.4 | AD17: 0.5 | AE17: 4 | AF17: 4.3 | AG17: 4 | AH17: 4 | AI17: 1.5 | AJ17: 1.5 | AK17: 2 | AL17: 2 | AM17: 2 | AN17: 0.5 | AO17: 1 | AP17: 1 | AQ17: 2 | AR17: 2 | AS17: 2 | AT17: 0.5 | AU17: 0.6 | AV17: 0.6 | AW17: 1.4 | AX17: 1.4 | AY17: 1.4
A18: Lipides / portion (g) | B18: 0.5 | C18: 0.5 | D18: 0.5 | G18: 0.2 | H18: 0.2 | I18: 0.2 | J18: 0.8 | K18: 0.8 | L18: 0.8 | M18: 0.8 | N18: 1.5 | O18: 1.5 | P18: 1.5 | Q18: 1.5 | R18: 0.6 | S18: 0.4 | T18: 0.4 | U18: 0.4 | V18: 0.4 | W18: 0.4 | Z18: 1.4 | AA18: 1.6 | AB18: 1.6 | AC18: 0.5 | AD18: 0.3 | AE18: 1.7 | AF18: 2 | AG18: 1.7 | AH18: 1.7 | AI18: 0.5 | AJ18: 0.5 | AK18: 1 | AL18: 1 | AM18: 1 | AN18: 0.1 | AO18: 0.5 | AP18: 0.5 | AQ18: 1 | AR18: 1 | AS18: 1 | AT18: 0.1 | AU18: 0.4 | AV18: 0.4 | AW18: 1.8 | AX18: 1.8 | AY18: 1.8
A19: Lactose | B19: faible | C19: faible | D19: faible | E19: present | F19: present | G19: tres_faible | H19: tres_faible | I19: tres_faible | J19: faible | K19: faible | L19: faible | M19: faible | N19: present | O19: present | P19: present | Q19: present | R19: tres_faible | S19: faible | T19: faible | U19: tres_faible | V19: tres_faible | W19: tres_faible | AA19: faible | AB19: faible | AC19: tres_faible | AD19: tres_faible | AF19: present | AI19: faible | AJ19: faible | AK19: present | AL19: present | AM19: present | AN19: tres_faible | AO19: faible | AP19: faible | AQ19: present | AR19: present | AS19: present | AT19: tres_faible | AU19: tres_faible | AV19: tres_faible
A20: PRIX — 3 COUCHES (nominal / current / marché médian)
A21: Prix nominal (site propre, barré) | B21: 39.9 | C21: 39.9 | D21: 37.9 | E21: 39.9 | F21: 39.9 | G21: 39.9 | H21: 104.9 | I21: 179.9 | J21: 31.95 | K21: 57.95 | L21: 116.95 | M21: 190.95 | N21: 19.95 | O21: 37.95 | P21: 80.95 | Q21: 131.95 | R21: 54.9 | S21: 39.9 | T21: 45.95 | U21: 33.9 | V21: 79.9 | W21: 94.9 | X21: 29.9 | Y21: 59.9 | Z21: 82.9 | AA21: 41.9 | AB21: 65.9 | AC21: 45.9 | AD21: 45.9 | AE21: 34.9 | AF21: 39.99 | AG21: 38.9 | AH21: 80.99 | AI21: 69.99 | AJ21: 159.99 | AK21: 37.99 | AL21: 84.99 | AM21: 159.99 | AN21: 31.49 | AO21: 57.99 | AP21: 124.99 | AQ21: 41.99 | AR21: 84.99 | AS21: 188.99 | AT21: 49.99 | AU21: 69.9 | AV21: 104.9 | AW21: 32.9 | AX21: 54.9 | AY21: 89.9
A22: Prix actuel (site propre, affiché) | B22: 39.9 | C22: 39.9 | D22: 37.9 | E22: 39.9 | F22: 39.9 | G22: 39.9 | H22: 104.9 | I22: 179.9 | J22: 31.95 | K22: 57.95 | L22: 116.95 | M22: 190.95 | N22: 19.95 | O22: 37.95 | P22: 80.95 | Q22: 131.95 | R22: 54.9 | S22: 39.9 | T22: 45.95 | U22: 33.9 | V22: 79.9 | W22: 94.9 | X22: 29.9 | Y22: 59.9 | Z22: 82.9 | AA22: 41.9 | AB22: 65.9 | AC22: 45.9 | AD22: 45.9 | AE22: 34.9 | AF22: 39.99 | AG22: 38.9 | AH22: 80.99 | AI22: 44.99 | AJ22: 99.99 | AK22: 27.99 | AL22: 64.99 | AM22: 129.99 | AN22: 25.99 | AO22: 57.99 | AP22: 124.99 | AQ22: 17.99 | AR22: 40.99 | AS22: 91.1 | AT22: 49.99 | AU22: 69.9 | AV22: 104.9 | AW22: 32.9 | AX22: 54.9 | AY22: 89.9
A23: Prix médian marché (idealo/ledenicheur) | AK23: 23.99 | AN23: 22.25 | AO23: 56.4 | AQ23: 34.99 | AR23: 56.4 | AS23: 188.99 | AX23: 27.02
A24: Écart nominal → actuel (%) | B24: =IFERROR((B21-B22)/B21*100,"") | C24: =IFERROR((C21-C22)/C21*100,"") | D24: =IFERROR((D21-D22)/D21*100,"") | E24: =IFERROR((E21-E22)/E21*100,"") | F24: =IFERROR((F21-F22)/F21*100,"") | G24: =IFERROR((G21-G22)/G21*100,"") | H24: =IFERROR((H21-H22)/H21*100,"") | I24: =IFERROR((I21-I22)/I21*100,"") | ... AY24: =IFERROR((AY21-AY22)/AY21*100,"")
A25: Écart actuel → marché (%) | B25: =IFERROR((B22-B23)/B22*100,"") | C25: =IFERROR((C22-C23)/C22*100,"") | D25: =IFERROR((D22-D23)/D22*100,"") | E25: =IFERROR((E22-E23)/E22*100,"") | F25: =IFERROR((F22-F23)/F22*100,"") | G25: =IFERROR((G22-G23)/G22*100,"") | H25: =IFERROR((H22-H23)/H22*100,"") | I25: =IFERROR((I22-I23)/I22*100,"") | ... AY25: =IFERROR((AY22-AY23)/AY22*100,"")
A26: PRIX DÉRIVÉS (base = prix actuel site propre)
A27: Prix actuel / kg (€) | B27: =IFERROR(B22/(B5/1000),"") | C27: =IFERROR(C22/(C5/1000),"") | D27: =IFERROR(D22/(D5/1000),"") | E27: =IFERROR(E22/(E5/1000),"") | F27: =IFERROR(F22/(F5/1000),"") | G27: =IFERROR(G22/(G5/1000),"") | H27: =IFERROR(H22/(H5/1000),"") | I27: =IFERROR(I22/(I5/1000),"") | ... AY27: =IFERROR(AY22/(AY5/1000),"")
A28: Prix actuel / portion (€) | B28: =IFERROR(B22/B15,"") | C28: =IFERROR(C22/C15,"") | D28: =IFERROR(D22/D15,"") | E28: =IFERROR(E22/E15,"") | F28: =IFERROR(F22/F15,"") | G28: =IFERROR(G22/G15,"") | H28: =IFERROR(H22/H15,"") | I28: =IFERROR(I22/I15,"") | ... AY28: =IFERROR(AY22/AY15,"")
A29: Prix actuel / g de protéine (€) | B29: =IFERROR(B22/(B15*B13),"") | C29: =IFERROR(C22/(C15*C13),"") | D29: =IFERROR(D22/(D15*D13),"") | E29: =IFERROR(E22/(E15*E13),"") | F29: =IFERROR(F22/(F15*F13),"") | G29: =IFERROR(G22/(G15*G13),"") | H29: =IFERROR(H22/(H15*H13),"") | I29: =IFERROR(I22/(I15*I13),"") | ... AY29: =IFERROR(AY22/(AY15*AY13),"")
A30: Prix marché / g de protéine (€) | B30: =IFERROR(B23/(B15*B13),"") | C30: =IFERROR(C23/(C15*C13),"") | D30: =IFERROR(D23/(D15*D13),"") | E30: =IFERROR(E23/(E15*E13),"") | F30: =IFERROR(F23/(F15*F13),"") | G30: =IFERROR(G23/(G15*G13),"") | H30: =IFERROR(H23/(H15*H13),"") | I30: =IFERROR(I23/(I15*I13),"") | ... AY30: =IFERROR(AY23/(AY15*AY13),"")
A31: Prix abonnement (€ TTC) | T31: 36.76
A32: Remise abo (%) | T32: 20
A33: PRIX EFFECTIF (avec code influenceur appliqué sur prix actuel)
A34: Remise bas fourchette (%) | B34: =IFERROR(VLOOKUP(B1,'Discounts par marque'!$A:$G,3,FALSE),0) | C34: =IFERROR(VLOOKUP(C1,'Discounts par marque'!$A:$G,3,FALSE),0) | D34: =IFERROR(VLOOKUP(D1,'Discounts par marque'!$A:$G,3,FALSE),0) | E34: =IFERROR(VLOOKUP(E1,'Discounts par marque'!$A:$G,3,FALSE),0) | F34: =IFERROR(VLOOKUP(F1,'Discounts par marque'!$A:$G,3,FALSE),0) | G34: =IFERROR(VLOOKUP(G1,'Discounts par marque'!$A:$G,3,FALSE),0) | H34: =IFERROR(VLOOKUP(H1,'Discounts par marque'!$A:$G,3,FALSE),0) | I34: =IFERROR(VLOOKUP(I1,'Discounts par marque'!$A:$G,3,FALSE),0) | ... AY34: =IFERROR(VLOOKUP(AY1,'Discounts par marque'!$A:$G,3,FALSE),0)
A35: Remise client standard (%) | B35: =IFERROR(VLOOKUP(B1,'Discounts par marque'!$A:$G,4,FALSE),0) | C35: =IFERROR(VLOOKUP(C1,'Discounts par marque'!$A:$G,4,FALSE),0) | D35: =IFERROR(VLOOKUP(D1,'Discounts par marque'!$A:$G,4,FALSE),0) | E35: =IFERROR(VLOOKUP(E1,'Discounts par marque'!$A:$G,4,FALSE),0) | F35: =IFERROR(VLOOKUP(F1,'Discounts par marque'!$A:$G,4,FALSE),0) | G35: =IFERROR(VLOOKUP(G1,'Discounts par marque'!$A:$G,4,FALSE),0) | H35: =IFERROR(VLOOKUP(H1,'Discounts par marque'!$A:$G,4,FALSE),0) | I35: =IFERROR(VLOOKUP(I1,'Discounts par marque'!$A:$G,4,FALSE),0) | ... AY35: =IFERROR(VLOOKUP(AY1,'Discounts par marque'!$A:$G,4,FALSE),0)
A36: Remise client averti (%) | B36: =IFERROR(VLOOKUP(B1,'Discounts par marque'!$A:$G,5,FALSE),0) | C36: =IFERROR(VLOOKUP(C1,'Discounts par marque'!$A:$G,5,FALSE),0) | D36: =IFERROR(VLOOKUP(D1,'Discounts par marque'!$A:$G,5,FALSE),0) | E36: =IFERROR(VLOOKUP(E1,'Discounts par marque'!$A:$G,5,FALSE),0) | F36: =IFERROR(VLOOKUP(F1,'Discounts par marque'!$A:$G,5,FALSE),0) | G36: =IFERROR(VLOOKUP(G1,'Discounts par marque'!$A:$G,5,FALSE),0) | H36: =IFERROR(VLOOKUP(H1,'Discounts par marque'!$A:$G,5,FALSE),0) | I36: =IFERROR(VLOOKUP(I1,'Discounts par marque'!$A:$G,5,FALSE),0) | ... AY36: =IFERROR(VLOOKUP(AY1,'Discounts par marque'!$A:$G,5,FALSE),0)
A37: Remise plafond observé (%) | B37: =IFERROR(VLOOKUP(B1,'Discounts par marque'!$A:$G,6,FALSE),0) | C37: =IFERROR(VLOOKUP(C1,'Discounts par marque'!$A:$G,6,FALSE),0) | D37: =IFERROR(VLOOKUP(D1,'Discounts par marque'!$A:$G,6,FALSE),0) | E37: =IFERROR(VLOOKUP(E1,'Discounts par marque'!$A:$G,6,FALSE),0) | F37: =IFERROR(VLOOKUP(F1,'Discounts par marque'!$A:$G,6,FALSE),0) | G37: =IFERROR(VLOOKUP(G1,'Discounts par marque'!$A:$G,6,FALSE),0) | H37: =IFERROR(VLOOKUP(H1,'Discounts par marque'!$A:$G,6,FALSE),0) | I37: =IFERROR(VLOOKUP(I1,'Discounts par marque'!$A:$G,6,FALSE),0) | ... AY37: =IFERROR(VLOOKUP(AY1,'Discounts par marque'!$A:$G,6,FALSE),0)
A38: Prix client standard (€) | B38: =IFERROR(B22*(1-B35/100),"") | C38: =IFERROR(C22*(1-C35/100),"") | D38: =IFERROR(D22*(1-D35/100),"") | E38: =IFERROR(E22*(1-E35/100),"") | F38: =IFERROR(F22*(1-F35/100),"") | G38: =IFERROR(G22*(1-G35/100),"") | H38: =IFERROR(H22*(1-H35/100),"") | I38: =IFERROR(I22*(1-I35/100),"") | ... AY38: =IFERROR(AY22*(1-AY35/100),"")
A39: Prix client averti (€) | B39: =IFERROR(B22*(1-B36/100),"") | C39: =IFERROR(C22*(1-C36/100),"") | D39: =IFERROR(D22*(1-D36/100),"") | E39: =IFERROR(E22*(1-E36/100),"") | F39: =IFERROR(F22*(1-F36/100),"") | G39: =IFERROR(G22*(1-G36/100),"") | H39: =IFERROR(H22*(1-H36/100),"") | I39: =IFERROR(I22*(1-I36/100),"") | ... AY39: =IFERROR(AY22*(1-AY36/100),"")
A40: Prix plafond (€) | B40: =IFERROR(B22*(1-B37/100),"") | C40: =IFERROR(C22*(1-C37/100),"") | D40: =IFERROR(D22*(1-D37/100),"") | E40: =IFERROR(E22*(1-E37/100),"") | F40: =IFERROR(F22*(1-F37/100),"") | G40: =IFERROR(G22*(1-G37/100),"") | H40: =IFERROR(H22*(1-H37/100),"") | I40: =IFERROR(I22*(1-I37/100),"") | ... AY40: =IFERROR(AY22*(1-AY37/100),"")
A41: Prix client standard / kg (€) | B41: =IFERROR(B38/(B5/1000),"") | C41: =IFERROR(C38/(C5/1000),"") | D41: =IFERROR(D38/(D5/1000),"") | E41: =IFERROR(E38/(E5/1000),"") | F41: =IFERROR(F38/(F5/1000),"") | G41: =IFERROR(G38/(G5/1000),"") | H41: =IFERROR(H38/(H5/1000),"") | I41: =IFERROR(I38/(I5/1000),"") | ... AY41: =IFERROR(AY38/(AY5/1000),"")
A42: Prix client standard / g prot (€) | B42: =IFERROR(B38/(B15*B13),"") | C42: =IFERROR(C38/(C15*C13),"") | D42: =IFERROR(D38/(D15*D13),"") | E42: =IFERROR(E38/(E15*E13),"") | F42: =IFERROR(F38/(F15*F13),"") | G42: =IFERROR(G38/(G15*G13),"") | H42: =IFERROR(H38/(H15*H13),"") | I42: =IFERROR(I38/(I15*I13),"") | ... AY42: =IFERROR(AY38/(AY15*AY13),"")
A43: Prix client averti / g prot (€) | B43: =IFERROR(B39/(B15*B13),"") | C43: =IFERROR(C39/(C15*C13),"") | D43: =IFERROR(D39/(D15*D13),"") | E43: =IFERROR(E39/(E15*E13),"") | F43: =IFERROR(F39/(F15*F13),"") | G43: =IFERROR(G39/(G15*G13),"") | H43: =IFERROR(H39/(H15*H13),"") | I43: =IFERROR(I39/(I15*I13),"") | ... AY43: =IFERROR(AY39/(AY15*AY13),"")
A44: DISTRIBUTION & SOURCE
A45: Canaux de vente | B45: site_propre | C45: site_propre | D45: site_propre | E45: Site propre | F45: Site propre | G45: Site propre, Amazon | H45: Site propre, Amazon | I45: Site propre, Amazon | J45: Site propre, Amazon, revendeurs | K45: Site propre, Amazon, revendeurs | L45: Site propre, Amazon, revendeurs | M45: Site propre, Amazon, revendeurs | N45: Site propre, Amazon, revendeurs | O45: Site propre, Amazon, revendeurs | P45: Site propre, Amazon, revendeurs | Q45: Site propre, Amazon, revendeurs | R45: Site propre, Pharmacies, Amazon | S45: Site propre, Pharmacies, Amazon | T45: Site propre | U45: Site propre, Amazon | V45: Site propre, Amazon | W45: Site propre, Amazon | X45: Site propre, Amazon | Y45: Site propre, Amazon | Z45: Site propre, Amazon | AA45: Site propre, Amazon | AB45: Site propre, Amazon | AC45: Site propre, Amazon, Pharmacies | AD45: Site propre, Amazon, Pharmacies | AE45: Site propre, Amazon, Pharmacies | AF45: Site propre, Amazon, Pharmacies | AG45: Site propre, Amazon, Pharmacies | AH45: Site propre, Amazon, Pharmacies | AI45: Site propre, Amazon | AJ45: Site propre | AK45: Site propre, Amazon | AL45: Site propre | AM45: Site propre | AN45: Site propre | AO45: Site propre, Amazon | AP45: Site propre, Amazon | AQ45: Site propre, Amazon, revendeurs | AR45: Site propre | AS45: Site propre | AT45: Site propre, Amazon | AU45: Site propre, Amazon | AV45: Site propre, Amazon | AW45: Site propre, Amazon | AX45: Site propre, Amazon | AY45: Site propre, Amazon
A46: Source URL (principale) | B46: https://impulse-nutrition.fr/products/whey-isolate-saveur-chocolat | C46: https://impulse-nutrition.fr/products/whey-isolate-saveur-vanille | D46: https://impulse-nutrition.fr/products/whey-isolate-nature | E46: https://impulse-nutrition.fr/products/whey-recovery-saveur-chocolat | F46: https://impulse-nutrition.fr/products/whey-recovery-saveur-vanille | G46: https://www.nutripure.fr/produits/whey-isolat-native-chocolat | H46: https://www.nutripure.fr/fr/musculation/147-1115-whey-chocolat-isolate.html#/332-poids_poudre-seau_2kg | I46: https://www.nutripure.fr/fr/musculation/147-674-whey-chocolat-isolate.html#/47-poids_poudre-seau_4kg | J46: https://www.nutrimuscle.com/products/whey-native-isolate | K46: https://www.nutrimuscle.com/products/whey-isolat-native | L46: https://www.nutrimuscle.com/products/whey-native-isolate | M46: https://www.nutrimuscle.com/products/whey-native-isolate | N46: https://www.nutrimuscle.com/products/whey-native | O46: https://www.nutrimuscle.com/products/whey-concentree-native | P46: https://www.nutrimuscle.com/products/whey-native | Q46: https://www.nutrimuscle.com/products/whey-native | R46: https://nutriandco.com/fr/produits/whey-isolate-native | S46: https://nutriandco.com/fr/produits/whey-native | T46: https://www.aqeelab-nutrition.fr/products/whey-native-fabriquee-en-france-lait-francais | U46: https://www.ericfavre.com/fr_fr/proteines/iso-zero-100-whey-proteine-cookies-cream-500g-p-194-o-1216.htm | V46: https://www.ericfavre.com/fr_fr/proteines/iso-zero-100-whey-proteine-choco-intense-1-5kg-p-194-o-1200.htm | W46: https://www.ericfavre.com/fr_fr/proteines/iso-zero-100-whey-proteine-chocotella-2kg-p-194-o-155.htm | X46: https://www.ericfavre.com/fr_fr/proteines/whey-optimax-protein-biscuit-cookie-500g-p-622-o-1369.htm | Y46: https://www.ericfavre.com/fr_fr/proteines/whey-optimax-protein-chocolat-1-5kg-p-622-o-1370.htm | Z46: https://www.ericfavre.com/fr_fr/proteines/whey-zero-chocolat-2kg-p-517-o-1093.htm | AA46: https://www.ericfavre.com/fr_fr/proteines/iso-fusion-biscuit-cookie-750g-p-907-o-1924.htm | AB46: https://www.ericfavre.com/fr_fr/proteines/iso-fusion-biscuit-cookie-2kg-p-907-o-1925.htm | AC46: https://www.eafit.com/eafit-pure-isolate.html | AD46: https://www.eafit.com/eafit-pure-isolate-premium.html | AE46: https://www.eafit.com/eafit-pure-whey.html | AF46: https://www.eafit.com/eafit-megawhey.html | AG46: https://www.eafit.com/eafit-pure-whey.html | AH46: https://www.eafit.com/eafit-pure-whey.html | AI46: https://www.bulk.com/fr/pure-whey-isolate-90.html | AJ46: https://www.bulk.com/fr/pure-whey-isolate-90.html | AK46: https://www.bulk.com/fr/pure-whey-protein-1.html | AL46: https://www.bulk.com/fr/pure-whey-protein-1.html | AM46: https://www.bulk.com/fr/pure-whey-protein-1.html | AN46: https://www.bulk.com/fr/clear-whey-isolate.html | AO46: https://fr.myprotein.com/p/nutrition-sportive/impact-whey-isolate/10852482/ | AP46: https://fr.myprotein.com/p/nutrition-sportive/impact-whey-isolate-framboise-poche-2.5-kg/10530927/ | AQ46: https://fr.myprotein.com/p/nutrition-sportive/myprotein-impact-whey-protein-chocolate-1kg/11068071/ | AR46: https://fr.myprotein.com/p/nutrition-sportive/myprotein-impact-whey-protein-chocolate-nut-2.5kg/10530969/ | AS46: https://fr.myprotein.com/p/nutrition-sportive/impact-whey-protein/10530943/ | AT46: https://fr.myprotein.com/p/nutrition-sportive/clear-whey-isolate/12081395/ | AU46: https://shop.biotechusa.fr/products/iso-whey-zero-908-g | AV46: https://shop.biotechusa.fr/products/iso-whey-zero-poudre-de-proteine-isolat-1816-g | AW46: https://shop.biotechusa.fr/products/100-pure-whey-400-g | AX46: https://shop.biotechusa.fr/products/100-pure-whey-renouvele-1000-g | AY46: https://shop.biotechusa.fr/products/100-pure-whey-2000-g
A47: Date snapshot | B47: 2026-04-14 | C47: 2026-04-14 | D47: 2026-04-14 | E47: 2026-04-14 | F47: 2026-04-14 | G47: 2026-04-14 | H47: 2026-04-14 | I47: 2026-04-14 | J47: 2026-04-14 | K47: 2026-04-14 | L47: 2026-04-14 | M47: 2026-04-14 | N47: 2026-04-14 | O47: 2026-04-14 | P47: 2026-04-14 | Q47: 2026-04-14 | R47: 2026-04-14 | S47: 2026-04-14 | T47: 2026-04-14 | U47: 2026-04-14 | V47: 2026-04-14 | W47: 2026-04-14 | X47: 2026-04-14 | Y47: 2026-04-14 | Z47: 2026-04-14 | AA47: 2026-04-14 | AB47: 2026-04-14 | AC47: 2026-04-14 | AD47: 2026-04-14 | AE47: 2026-04-14 | AF47: 2026-04-14 | AG47: 2026-04-14 | AH47: 2026-04-14 | AI47: 2026-04-14 | AJ47: 2026-04-14 | AK47: 2026-04-14 | AL47: 2026-04-14 | AM47: 2026-04-14 | AN47: 2026-04-14 | AO47: 2026-04-14 | AP47: 2026-04-14 | AQ47: 2026-04-14 | AR47: 2026-04-14 | AS47: 2026-04-14 | AT47: 2026-04-14 | AU47: 2026-04-14 | AV47: 2026-04-14 | AW47: 2026-04-14 | AX47: 2026-04-14 | AY47: 2026-04-14
A48: Note gap catalogue/marché | E48: Blend recovery (concentrat whey + créatine Creapure 3g + collagène Peptan 5g + magnésium). Pas comparable 1-pour-1 aux whey pures — 60% protéines car le reste = additifs de récupération. | F48: Blend recovery (concentrat whey + créatine Creapure 3g + collagène Peptan 5g + magnésium). Pas comparable 1-pour-1 aux whey pures — 60% protéines car le reste = additifs de récupération. | G48: Prix marché = null (Nutripure vend uniquement sur site propre, pas de cross-retailers significatifs). Ancien 46€ sourcé via robshop.fr était un revendeur cher, pas un vrai marché médian. | H48: Confirmé via Playwright click sur variant radio Seau 2KG (id=332). Page nutripure.fr. Agent v2 avait mal lu '90€' (probablement le 'à partir de' affiché sur la page parent). | I48: Confirmé via Playwright click sur variant radio Seau 4KG (id=47). Prix réel 179,90€ (pas 159,90€ extrapolé). | K48: v1 avait 39.95€ (+45% correction) | O48: v1 avait 25.95€ (+46% correction) | AI48: Catalogue fictif majeur: 69.99€ barré vs 44.99€ réel (-36%) | AJ48: Catalogue fictif fort: 159.99€ vs 99.99€ réel (-37%) | AK48: Catalogue partiellement fictif: barré 37.99€ vs current 27.99€ vs marché 23.99€ | AL48: Catalogue fictif: 84.99€ barré vs 64.99€ réel (-23%) | AM48: Catalogue fictif: 159.99€ vs 129.99€ payé (-19%) | AN48: Catalogue 31.49€ barré vs 25.99€ payé (-17%). Marché 22.25€ | AO48: Isolate EXCLU de la promo -30% MyProtein. Prix current = prix nominal (pas de discount automatique). Revert de l'ancienne estimation ×0.7. | AP48: Confirmé via variant Framboise 2.5kg (10530927) : 124.99€ affiché sans strikethrough. Isolate exclu de la promo -30%. | AQ48: Prix actuel = 17.99€ sur fr.myprotein.com/.../11068071/ (scraped Playwright 2026-04-14). Promo site -30% + extra app ramène à 17.99 vs 41.99 nominal (soit -57%). Pattern MyProtein Whey Protein uniquement. | AR48: Prix scrapé via variant Chocolate Nut 2.5kg (10530969) : 84.99€ barré / 40.99€ actuel. Promo -52%. Playwright 2026-04-14. | AS48: 5kg n'existe qu'en 'Sans arôme' (chocolat inexistant). Current price = extrapolation du ratio 2.5kg (40.99/84.99=0.482) : 188.99 × 0.482 ≈ 91.10€. | AT48: Clear Whey exclu de la promo -30% (mention explicite). Format 875g max (pas de 1kg). Confirmé via scraping 12081395. | AW48: 8.2€/100g vs 5.5€/100g sur format 1kg (petit format plus cher) | AX48: GROS ÉCART : site marque 54.90€ vs idealo 27.02€ (-51%). Cross-retailers beaucoup moins cher. | AY48: Cohérent avec 1kg : site marque surcoté vs cross-retailers (~-40-50%)

Sheet Synthèse prix
A1: Marque | B1: Produit | C1: Type | D1: Natif/Fromagère | E1: Format (g) | F1: Nb portions | G1: Prot/portion (g) | H1: Prix nominal (€) | I1: Prix actuel (€) | J1: Prix marché (€) | K1: Gap nominal→actuel (%) | L1: Gap actuel→marché (%) | M1: Prix actuel /kg | N1: Prix actuel /g prot | O1: Prix abo (€) | P1: % abo | Q1: Remise client standard (%) | R1: Remise client averti (%) | S1: Prix client standard (€) | T1: Prix client standard /g prot | U1: Prix client averti (€) | V1: Prix client averti /g prot | W1: Source URL | X1: Gap note
A2: ='Benchmark détaillé'!B1 | B2: Whey Isolate | C2: ='Benchmark détaillé'!B4 | D2: ='Benchmark détaillé'!B10 | E2: ='Benchmark détaillé'!B5 | F2: ='Benchmark détaillé'!B15 | G2: ='Benchmark détaillé'!B13 | H2: ='Benchmark détaillé'!B21 | I2: ='Benchmark détaillé'!B22 | J2: ='Benchmark détaillé'!B23 | K2: =IFERROR((H2-I2)/H2*100,"") | L2: =IFERROR((I2-J2)/I2*100,"") | M2: =IFERROR(I2/(E2/1000),"") | N2: =IFERROR(I2/(F2*G2),"") | O2: ='Benchmark détaillé'!B31 | P2: ='Benchmark détaillé'!B32 | Q2: =IFERROR(VLOOKUP(A2,'Discounts par marque'!$A:$G,4,FALSE),0) | R2: =IFERROR(VLOOKUP(A2,'Discounts par marque'!$A:$G,5,FALSE),0) | S2: =IFERROR(I2*(1-Q2/100),"") | T2: =IFERROR(S2/(F2*G2),"") | U2: =IFERROR(I2*(1-R2/100),"") | V2: =IFERROR(U2/(F2*G2),"") | W2: https://impulse-nutrition.fr/products/whey-isolate-saveur-chocolat
A3: ='Benchmark détaillé'!C1 | B3: Whey Isolate | C3: ='Benchmark détaillé'!C4 | D3: ='Benchmark détaillé'!C10 | E3: ='Benchmark détaillé'!C5 | F3: ='Benchmark détaillé'!C15 | G3: ='Benchmark détaillé'!C13 | H3: ='Benchmark détaillé'!C21 | I3: ='Benchmark détaillé'!C22 | J3: ='Benchmark détaillé'!C23 | K3: =IFERROR((H3-I3)/H3*100,"") | L3: =IFERROR((I3-J3)/I3*100,"") | M3: =IFERROR(I3/(E3/1000),"") | N3: =IFERROR(I3/(F3*G3),"") | O3: ='Benchmark détaillé'!C31 | P3: ='Benchmark détaillé'!C32 | Q3: =IFERROR(VLOOKUP(A3,'Discounts par marque'!$A:$G,4,FALSE),0) | R3: =IFERROR(VLOOKUP(A3,'Discounts par marque'!$A:$G,5,FALSE),0) | S3: =IFERROR(I3*(1-Q3/100),"") | T3: =IFERROR(S3/(F3*G3),"") | U3: =IFERROR(I3*(1-R3/100),"") | V3: =IFERROR(U3/(F3*G3),"") | W3: https://impulse-nutrition.fr/products/whey-isolate-saveur-vanille
A4: ='Benchmark détaillé'!D1 | B4: Whey Isolate | C4: ='Benchmark détaillé'!D4 | D4: ='Benchmark détaillé'!D10 | E4: ='Benchmark détaillé'!D5 | F4: ='Benchmark détaillé'!D15 | G4: ='Benchmark détaillé'!D13 | H4: ='Benchmark détaillé'!D21 | I4: ='Benchmark détaillé'!D22 | J4: ='Benchmark détaillé'!D23 | K4: =IFERROR((H4-I4)/H4*100,"") | L4: =IFERROR((I4-J4)/I4*100,"") | M4: =IFERROR(I4/(E4/1000),"") | N4: =IFERROR(I4/(F4*G4),"") | O4: ='Benchmark détaillé'!D31 | P4: ='Benchmark détaillé'!D32 | Q4: =IFERROR(VLOOKUP(A4,'Discounts par marque'!$A:$G,4,FALSE),0) | R4: =IFERROR(VLOOKUP(A4,'Discounts par marque'!$A:$G,5,FALSE),0) | S4: =IFERROR(I4*(1-Q4/100),"") | T4: =IFERROR(S4/(F4*G4),"") | U4: =IFERROR(I4*(1-R4/100),"") | V4: =IFERROR(U4/(F4*G4),"") | W4: https://impulse-nutrition.fr/products/whey-isolate-nature
A5: ='Benchmark détaillé'!E1 | B5: Whey Recovery | C5: ='Benchmark détaillé'!E4 | D5: ='Benchmark détaillé'!E10 | E5: ='Benchmark détaillé'!E5 | F5: ='Benchmark détaillé'!E15 | G5: ='Benchmark détaillé'!E13 | H5: ='Benchmark détaillé'!E21 | I5: ='Benchmark détaillé'!E22 | J5: ='Benchmark détaillé'!E23 | K5: =IFERROR((H5-I5)/H5*100,"") | L5: =IFERROR((I5-J5)/I5*100,"") | M5: =IFERROR(I5/(E5/1000),"") | N5: =IFERROR(I5/(F5*G5),"") | O5: ='Benchmark détaillé'!E31 | P5: ='Benchmark détaillé'!E32 | Q5: =IFERROR(VLOOKUP(A5,'Discounts par marque'!$A:$G,4,FALSE),0) | R5: =IFERROR(VLOOKUP(A5,'Discounts par marque'!$A:$G,5,FALSE),0) | S5: =IFERROR(I5*(1-Q5/100),"") | T5: =IFERROR(S5/(F5*G5),"") | U5: =IFERROR(I5*(1-R5/100),"") | V5: =IFERROR(U5/(F5*G5),"") | W5: https://impulse-nutrition.fr/products/whey-recovery-saveur-chocolat | X5: Blend recovery (concentrat whey + créatine Creapure 3g + collagène Peptan 5g + magnésium). Pas comparable 1-pour-1 aux whey pures — 60% protéines car le reste = additifs de récupération.
A6: ='Benchmark détaillé'!F1 | B6: Whey Recovery | C6: ='Benchmark détaillé'!F4 | D6: ='Benchmark détaillé'!F10 | E6: ='Benchmark détaillé'!F5 | F6: ='Benchmark détaillé'!F15 | G6: ='Benchmark détaillé'!F13 | H6: ='Benchmark détaillé'!F21 | I6: ='Benchmark détaillé'!F22 | J6: ='Benchmark détaillé'!F23 | K6: =IFERROR((H6-I6)/H6*100,"") | L6: =IFERROR((I6-J6)/I6*100,"") | M6: =IFERROR(I6/(E6/1000),"") | N6: =IFERROR(I6/(F6*G6),"") | O6: ='Benchmark détaillé'!F31 | P6: ='Benchmark détaillé'!F32 | Q6: =IFERROR(VLOOKUP(A6,'Discounts par marque'!$A:$G,4,FALSE),0) | R6: =IFERROR(VLOOKUP(A6,'Discounts par marque'!$A:$G,5,FALSE),0) | S6: =IFERROR(I6*(1-Q6/100),"") | T6: =IFERROR(S6/(F6*G6),"") | U6: =IFERROR(I6*(1-R6/100),"") | V6: =IFERROR(U6/(F6*G6),"") | W6: https://impulse-nutrition.fr/products/whey-recovery-saveur-vanille | X6: Blend recovery (concentrat whey + créatine Creapure 3g + collagène Peptan 5g + magnésium). Pas comparable 1-pour-1 aux whey pures — 60% protéines car le reste = additifs de récupération.
A7: ='Benchmark détaillé'!G1 | B7: Whey Isolat Native 750g | C7: ='Benchmark détaillé'!G4 | D7: ='Benchmark détaillé'!G10 | E7: ='Benchmark détaillé'!G5 | F7: ='Benchmark détaillé'!G15 | G7: ='Benchmark détaillé'!G13 | H7: ='Benchmark détaillé'!G21 | I7: ='Benchmark détaillé'!G22 | J7: ='Benchmark détaillé'!G23 | K7: =IFERROR((H7-I7)/H7*100,"") | L7: =IFERROR((I7-J7)/I7*100,"") | M7: =IFERROR(I7/(E7/1000),"") | N7: =IFERROR(I7/(F7*G7),"") | O7: ='Benchmark détaillé'!G31 | P7: ='Benchmark détaillé'!G32 | Q7: =IFERROR(VLOOKUP(A7,'Discounts par marque'!$A:$G,4,FALSE),0) | R7: =IFERROR(VLOOKUP(A7,'Discounts par marque'!$A:$G,5,FALSE),0) | S7: =IFERROR(I7*(1-Q7/100),"") | T7: =IFERROR(S7/(F7*G7),"") | U7: =IFERROR(I7*(1-R7/100),"") | V7: =IFERROR(U7/(F7*G7),"") | W7: https://www.nutripure.fr/produits/whey-isolat-native-chocolat | X7: Prix marché = null (Nutripure vend uniquement sur site propre, pas de cross-retailers significatifs). Ancien 46€ sourcé via robshop.fr était un revendeur cher, pas un vrai marché médian.
A8: ='Benchmark détaillé'!H1 | B8: Whey Isolat Native 2kg | C8: ='Benchmark détaillé'!H4 | D8: ='Benchmark détaillé'!H10 | E8: ='Benchmark détaillé'!H5 | F8: ='Benchmark détaillé'!H15 | G8: ='Benchmark détaillé'!H13 | H8: ='Benchmark détaillé'!H21 | I8: ='Benchmark détaillé'!H22 | J8: ='Benchmark détaillé'!H23 | K8: =IFERROR((H8-I8)/H8*100,"") | L8: =IFERROR((I8-J8)/I8*100,"") | M8: =IFERROR(I8/(E8/1000),"") | N8: =IFERROR(I8/(F8*G8),"") | O8: ='Benchmark détaillé'!H31 | P8: ='Benchmark détaillé'!H32 | Q8: =IFERROR(VLOOKUP(A8,'Discounts par marque'!$A:$G,4,FALSE),0) | R8: =IFERROR(VLOOKUP(A8,'Discounts par marque'!$A:$G,5,FALSE),0) | S8: =IFERROR(I8*(1-Q8/100),"") | T8: =IFERROR(S8/(F8*G8),"") | U8: =IFERROR(I8*(1-R8/100),"") | V8: =IFERROR(U8/(F8*G8),"") | W8: https://www.nutripure.fr/fr/musculation/147-1115-whey-chocolat-isolate.html#/332-poids_poudre-seau_2kg | X8: Confirmé via Playwright click sur variant radio Seau 2KG (id=332). Page nutripure.fr. Agent v2 avait mal lu '90€' (probablement le 'à partir de' affiché sur la page parent).
A9: ='Benchmark détaillé'!I1 | B9: Whey Isolat Native 4kg | C9: ='Benchmark détaillé'!I4 | D9: ='Benchmark détaillé'!I10 | E9: ='Benchmark détaillé'!I5 | F9: ='Benchmark détaillé'!I15 | G9: ='Benchmark détaillé'!I13 | H9: ='Benchmark détaillé'!I21 | I9: ='Benchmark détaillé'!I22 | J9: ='Benchmark détaillé'!I23 | K9: =IFERROR((H9-I9)/H9*100,"") | L9: =IFERROR((I9-J9)/I9*100,"") | M9: =IFERROR(I9/(E9/1000),"") | N9: =IFERROR(I9/(F9*G9),"") | O9: ='Benchmark détaillé'!I31 | P9: ='Benchmark détaillé'!I32 | Q9: =IFERROR(VLOOKUP(A9,'Discounts par marque'!$A:$G,4,FALSE),0) | R9: =IFERROR(VLOOKUP(A9,'Discounts par marque'!$A:$G,5,FALSE),0) | S9: =IFERROR(I9*(1-Q9/100),"") | T9: =IFERROR(S9/(F9*G9),"") | U9: =IFERROR(I9*(1-R9/100),"") | V9: =IFERROR(U9/(F9*G9),"") | W9: https://www.nutripure.fr/fr/musculation/147-674-whey-chocolat-isolate.html#/47-poids_poudre-seau_4kg | X9: Confirmé via Playwright click sur variant radio Seau 4KG (id=47). Prix réel 179,90€ (pas 159,90€ extrapolé).
A10: ='Benchmark détaillé'!J1 | B10: Whey Native Isolate 500g | C10: ='Benchmark détaillé'!J4 | D10: ='Benchmark détaillé'!J10 | E10: ='Benchmark détaillé'!J5 | F10: ='Benchmark détaillé'!J15 | G10: ='Benchmark détaillé'!J13 | H10: ='Benchmark détaillé'!J21 | I10: ='Benchmark détaillé'!J22 | J10: ='Benchmark détaillé'!J23 | K10: =IFERROR((H10-I10)/H10*100,"") | L10: =IFERROR((I10-J10)/I10*100,"") | M10: =IFERROR(I10/(E10/1000),"") | N10: =IFERROR(I10/(F10*G10),"") | O10: ='Benchmark détaillé'!J31 | P10: ='Benchmark détaillé'!J32 | Q10: =IFERROR(VLOOKUP(A10,'Discounts par marque'!$A:$G,4,FALSE),0) | R10: =IFERROR(VLOOKUP(A10,'Discounts par marque'!$A:$G,5,FALSE),0) | S10: =IFERROR(I10*(1-Q10/100),"") | T10: =IFERROR(S10/(F10*G10),"") | U10: =IFERROR(I10*(1-R10/100),"") | V10: =IFERROR(U10/(F10*G10),"") | W10: https://www.nutrimuscle.com/products/whey-native-isolate
A11: ='Benchmark détaillé'!K1 | B11: Whey Native Isolate | C11: ='Benchmark détaillé'!K4 | D11: ='Benchmark détaillé'!K10 | E11: ='Benchmark détaillé'!K5 | F11: ='Benchmark détaillé'!K15 | G11: ='Benchmark détaillé'!K13 | H11: ='Benchmark détaillé'!K21 | I11: ='Benchmark détaillé'!K22 | J11: ='Benchmark détaillé'!K23 | K11: =IFERROR((H11-I11)/H11*100,"") | L11: =IFERROR((I11-J11)/I11*100,"") | M11: =IFERROR(I11/(E11/1000),"") | N11: =IFERROR(I11/(F11*G11),"") | O11: ='Benchmark détaillé'!K31 | P11: ='Benchmark détaillé'!K32 | Q11: =IFERROR(VLOOKUP(A11,'Discounts par marque'!$A:$G,4,FALSE),0) | R11: =IFERROR(VLOOKUP(A11,'Discounts par marque'!$A:$G,5,FALSE),0) | S11: =IFERROR(I11*(1-Q11/100),"") | T11: =IFERROR(S11/(F11*G11),"") | U11: =IFERROR(I11*(1-R11/100),"") | V11: =IFERROR(U11/(F11*G11),"") | W11: https://www.nutrimuscle.com/products/whey-isolat-native | X11: v1 avait 39.95€ (+45% correction)
A12: ='Benchmark détaillé'!L1 | B12: Whey Native Isolate 2,25kg | C12: ='Benchmark détaillé'!L4 | D12: ='Benchmark détaillé'!L10 | E12: ='Benchmark détaillé'!L5 | F12: ='Benchmark détaillé'!L15 | G12: ='Benchmark détaillé'!L13 | H12: ='Benchmark détaillé'!L21 | I12: ='Benchmark détaillé'!L22 | J12: ='Benchmark détaillé'!L23 | K12: =IFERROR((H12-I12)/H12*100,"") | L12: =IFERROR((I12-J12)/I12*100,"") | M12: =IFERROR(I12/(E12/1000),"") | N12: =IFERROR(I12/(F12*G12),"") | O12: ='Benchmark détaillé'!L31 | P12: ='Benchmark détaillé'!L32 | Q12: =IFERROR(VLOOKUP(A12,'Discounts par marque'!$A:$G,4,FALSE),0) | R12: =IFERROR(VLOOKUP(A12,'Discounts par marque'!$A:$G,5,FALSE),0) | S12: =IFERROR(I12*(1-Q12/100),"") | T12: =IFERROR(S12/(F12*G12),"") | U12: =IFERROR(I12*(1-R12/100),"") | V12: =IFERROR(U12/(F12*G12),"") | W12: https://www.nutrimuscle.com/products/whey-native-isolate
A13: ='Benchmark détaillé'!M1 | B13: Whey Native Isolate 4kg | C13: ='Benchmark détaillé'!M4 | D13: ='Benchmark détaillé'!M10 | E13: ='Benchmark détaillé'!M5 | F13: ='Benchmark détaillé'!M15 | G13: ='Benchmark détaillé'!M13 | H13: ='Benchmark détaillé'!M21 | I13: ='Benchmark détaillé'!M22 | J13: ='Benchmark détaillé'!M23 | K13: =IFERROR((H13-I13)/H13*100,"") | L13: =IFERROR((I13-J13)/I13*100,"") | M13: =IFERROR(I13/(E13/1000),"") | N13: =IFERROR(I13/(F13*G13),"") | O13: ='Benchmark détaillé'!M31 | P13: ='Benchmark détaillé'!M32 | Q13: =IFERROR(VLOOKUP(A13,'Discounts par marque'!$A:$G,4,FALSE),0) | R13: =IFERROR(VLOOKUP(A13,'Discounts par marque'!$A:$G,5,FALSE),0) | S13: =IFERROR(I13*(1-Q13/100),"") | T13: =IFERROR(S13/(F13*G13),"") | U13: =IFERROR(I13*(1-R13/100),"") | V13: =IFERROR(U13/(F13*G13),"") | W13: https://www.nutrimuscle.com/products/whey-native-isolate
A14: ='Benchmark détaillé'!N1 | B14: Whey Native Concentrat 500g | C14: ='Benchmark détaillé'!N4 | D14: ='Benchmark détaillé'!N10 | E14: ='Benchmark détaillé'!N5 | F14: ='Benchmark détaillé'!N15 | G14: ='Benchmark détaillé'!N13 | H14: ='Benchmark détaillé'!N21 | I14: ='Benchmark détaillé'!N22 | J14: ='Benchmark détaillé'!N23 | K14: =IFERROR((H14-I14)/H14*100,"") | L14: =IFERROR((I14-J14)/I14*100,"") | M14: =IFERROR(I14/(E14/1000),"") | N14: =IFERROR(I14/(F14*G14),"") | O14: ='Benchmark détaillé'!N31 | P14: ='Benchmark détaillé'!N32 | Q14: =IFERROR(VLOOKUP(A14,'Discounts par marque'!$A:$G,4,FALSE),0) | R14: =IFERROR(VLOOKUP(A14,'Discounts par marque'!$A:$G,5,FALSE),0) | S14: =IFERROR(I14*(1-Q14/100),"") | T14: =IFERROR(S14/(F14*G14),"") | U14: =IFERROR(I14*(1-R14/100),"") | V14: =IFERROR(U14/(F14*G14),"") | W14: https://www.nutrimuscle.com/products/whey-native
A15: ='Benchmark détaillé'!O1 | B15: Whey Native Concentrat | C15: ='Benchmark détaillé'!O4 | D15: ='Benchmark détaillé'!O10 | E15: ='Benchmark détaillé'!O5 | F15: ='Benchmark détaillé'!O15 | G15: ='Benchmark détaillé'!O13 | H15: ='Benchmark détaillé'!O21 | I15: ='Benchmark détaillé'!O22 | J15: ='Benchmark détaillé'!O23 | K15: =IFERROR((H15-I15)/H15*100,"") | L15: =IFERROR((I15-J15)/I15*100,"") | M15: =IFERROR(I15/(E15/1000),"") | N15: =IFERROR(I15/(F15*G15),"") | O15: ='Benchmark détaillé'!O31 | P15: ='Benchmark détaillé'!O32 | Q15: =IFERROR(VLOOKUP(A15,'Discounts par marque'!$A:$G,4,FALSE),0) | R15: =IFERROR(VLOOKUP(A15,'Discounts par marque'!$A:$G,5,FALSE),0) | S15: =IFERROR(I15*(1-Q15/100),"") | T15: =IFERROR(S15/(F15*G15),"") | U15: =IFERROR(I15*(1-R15/100),"") | V15: =IFERROR(U15/(F15*G15),"") | W15: https://www.nutrimuscle.com/products/whey-concentree-native | X15: v1 avait 25.95€ (+46% correction)
A16: ='Benchmark détaillé'!P1 | B16: Whey Native Concentrat 2,25kg | C16: ='Benchmark détaillé'!P4 | D16: ='Benchmark détaillé'!P10 | E16: ='Benchmark détaillé'!P5 | F16: ='Benchmark détaillé'!P15 | G16: ='Benchmark détaillé'!P13 | H16: ='Benchmark détaillé'!P21 | I16: ='Benchmark détaillé'!P22 | J16: ='Benchmark détaillé'!P23 | K16: =IFERROR((H16-I16)/H16*100,"") | L16: =IFERROR((I16-J16)/I16*100,"") | M16: =IFERROR(I16/(E16/1000),"") | N16: =IFERROR(I16/(F16*G16),"") | O16: ='Benchmark détaillé'!P31 | P16: ='Benchmark détaillé'!P32 | Q16: =IFERROR(VLOOKUP(A16,'Discounts par marque'!$A:$G,4,FALSE),0) | R16: =IFERROR(VLOOKUP(A16,'Discounts par marque'!$A:$G,5,FALSE),0) | S16: =IFERROR(I16*(1-Q16/100),"") | T16: =IFERROR(S16/(F16*G16),"") | U16: =IFERROR(I16*(1-R16/100),"") | V16: =IFERROR(U16/(F16*G16),"") | W16: https://www.nutrimuscle.com/products/whey-native
A17: ='Benchmark détaillé'!Q1 | B17: Whey Native Concentrat 4kg | C17: ='Benchmark détaillé'!Q4 | D17: ='Benchmark détaillé'!Q10 | E17: ='Benchmark détaillé'!Q5 | F17: ='Benchmark détaillé'!Q15 | G17: ='Benchmark détaillé'!Q13 | H17: ='Benchmark détaillé'!Q21 | I17: ='Benchmark détaillé'!Q22 | J17: ='Benchmark détaillé'!Q23 | K17: =IFERROR((H17-I17)/H17*100,"") | L17: =IFERROR((I17-J17)/I17*100,"") | M17: =IFERROR(I17/(E17/1000),"") | N17: =IFERROR(I17/(F17*G17),"") | O17: ='Benchmark détaillé'!Q31 | P17: ='Benchmark détaillé'!Q32 | Q17: =IFERROR(VLOOKUP(A17,'Discounts par marque'!$A:$G,4,FALSE),0) | R17: =IFERROR(VLOOKUP(A17,'Discounts par marque'!$A:$G,5,FALSE),0) | S17: =IFERROR(I17*(1-Q17/100),"") | T17: =IFERROR(S17/(F17*G17),"") | U17: =IFERROR(I17*(1-R17/100),"") | V17: =IFERROR(U17/(F17*G17),"") | W17: https://www.nutrimuscle.com/products/whey-native
A18: ='Benchmark détaillé'!R1 | B18: Whey Isolate Native 900g | C18: ='Benchmark détaillé'!R4 | D18: ='Benchmark détaillé'!R10 | E18: ='Benchmark détaillé'!R5 | F18: ='Benchmark détaillé'!R15 | G18: ='Benchmark détaillé'!R13 | H18: ='Benchmark détaillé'!R21 | I18: ='Benchmark détaillé'!R22 | J18: ='Benchmark détaillé'!R23 | K18: =IFERROR((H18-I18)/H18*100,"") | L18: =IFERROR((I18-J18)/I18*100,"") | M18: =IFERROR(I18/(E18/1000),"") | N18: =IFERROR(I18/(F18*G18),"") | O18: ='Benchmark détaillé'!R31 | P18: ='Benchmark détaillé'!R32 | Q18: =IFERROR(VLOOKUP(A18,'Discounts par marque'!$A:$G,4,FALSE),0) | R18: =IFERROR(VLOOKUP(A18,'Discounts par marque'!$A:$G,5,FALSE),0) | S18: =IFERROR(I18*(1-Q18/100),"") | T18: =IFERROR(S18/(F18*G18),"") | U18: =IFERROR(I18*(1-R18/100),"") | V18: =IFERROR(U18/(F18*G18),"") | W18: https://nutriandco.com/fr/produits/whey-isolate-native
A19: ='Benchmark détaillé'!S1 | B19: Whey Concentrée Native 900g | C19: ='Benchmark détaillé'!S4 | D19: ='Benchmark détaillé'!S10 | E19: ='Benchmark détaillé'!S5 | F19: ='Benchmark détaillé'!S15 | G19: ='Benchmark détaillé'!S13 | H19: ='Benchmark détaillé'!S21 | I19: ='Benchmark détaillé'!S22 | J19: ='Benchmark détaillé'!S23 | K19: =IFERROR((H19-I19)/H19*100,"") | L19: =IFERROR((I19-J19)/I19*100,"") | M19: =IFERROR(I19/(E19/1000),"") | N19: =IFERROR(I19/(F19*G19),"") | O19: ='Benchmark détaillé'!S31 | P19: ='Benchmark détaillé'!S32 | Q19: =IFERROR(VLOOKUP(A19,'Discounts par marque'!$A:$G,4,FALSE),0) | R19: =IFERROR(VLOOKUP(A19,'Discounts par marque'!$A:$G,5,FALSE),0) | S19: =IFERROR(I19*(1-Q19/100),"") | T19: =IFERROR(S19/(F19*G19),"") | U19: =IFERROR(I19*(1-R19/100),"") | V19: =IFERROR(U19/(F19*G19),"") | W19: https://nutriandco.com/fr/produits/whey-native
A20: ='Benchmark détaillé'!T1 | B20: Whey Native 810g | C20: ='Benchmark détaillé'!T4 | D20: ='Benchmark détaillé'!T10 | E20: ='Benchmark détaillé'!T5 | F20: ='Benchmark détaillé'!T15 | G20: ='Benchmark détaillé'!T13 | H20: ='Benchmark détaillé'!T21 | I20: ='Benchmark détaillé'!T22 | J20: ='Benchmark détaillé'!T23 | K20: =IFERROR((H20-I20)/H20*100,"") | L20: =IFERROR((I20-J20)/I20*100,"") | M20: =IFERROR(I20/(E20/1000),"") | N20: =IFERROR(I20/(F20*G20),"") | O20: ='Benchmark détaillé'!T31 | P20: ='Benchmark détaillé'!T32 | Q20: =IFERROR(VLOOKUP(A20,'Discounts par marque'!$A:$G,4,FALSE),0) | R20: =IFERROR(VLOOKUP(A20,'Discounts par marque'!$A:$G,5,FALSE),0) | S20: =IFERROR(I20*(1-Q20/100),"") | T20: =IFERROR(S20/(F20*G20),"") | U20: =IFERROR(I20*(1-R20/100),"") | V20: =IFERROR(U20/(F20*G20),"") | W20: https://www.aqeelab-nutrition.fr/products/whey-native-fabriquee-en-france-lait-francais
A21: ='Benchmark détaillé'!U1 | B21: Iso Zero 100% Whey Protéine 500g | C21: ='Benchmark détaillé'!U4 | D21: ='Benchmark détaillé'!U10 | E21: ='Benchmark détaillé'!U5 | F21: ='Benchmark détaillé'!U15 | G21: ='Benchmark détaillé'!U13 | H21: ='Benchmark détaillé'!U21 | I21: ='Benchmark détaillé'!U22 | J21: ='Benchmark détaillé'!U23 | K21: =IFERROR((H21-I21)/H21*100,"") | L21: =IFERROR((I21-J21)/I21*100,"") | M21: =IFERROR(I21/(E21/1000),"") | N21: =IFERROR(I21/(F21*G21),"") | O21: ='Benchmark détaillé'!U31 | P21: ='Benchmark détaillé'!U32 | Q21: =IFERROR(VLOOKUP(A21,'Discounts par marque'!$A:$G,4,FALSE),0) | R21: =IFERROR(VLOOKUP(A21,'Discounts par marque'!$A:$G,5,FALSE),0) | S21: =IFERROR(I21*(1-Q21/100),"") | T21: =IFERROR(S21/(F21*G21),"") | U21: =IFERROR(I21*(1-R21/100),"") | V21: =IFERROR(U21/(F21*G21),"") | W21: https://www.ericfavre.com/fr_fr/proteines/iso-zero-100-whey-proteine-cookies-cream-500g-p-194-o-1216.htm
A22: ='Benchmark détaillé'!V1 | B22: Iso Zero 100% Whey Protéine 1,5kg | C22: ='Benchmark détaillé'!V4 | D22: ='Benchmark détaillé'!V10 | E22: ='Benchmark détaillé'!V5 | F22: ='Benchmark détaillé'!V15 | G22: ='Benchmark détaillé'!V13 | H22: ='Benchmark détaillé'!V21 | I22: ='Benchmark détaillé'!V22 | J22: ='Benchmark détaillé'!V23 | K22: =IFERROR((H22-I22)/H22*100,"") | L22: =IFERROR((I22-J22)/I22*100,"") | M22: =IFERROR(I22/(E22/1000),"") | N22: =IFERROR(I22/(F22*G22),"") | O22: ='Benchmark détaillé'!V31 | P22: ='Benchmark détaillé'!V32 | Q22: =IFERROR(VLOOKUP(A22,'Discounts par marque'!$A:$G,4,FALSE),0) | R22: =IFERROR(VLOOKUP(A22,'Discounts par marque'!$A:$G,5,FALSE),0) | S22: =IFERROR(I22*(1-Q22/100),"") | T22: =IFERROR(S22/(F22*G22),"") | U22: =IFERROR(I22*(1-R22/100),"") | V22: =IFERROR(U22/(F22*G22),"") | W22: https://www.ericfavre.com/fr_fr/proteines/iso-zero-100-whey-proteine-choco-intense-1-5kg-p-194-o-1200.htm
A23: ='Benchmark détaillé'!W1 | B23: Iso Zero 100% Whey Protéine 2kg | C23: ='Benchmark détaillé'!W4 | D23: ='Benchmark détaillé'!W10 | E23: ='Benchmark détaillé'!W5 | F23: ='Benchmark détaillé'!W15 | G23: ='Benchmark détaillé'!W13 | H23: ='Benchmark détaillé'!W21 | I23: ='Benchmark détaillé'!W22 | J23: ='Benchmark détaillé'!W23 | K23: =IFERROR((H23-I23)/H23*100,"") | L23: =IFERROR((I23-J23)/I23*100,"") | M23: =IFERROR(I23/(E23/1000),"") | N23: =IFERROR(I23/(F23*G23),"") | O23: ='Benchmark détaillé'!W31 | P23: ='Benchmark détaillé'!W32 | Q23: =IFERROR(VLOOKUP(A23,'Discounts par marque'!$A:$G,4,FALSE),0) | R23: =IFERROR(VLOOKUP(A23,'Discounts par marque'!$A:$G,5,FALSE),0) | S23: =IFERROR(I23*(1-Q23/100),"") | T23: =IFERROR(S23/(F23*G23),"") | U23: =IFERROR(I23*(1-R23/100),"") | V23: =IFERROR(U23/(F23*G23),"") | W23: https://www.ericfavre.com/fr_fr/proteines/iso-zero-100-whey-proteine-chocotella-2kg-p-194-o-155.htm
A24: ='Benchmark détaillé'!X1 | B24: Whey Optimax Protein 500g | C24: ='Benchmark détaillé'!X4 | D24: ='Benchmark détaillé'!X10 | E24: ='Benchmark détaillé'!X5 | F24: ='Benchmark détaillé'!X15 | G24: ='Benchmark détaillé'!X13 | H24: ='Benchmark détaillé'!X21 | I24: ='Benchmark détaillé'!X22 | J24: ='Benchmark détaillé'!X23 | K24: =IFERROR((H24-I24)/H24*100,"") | L24: =IFERROR((I24-J24)/I24*100,"") | M24: =IFERROR(I24/(E24/1000),"") | N24: =IFERROR(I24/(F24*G24),"") | O24: ='Benchmark détaillé'!X31 | P24: ='Benchmark détaillé'!X32 | Q24: =IFERROR(VLOOKUP(A24,'Discounts par marque'!$A:$G,4,FALSE),0) | R24: =IFERROR(VLOOKUP(A24,'Discounts par marque'!$A:$G,5,FALSE),0) | S24: =IFERROR(I24*(1-Q24/100),"") | T24: =IFERROR(S24/(F24*G24),"") | U24: =IFERROR(I24*(1-R24/100),"") | V24: =IFERROR(U24/(F24*G24),"") | W24: https://www.ericfavre.com/fr_fr/proteines/whey-optimax-protein-biscuit-cookie-500g-p-622-o-1369.htm
A25: ='Benchmark détaillé'!Y1 | B25: Whey Optimax Protein 1,5kg | C25: ='Benchmark détaillé'!Y4 | D25: ='Benchmark détaillé'!Y10 | E25: ='Benchmark détaillé'!Y5 | F25: ='Benchmark détaillé'!Y15 | G25: ='Benchmark détaillé'!Y13 | H25: ='Benchmark détaillé'!Y21 | I25: ='Benchmark détaillé'!Y22 | J25: ='Benchmark détaillé'!Y23 | K25: =IFERROR((H25-I25)/H25*100,"") | L25: =IFERROR((I25-J25)/I25*100,"") | M25: =IFERROR(I25/(E25/1000),"") | N25: =IFERROR(I25/(F25*G25),"") | O25: ='Benchmark détaillé'!Y31 | P25: ='Benchmark détaillé'!Y32 | Q25: =IFERROR(VLOOKUP(A25,'Discounts par marque'!$A:$G,4,FALSE),0) | R25: =IFERROR(VLOOKUP(A25,'Discounts par marque'!$A:$G,5,FALSE),0) | S25: =IFERROR(I25*(1-Q25/100),"") | T25: =IFERROR(S25/(F25*G25),"") | U25: =IFERROR(I25*(1-R25/100),"") | V25: =IFERROR(U25/(F25*G25),"") | W25: https://www.ericfavre.com/fr_fr/proteines/whey-optimax-protein-chocolat-1-5kg-p-622-o-1370.htm
A26: ='Benchmark détaillé'!Z1 | B26: Whey Zero Protéine 2kg | C26: ='Benchmark détaillé'!Z4 | D26: ='Benchmark détaillé'!Z10 | E26: ='Benchmark détaillé'!Z5 | F26: ='Benchmark détaillé'!Z15 | G26: ='Benchmark détaillé'!Z13 | H26: ='Benchmark détaillé'!Z21 | I26: ='Benchmark détaillé'!Z22 | J26: ='Benchmark détaillé'!Z23 | K26: =IFERROR((H26-I26)/H26*100,"") | L26: =IFERROR((I26-J26)/I26*100,"") | M26: =IFERROR(I26/(E26/1000),"") | N26: =IFERROR(I26/(F26*G26),"") | O26: ='Benchmark détaillé'!Z31 | P26: ='Benchmark détaillé'!Z32 | Q26: =IFERROR(VLOOKUP(A26,'Discounts par marque'!$A:$G,4,FALSE),0) | R26: =IFERROR(VLOOKUP(A26,'Discounts par marque'!$A:$G,5,FALSE),0) | S26: =IFERROR(I26*(1-Q26/100),"") | T26: =IFERROR(S26/(F26*G26),"") | U26: =IFERROR(I26*(1-R26/100),"") | V26: =IFERROR(U26/(F26*G26),"") | W26: https://www.ericfavre.com/fr_fr/proteines/whey-zero-chocolat-2kg-p-517-o-1093.htm
A27: ='Benchmark détaillé'!AA1 | B27: Iso Fusion Protein Complex 750g | C27: ='Benchmark détaillé'!AA4 | D27: ='Benchmark détaillé'!AA10 | E27: ='Benchmark détaillé'!AA5 | F27: ='Benchmark détaillé'!AA15 | G27: ='Benchmark détaillé'!AA13 | H27: ='Benchmark détaillé'!AA21 | I27: ='Benchmark détaillé'!AA22 | J27: ='Benchmark détaillé'!AA23 | K27: =IFERROR((H27-I27)/H27*100,"") | L27: =IFERROR((I27-J27)/I27*100,"") | M27: =IFERROR(I27/(E27/1000),"") | N27: =IFERROR(I27/(F27*G27),"") | O27: ='Benchmark détaillé'!AA31 | P27: ='Benchmark détaillé'!AA32 | Q27: =IFERROR(VLOOKUP(A27,'Discounts par marque'!$A:$G,4,FALSE),0) | R27: =IFERROR(VLOOKUP(A27,'Discounts par marque'!$A:$G,5,FALSE),0) | S27: =IFERROR(I27*(1-Q27/100),"") | T27: =IFERROR(S27/(F27*G27),"") | U27: =IFERROR(I27*(1-R27/100),"") | V27: =IFERROR(U27/(F27*G27),"") | W27: https://www.ericfavre.com/fr_fr/proteines/iso-fusion-biscuit-cookie-750g-p-907-o-1924.htm
A28: ='Benchmark détaillé'!AB1 | B28: Iso Fusion Protein Complex 2kg | C28: ='Benchmark détaillé'!AB4 | D28: ='Benchmark détaillé'!AB10 | E28: ='Benchmark détaillé'!AB5 | F28: ='Benchmark détaillé'!AB15 | G28: ='Benchmark détaillé'!AB13 | H28: ='Benchmark détaillé'!AB21 | I28: ='Benchmark détaillé'!AB22 | J28: ='Benchmark détaillé'!AB23 | K28: =IFERROR((H28-I28)/H28*100,"") | L28: =IFERROR((I28-J28)/I28*100,"") | M28: =IFERROR(I28/(E28/1000),"") | N28: =IFERROR(I28/(F28*G28),"") | O28: ='Benchmark détaillé'!AB31 | P28: ='Benchmark détaillé'!AB32 | Q28: =IFERROR(VLOOKUP(A28,'Discounts par marque'!$A:$G,4,FALSE),0) | R28: =IFERROR(VLOOKUP(A28,'Discounts par marque'!$A:$G,5,FALSE),0) | S28: =IFERROR(I28*(1-Q28/100),"") | T28: =IFERROR(S28/(F28*G28),"") | U28: =IFERROR(I28*(1-R28/100),"") | V28: =IFERROR(U28/(F28*G28),"") | W28: https://www.ericfavre.com/fr_fr/proteines/iso-fusion-biscuit-cookie-2kg-p-907-o-1925.htm
A29: ='Benchmark détaillé'!AC1 | B29: Pure Isolate 750g | C29: ='Benchmark détaillé'!AC4 | D29: ='Benchmark détaillé'!AC10 | E29: ='Benchmark détaillé'!AC5 | F29: ='Benchmark détaillé'!AC15 | G29: ='Benchmark détaillé'!AC13 | H29: ='Benchmark détaillé'!AC21 | I29: ='Benchmark détaillé'!AC22 | J29: ='Benchmark détaillé'!AC23 | K29: =IFERROR((H29-I29)/H29*100,"") | L29: =IFERROR((I29-J29)/I29*100,"") | M29: =IFERROR(I29/(E29/1000),"") | N29: =IFERROR(I29/(F29*G29),"") | O29: ='Benchmark détaillé'!AC31 | P29: ='Benchmark détaillé'!AC32 | Q29: =IFERROR(VLOOKUP(A29,'Discounts par marque'!$A:$G,4,FALSE),0) | R29: =IFERROR(VLOOKUP(A29,'Discounts par marque'!$A:$G,5,FALSE),0) | S29: =IFERROR(I29*(1-Q29/100),"") | T29: =IFERROR(S29/(F29*G29),"") | U29: =IFERROR(I29*(1-R29/100),"") | V29: =IFERROR(U29/(F29*G29),"") | W29: https://www.eafit.com/eafit-pure-isolate.html
A30: ='Benchmark détaillé'!AD1 | B30: Pure Isolate Premium 750g | C30: ='Benchmark détaillé'!AD4 | D30: ='Benchmark détaillé'!AD10 | E30: ='Benchmark détaillé'!AD5 | F30: ='Benchmark détaillé'!AD15 | G30: ='Benchmark détaillé'!AD13 | H30: ='Benchmark détaillé'!AD21 | I30: ='Benchmark détaillé'!AD22 | J30: ='Benchmark détaillé'!AD23 | K30: =IFERROR((H30-I30)/H30*100,"") | L30: =IFERROR((I30-J30)/I30*100,"") | M30: =IFERROR(I30/(E30/1000),"") | N30: =IFERROR(I30/(F30*G30),"") | O30: ='Benchmark détaillé'!AD31 | P30: ='Benchmark détaillé'!AD32 | Q30: =IFERROR(VLOOKUP(A30,'Discounts par marque'!$A:$G,4,FALSE),0) | R30: =IFERROR(VLOOKUP(A30,'Discounts par marque'!$A:$G,5,FALSE),0) | S30: =IFERROR(I30*(1-Q30/100),"") | T30: =IFERROR(S30/(F30*G30),"") | U30: =IFERROR(I30*(1-R30/100),"") | V30: =IFERROR(U30/(F30*G30),"") | W30: https://www.eafit.com/eafit-pure-isolate-premium.html
A31: ='Benchmark détaillé'!AE1 | B31: Pure Whey Protein 750g | C31: ='Benchmark détaillé'!AE4 | D31: ='Benchmark détaillé'!AE10 | E31: ='Benchmark détaillé'!AE5 | F31: ='Benchmark détaillé'!AE15 | G31: ='Benchmark détaillé'!AE13 | H31: ='Benchmark détaillé'!AE21 | I31: ='Benchmark détaillé'!AE22 | J31: ='Benchmark détaillé'!AE23 | K31: =IFERROR((H31-I31)/H31*100,"") | L31: =IFERROR((I31-J31)/I31*100,"") | M31: =IFERROR(I31/(E31/1000),"") | N31: =IFERROR(I31/(F31*G31),"") | O31: ='Benchmark détaillé'!AE31 | P31: ='Benchmark détaillé'!AE32 | Q31: =IFERROR(VLOOKUP(A31,'Discounts par marque'!$A:$G,4,FALSE),0) | R31: =IFERROR(VLOOKUP(A31,'Discounts par marque'!$A:$G,5,FALSE),0) | S31: =IFERROR(I31*(1-Q31/100),"") | T31: =IFERROR(S31/(F31*G31),"") | U31: =IFERROR(I31*(1-R31/100),"") | V31: =IFERROR(U31/(F31*G31),"") | W31: https://www.eafit.com/eafit-pure-whey.html
A32: ='Benchmark détaillé'!AF1 | B32: Mega Whey Creatine Complex 750g | C32: ='Benchmark détaillé'!AF4 | D32: ='Benchmark détaillé'!AF10 | E32: ='Benchmark détaillé'!AF5 | F32: ='Benchmark détaillé'!AF15 | G32: ='Benchmark détaillé'!AF13 | H32: ='Benchmark détaillé'!AF21 | I32: ='Benchmark détaillé'!AF22 | J32: ='Benchmark détaillé'!AF23 | K32: =IFERROR((H32-I32)/H32*100,"") | L32: =IFERROR((I32-J32)/I32*100,"") | M32: =IFERROR(I32/(E32/1000),"") | N32: =IFERROR(I32/(F32*G32),"") | O32: ='Benchmark détaillé'!AF31 | P32: ='Benchmark détaillé'!AF32 | Q32: =IFERROR(VLOOKUP(A32,'Discounts par marque'!$A:$G,4,FALSE),0) | R32: =IFERROR(VLOOKUP(A32,'Discounts par marque'!$A:$G,5,FALSE),0) | S32: =IFERROR(I32*(1-Q32/100),"") | T32: =IFERROR(S32/(F32*G32),"") | U32: =IFERROR(I32*(1-R32/100),"") | V32: =IFERROR(U32/(F32*G32),"") | W32: https://www.eafit.com/eafit-megawhey.html
A33: ='Benchmark détaillé'!AG1 | B33: Pure Whey Protein 850g | C33: ='Benchmark détaillé'!AG4 | D33: ='Benchmark détaillé'!AG10 | E33: ='Benchmark détaillé'!AG5 | F33: ='Benchmark détaillé'!AG15 | G33: ='Benchmark détaillé'!AG13 | H33: ='Benchmark détaillé'!AG21 | I33: ='Benchmark détaillé'!AG22 | J33: ='Benchmark détaillé'!AG23 | K33: =IFERROR((H33-I33)/H33*100,"") | L33: =IFERROR((I33-J33)/I33*100,"") | M33: =IFERROR(I33/(E33/1000),"") | N33: =IFERROR(I33/(F33*G33),"") | O33: ='Benchmark détaillé'!AG31 | P33: ='Benchmark détaillé'!AG32 | Q33: =IFERROR(VLOOKUP(A33,'Discounts par marque'!$A:$G,4,FALSE),0) | R33: =IFERROR(VLOOKUP(A33,'Discounts par marque'!$A:$G,5,FALSE),0) | S33: =IFERROR(I33*(1-Q33/100),"") | T33: =IFERROR(S33/(F33*G33),"") | U33: =IFERROR(I33*(1-R33/100),"") | V33: =IFERROR(U33/(F33*G33),"") | W33: https://www.eafit.com/eafit-pure-whey.html
A34: ='Benchmark détaillé'!AH1 | B34: Pure Whey Protein 2.2kg | C34: ='Benchmark détaillé'!AH4 | D34: ='Benchmark détaillé'!AH10 | E34: ='Benchmark détaillé'!AH5 | F34: ='Benchmark détaillé'!AH15 | G34: ='Benchmark détaillé'!AH13 | H34: ='Benchmark détaillé'!AH21 | I34: ='Benchmark détaillé'!AH22 | J34: ='Benchmark détaillé'!AH23 | K34: =IFERROR((H34-I34)/H34*100,"") | L34: =IFERROR((I34-J34)/I34*100,"") | M34: =IFERROR(I34/(E34/1000),"") | N34: =IFERROR(I34/(F34*G34),"") | O34: ='Benchmark détaillé'!AH31 | P34: ='Benchmark détaillé'!AH32 | Q34: =IFERROR(VLOOKUP(A34,'Discounts par marque'!$A:$G,4,FALSE),0) | R34: =IFERROR(VLOOKUP(A34,'Discounts par marque'!$A:$G,5,FALSE),0) | S34: =IFERROR(I34*(1-Q34/100),"") | T34: =IFERROR(S34/(F34*G34),"") | U34: =IFERROR(I34*(1-R34/100),"") | V34: =IFERROR(U34/(F34*G34),"") | W34: https://www.eafit.com/eafit-pure-whey.html
A35: ='Benchmark détaillé'!AI1 | B35: Pure Whey Isolate 1kg | C35: ='Benchmark détaillé'!AI4 | D35: ='Benchmark détaillé'!AI10 | E35: ='Benchmark détaillé'!AI5 | F35: ='Benchmark détaillé'!AI15 | G35: ='Benchmark détaillé'!AI13 | H35: ='Benchmark détaillé'!AI21 | I35: ='Benchmark détaillé'!AI22 | J35: ='Benchmark détaillé'!AI23 | K35: =IFERROR((H35-I35)/H35*100,"") | L35: =IFERROR((I35-J35)/I35*100,"") | M35: =IFERROR(I35/(E35/1000),"") | N35: =IFERROR(I35/(F35*G35),"") | O35: ='Benchmark détaillé'!AI31 | P35: ='Benchmark détaillé'!AI32 | Q35: =IFERROR(VLOOKUP(A35,'Discounts par marque'!$A:$G,4,FALSE),0) | R35: =IFERROR(VLOOKUP(A35,'Discounts par marque'!$A:$G,5,FALSE),0) | S35: =IFERROR(I35*(1-Q35/100),"") | T35: =IFERROR(S35/(F35*G35),"") | U35: =IFERROR(I35*(1-R35/100),"") | V35: =IFERROR(U35/(F35*G35),"") | W35: https://www.bulk.com/fr/pure-whey-isolate-90.html | X35: Catalogue fictif majeur: 69.99€ barré vs 44.99€ réel (-36%)
A36: ='Benchmark détaillé'!AJ1 | B36: Pure Whey Isolate 2,5kg | C36: ='Benchmark détaillé'!AJ4 | D36: ='Benchmark détaillé'!AJ10 | E36: ='Benchmark détaillé'!AJ5 | F36: ='Benchmark détaillé'!AJ15 | G36: ='Benchmark détaillé'!AJ13 | H36: ='Benchmark détaillé'!AJ21 | I36: ='Benchmark détaillé'!AJ22 | J36: ='Benchmark détaillé'!AJ23 | K36: =IFERROR((H36-I36)/H36*100,"") | L36: =IFERROR((I36-J36)/I36*100,"") | M36: =IFERROR(I36/(E36/1000),"") | N36: =IFERROR(I36/(F36*G36),"") | O36: ='Benchmark détaillé'!AJ31 | P36: ='Benchmark détaillé'!AJ32 | Q36: =IFERROR(VLOOKUP(A36,'Discounts par marque'!$A:$G,4,FALSE),0) | R36: =IFERROR(VLOOKUP(A36,'Discounts par marque'!$A:$G,5,FALSE),0) | S36: =IFERROR(I36*(1-Q36/100),"") | T36: =IFERROR(S36/(F36*G36),"") | U36: =IFERROR(I36*(1-R36/100),"") | V36: =IFERROR(U36/(F36*G36),"") | W36: https://www.bulk.com/fr/pure-whey-isolate-90.html | X36: Catalogue fictif fort: 159.99€ vs 99.99€ réel (-37%)
A37: ='Benchmark détaillé'!AK1 | B37: Pure Whey Protein 1kg | C37: ='Benchmark détaillé'!AK4 | D37: ='Benchmark détaillé'!AK10 | E37: ='Benchmark détaillé'!AK5 | F37: ='Benchmark détaillé'!AK15 | G37: ='Benchmark détaillé'!AK13 | H37: ='Benchmark détaillé'!AK21 | I37: ='Benchmark détaillé'!AK22 | J37: ='Benchmark détaillé'!AK23 | K37: =IFERROR((H37-I37)/H37*100,"") | L37: =IFERROR((I37-J37)/I37*100,"") | M37: =IFERROR(I37/(E37/1000),"") | N37: =IFERROR(I37/(F37*G37),"") | O37: ='Benchmark détaillé'!AK31 | P37: ='Benchmark détaillé'!AK32 | Q37: =IFERROR(VLOOKUP(A37,'Discounts par marque'!$A:$G,4,FALSE),0) | R37: =IFERROR(VLOOKUP(A37,'Discounts par marque'!$A:$G,5,FALSE),0) | S37: =IFERROR(I37*(1-Q37/100),"") | T37: =IFERROR(S37/(F37*G37),"") | U37: =IFERROR(I37*(1-R37/100),"") | V37: =IFERROR(U37/(F37*G37),"") | W37: https://www.bulk.com/fr/pure-whey-protein-1.html | X37: Catalogue partiellement fictif: barré 37.99€ vs current 27.99€ vs marché 23.99€
A38: ='Benchmark détaillé'!AL1 | B38: Pure Whey Protein 2,5kg | C38: ='Benchmark détaillé'!AL4 | D38: ='Benchmark détaillé'!AL10 | E38: ='Benchmark détaillé'!AL5 | F38: ='Benchmark détaillé'!AL15 | G38: ='Benchmark détaillé'!AL13 | H38: ='Benchmark détaillé'!AL21 | I38: ='Benchmark détaillé'!AL22 | J38: ='Benchmark détaillé'!AL23 | K38: =IFERROR((H38-I38)/H38*100,"") | L38: =IFERROR((I38-J38)/I38*100,"") | M38: =IFERROR(I38/(E38/1000),"") | N38: =IFERROR(I38/(F38*G38),"") | O38: ='Benchmark détaillé'!AL31 | P38: ='Benchmark détaillé'!AL32 | Q38: =IFERROR(VLOOKUP(A38,'Discounts par marque'!$A:$G,4,FALSE),0) | R38: =IFERROR(VLOOKUP(A38,'Discounts par marque'!$A:$G,5,FALSE),0) | S38: =IFERROR(I38*(1-Q38/100),"") | T38: =IFERROR(S38/(F38*G38),"") | U38: =IFERROR(I38*(1-R38/100),"") | V38: =IFERROR(U38/(F38*G38),"") | W38: https://www.bulk.com/fr/pure-whey-protein-1.html | X38: Catalogue fictif: 84.99€ barré vs 64.99€ réel (-23%)
A39: ='Benchmark détaillé'!AM1 | B39: Pure Whey Protein 5kg | C39: ='Benchmark détaillé'!AM4 | D39: ='Benchmark détaillé'!AM10 | E39: ='Benchmark détaillé'!AM5 | F39: ='Benchmark détaillé'!AM15 | G39: ='Benchmark détaillé'!AM13 | H39: ='Benchmark détaillé'!AM21 | I39: ='Benchmark détaillé'!AM22 | J39: ='Benchmark détaillé'!AM23 | K39: =IFERROR((H39-I39)/H39*100,"") | L39: =IFERROR((I39-J39)/I39*100,"") | M39: =IFERROR(I39/(E39/1000),"") | N39: =IFERROR(I39/(F39*G39),"") | O39: ='Benchmark détaillé'!AM31 | P39: ='Benchmark détaillé'!AM32 | Q39: =IFERROR(VLOOKUP(A39,'Discounts par marque'!$A:$G,4,FALSE),0) | R39: =IFERROR(VLOOKUP(A39,'Discounts par marque'!$A:$G,5,FALSE),0) | S39: =IFERROR(I39*(1-Q39/100),"") | T39: =IFERROR(S39/(F39*G39),"") | U39: =IFERROR(I39*(1-R39/100),"") | V39: =IFERROR(U39/(F39*G39),"") | W39: https://www.bulk.com/fr/pure-whey-protein-1.html | X39: Catalogue fictif: 159.99€ vs 129.99€ payé (-19%)
A40: ='Benchmark détaillé'!AN1 | B40: Clear Whey Isolate 500g | C40: ='Benchmark détaillé'!AN4 | D40: ='Benchmark détaillé'!AN10 | E40: ='Benchmark détaillé'!AN5 | F40: ='Benchmark détaillé'!AN15 | G40: ='Benchmark détaillé'!AN13 | H40: ='Benchmark détaillé'!AN21 | I40: ='Benchmark détaillé'!AN22 | J40: ='Benchmark détaillé'!AN23 | K40: =IFERROR((H40-I40)/H40*100,"") | L40: =IFERROR((I40-J40)/I40*100,"") | M40: =IFERROR(I40/(E40/1000),"") | N40: =IFERROR(I40/(F40*G40),"") | O40: ='Benchmark détaillé'!AN31 | P40: ='Benchmark détaillé'!AN32 | Q40: =IFERROR(VLOOKUP(A40,'Discounts par marque'!$A:$G,4,FALSE),0) | R40: =IFERROR(VLOOKUP(A40,'Discounts par marque'!$A:$G,5,FALSE),0) | S40: =IFERROR(I40*(1-Q40/100),"") | T40: =IFERROR(S40/(F40*G40),"") | U40: =IFERROR(I40*(1-R40/100),"") | V40: =IFERROR(U40/(F40*G40),"") | W40: https://www.bulk.com/fr/clear-whey-isolate.html | X40: Catalogue 31.49€ barré vs 25.99€ payé (-17%). Marché 22.25€
A41: ='Benchmark détaillé'!AO1 | B41: Impact Whey Isolate 1kg | C41: ='Benchmark détaillé'!AO4 | D41: ='Benchmark détaillé'!AO10 | E41: ='Benchmark détaillé'!AO5 | F41: ='Benchmark détaillé'!AO15 | G41: ='Benchmark détaillé'!AO13 | H41: ='Benchmark détaillé'!AO21 | I41: ='Benchmark détaillé'!AO22 | J41: ='Benchmark détaillé'!AO23 | K41: =IFERROR((H41-I41)/H41*100,"") | L41: =IFERROR((I41-J41)/I41*100,"") | M41: =IFERROR(I41/(E41/1000),"") | N41: =IFERROR(I41/(F41*G41),"") | O41: ='Benchmark détaillé'!AO31 | P41: ='Benchmark détaillé'!AO32 | Q41: =IFERROR(VLOOKUP(A41,'Discounts par marque'!$A:$G,4,FALSE),0) | R41: =IFERROR(VLOOKUP(A41,'Discounts par marque'!$A:$G,5,FALSE),0) | S41: =IFERROR(I41*(1-Q41/100),"") | T41: =IFERROR(S41/(F41*G41),"") | U41: =IFERROR(I41*(1-R41/100),"") | V41: =IFERROR(U41/(F41*G41),"") | W41: https://fr.myprotein.com/p/nutrition-sportive/impact-whey-isolate/10852482/ | X41: Isolate EXCLU de la promo -30% MyProtein. Prix current = prix nominal (pas de discount automatique). Revert de l'ancienne estimation ×0.7.
A42: ='Benchmark détaillé'!AP1 | B42: Impact Whey Isolate 2,5kg | C42: ='Benchmark détaillé'!AP4 | D42: ='Benchmark détaillé'!AP10 | E42: ='Benchmark détaillé'!AP5 | F42: ='Benchmark détaillé'!AP15 | G42: ='Benchmark détaillé'!AP13 | H42: ='Benchmark détaillé'!AP21 | I42: ='Benchmark détaillé'!AP22 | J42: ='Benchmark détaillé'!AP23 | K42: =IFERROR((H42-I42)/H42*100,"") | L42: =IFERROR((I42-J42)/I42*100,"") | M42: =IFERROR(I42/(E42/1000),"") | N42: =IFERROR(I42/(F42*G42),"") | O42: ='Benchmark détaillé'!AP31 | P42: ='Benchmark détaillé'!AP32 | Q42: =IFERROR(VLOOKUP(A42,'Discounts par marque'!$A:$G,4,FALSE),0) | R42: =IFERROR(VLOOKUP(A42,'Discounts par marque'!$A:$G,5,FALSE),0) | S42: =IFERROR(I42*(1-Q42/100),"") | T42: =IFERROR(S42/(F42*G42),"") | U42: =IFERROR(I42*(1-R42/100),"") | V42: =IFERROR(U42/(F42*G42),"") | W42: https://fr.myprotein.com/p/nutrition-sportive/impact-whey-isolate-framboise-poche-2.5-kg/10530927/ | X42: Confirmé via variant Framboise 2.5kg (10530927) : 124.99€ affiché sans strikethrough. Isolate exclu de la promo -30%.
A43: ='Benchmark détaillé'!AQ1 | B43: Impact Whey Protein 1kg | C43: ='Benchmark détaillé'!AQ4 | D43: ='Benchmark détaillé'!AQ10 | E43: ='Benchmark détaillé'!AQ5 | F43: ='Benchmark détaillé'!AQ15 | G43: ='Benchmark détaillé'!AQ13 | H43: ='Benchmark détaillé'!AQ21 | I43: ='Benchmark détaillé'!AQ22 | J43: ='Benchmark détaillé'!AQ23 | K43: =IFERROR((H43-I43)/H43*100,"") | L43: =IFERROR((I43-J43)/I43*100,"") | M43: =IFERROR(I43/(E43/1000),"") | N43: =IFERROR(I43/(F43*G43),"") | O43: ='Benchmark détaillé'!AQ31 | P43: ='Benchmark détaillé'!AQ32 | Q43: =IFERROR(VLOOKUP(A43,'Discounts par marque'!$A:$G,4,FALSE),0) | R43: =IFERROR(VLOOKUP(A43,'Discounts par marque'!$A:$G,5,FALSE),0) | S43: =IFERROR(I43*(1-Q43/100),"") | T43: =IFERROR(S43/(F43*G43),"") | U43: =IFERROR(I43*(1-R43/100),"") | V43: =IFERROR(U43/(F43*G43),"") | W43: https://fr.myprotein.com/p/nutrition-sportive/myprotein-impact-whey-protein-chocolate-1kg/11068071/ | X43: Prix actuel = 17.99€ sur fr.myprotein.com/.../11068071/ (scraped Playwright 2026-04-14). Promo site -30% + extra app ramène à 17.99 vs 41.99 nominal (soit -57%). Pattern MyProtein Whey Protein uniquement.
A44: ='Benchmark détaillé'!AR1 | B44: Impact Whey Protein 2,5kg | C44: ='Benchmark détaillé'!AR4 | D44: ='Benchmark détaillé'!AR10 | E44: ='Benchmark détaillé'!AR5 | F44: ='Benchmark détaillé'!AR15 | G44: ='Benchmark détaillé'!AR13 | H44: ='Benchmark détaillé'!AR21 | I44: ='Benchmark détaillé'!AR22 | J44: ='Benchmark détaillé'!AR23 | K44: =IFERROR((H44-I44)/H44*100,"") | L44: =IFERROR((I44-J44)/I44*100,"") | M44: =IFERROR(I44/(E44/1000),"") | N44: =IFERROR(I44/(F44*G44),"") | O44: ='Benchmark détaillé'!AR31 | P44: ='Benchmark détaillé'!AR32 | Q44: =IFERROR(VLOOKUP(A44,'Discounts par marque'!$A:$G,4,FALSE),0) | R44: =IFERROR(VLOOKUP(A44,'Discounts par marque'!$A:$G,5,FALSE),0) | S44: =IFERROR(I44*(1-Q44/100),"") | T44: =IFERROR(S44/(F44*G44),"") | U44: =IFERROR(I44*(1-R44/100),"") | V44: =IFERROR(U44/(F44*G44),"") | W44: https://fr.myprotein.com/p/nutrition-sportive/myprotein-impact-whey-protein-chocolate-nut-2.5kg/10530969/ | X44: Prix scrapé via variant Chocolate Nut 2.5kg (10530969) : 84.99€ barré / 40.99€ actuel. Promo -52%. Playwright 2026-04-14.
A45: ='Benchmark détaillé'!AS1 | B45: Impact Whey Protein 5kg (Sans arôme) | C45: ='Benchmark détaillé'!AS4 | D45: ='Benchmark détaillé'!AS10 | E45: ='Benchmark détaillé'!AS5 | F45: ='Benchmark détaillé'!AS15 | G45: ='Benchmark détaillé'!AS13 | H45: ='Benchmark détaillé'!AS21 | I45: ='Benchmark détaillé'!AS22 | J45: ='Benchmark détaillé'!AS23 | K45: =IFERROR((H45-I45)/H45*100,"") | L45: =IFERROR((I45-J45)/I45*100,"") | M45: =IFERROR(I45/(E45/1000),"") | N45: =IFERROR(I45/(F45*G45),"") | O45: ='Benchmark détaillé'!AS31 | P45: ='Benchmark détaillé'!AS32 | Q45: =IFERROR(VLOOKUP(A45,'Discounts par marque'!$A:$G,4,FALSE),0) | R45: =IFERROR(VLOOKUP(A45,'Discounts par marque'!$A:$G,5,FALSE),0) | S45: =IFERROR(I45*(1-Q45/100),"") | T45: =IFERROR(S45/(F45*G45),"") | U45: =IFERROR(I45*(1-R45/100),"") | V45: =IFERROR(U45/(F45*G45),"") | W45: https://fr.myprotein.com/p/nutrition-sportive/impact-whey-protein/10530943/ | X45: 5kg n'existe qu'en 'Sans arôme' (chocolat inexistant). Current price = extrapolation du ratio 2.5kg (40.99/84.99=0.482) : 188.99 × 0.482 ≈ 91.10€.
A46: ='Benchmark détaillé'!AT1 | B46: Clear Whey Isolate 875g | C46: ='Benchmark détaillé'!AT4 | D46: ='Benchmark détaillé'!AT10 | E46: ='Benchmark détaillé'!AT5 | F46: ='Benchmark détaillé'!AT15 | G46: ='Benchmark détaillé'!AT13 | H46: ='Benchmark détaillé'!AT21 | I46: ='Benchmark détaillé'!AT22 | J46: ='Benchmark détaillé'!AT23 | K46: =IFERROR((H46-I46)/H46*100,"") | L46: =IFERROR((I46-J46)/I46*100,"") | M46: =IFERROR(I46/(E46/1000),"") | N46: =IFERROR(I46/(F46*G46),"") | O46: ='Benchmark détaillé'!AT31 | P46: ='Benchmark détaillé'!AT32 | Q46: =IFERROR(VLOOKUP(A46,'Discounts par marque'!$A:$G,4,FALSE),0) | R46: =IFERROR(VLOOKUP(A46,'Discounts par marque'!$A:$G,5,FALSE),0) | S46: =IFERROR(I46*(1-Q46/100),"") | T46: =IFERROR(S46/(F46*G46),"") | U46: =IFERROR(I46*(1-R46/100),"") | V46: =IFERROR(U46/(F46*G46),"") | W46: https://fr.myprotein.com/p/nutrition-sportive/clear-whey-isolate/12081395/ | X46: Clear Whey exclu de la promo -30% (mention explicite). Format 875g max (pas de 1kg). Confirmé via scraping 12081395.
A47: ='Benchmark détaillé'!AU1 | B47: Iso Whey Zero 908g | C47: ='Benchmark détaillé'!AU4 | D47: ='Benchmark détaillé'!AU10 | E47: ='Benchmark détaillé'!AU5 | F47: ='Benchmark détaillé'!AU15 | G47: ='Benchmark détaillé'!AU13 | H47: ='Benchmark détaillé'!AU21 | I47: ='Benchmark détaillé'!AU22 | J47: ='Benchmark détaillé'!AU23 | K47: =IFERROR((H47-I47)/H47*100,"") | L47: =IFERROR((I47-J47)/I47*100,"") | M47: =IFERROR(I47/(E47/1000),"") | N47: =IFERROR(I47/(F47*G47),"") | O47: ='Benchmark détaillé'!AU31 | P47: ='Benchmark détaillé'!AU32 | Q47: =IFERROR(VLOOKUP(A47,'Discounts par marque'!$A:$G,4,FALSE),0) | R47: =IFERROR(VLOOKUP(A47,'Discounts par marque'!$A:$G,5,FALSE),0) | S47: =IFERROR(I47*(1-Q47/100),"") | T47: =IFERROR(S47/(F47*G47),"") | U47: =IFERROR(I47*(1-R47/100),"") | V47: =IFERROR(U47/(F47*G47),"") | W47: https://shop.biotechusa.fr/products/iso-whey-zero-908-g
A48: ='Benchmark détaillé'!AV1 | B48: Iso Whey Zero 1816g | C48: ='Benchmark détaillé'!AV4 | D48: ='Benchmark détaillé'!AV10 | E48: ='Benchmark détaillé'!AV5 | F48: ='Benchmark détaillé'!AV15 | G48: ='Benchmark détaillé'!AV13 | H48: ='Benchmark détaillé'!AV21 | I48: ='Benchmark détaillé'!AV22 | J48: ='Benchmark détaillé'!AV23 | K48: =IFERROR((H48-I48)/H48*100,"") | L48: =IFERROR((I48-J48)/I48*100,"") | M48: =IFERROR(I48/(E48/1000),"") | N48: =IFERROR(I48/(F48*G48),"") | O48: ='Benchmark détaillé'!AV31 | P48: ='Benchmark détaillé'!AV32 | Q48: =IFERROR(VLOOKUP(A48,'Discounts par marque'!$A:$G,4,FALSE),0) | R48: =IFERROR(VLOOKUP(A48,'Discounts par marque'!$A:$G,5,FALSE),0) | S48: =IFERROR(I48*(1-Q48/100),"") | T48: =IFERROR(S48/(F48*G48),"") | U48: =IFERROR(I48*(1-R48/100),"") | V48: =IFERROR(U48/(F48*G48),"") | W48: https://shop.biotechusa.fr/products/iso-whey-zero-poudre-de-proteine-isolat-1816-g
A49: ='Benchmark détaillé'!AW1 | B49: 100% Pure Whey 400g | C49: ='Benchmark détaillé'!AW4 | D49: ='Benchmark détaillé'!AW10 | E49: ='Benchmark détaillé'!AW5 | F49: ='Benchmark détaillé'!AW15 | G49: ='Benchmark détaillé'!AW13 | H49: ='Benchmark détaillé'!AW21 | I49: ='Benchmark détaillé'!AW22 | J49: ='Benchmark détaillé'!AW23 | K49: =IFERROR((H49-I49)/H49*100,"") | L49: =IFERROR((I49-J49)/I49*100,"") | M49: =IFERROR(I49/(E49/1000),"") | N49: =IFERROR(I49/(F49*G49),"") | O49: ='Benchmark détaillé'!AW31 | P49: ='Benchmark détaillé'!AW32 | Q49: =IFERROR(VLOOKUP(A49,'Discounts par marque'!$A:$G,4,FALSE),0) | R49: =IFERROR(VLOOKUP(A49,'Discounts par marque'!$A:$G,5,FALSE),0) | S49: =IFERROR(I49*(1-Q49/100),"") | T49: =IFERROR(S49/(F49*G49),"") | U49: =IFERROR(I49*(1-R49/100),"") | V49: =IFERROR(U49/(F49*G49),"") | W49: https://shop.biotechusa.fr/products/100-pure-whey-400-g | X49: 8.2€/100g vs 5.5€/100g sur format 1kg (petit format plus cher)
A50: ='Benchmark détaillé'!AX1 | B50: 100% Pure Whey 1000g | C50: ='Benchmark détaillé'!AX4 | D50: ='Benchmark détaillé'!AX10 | E50: ='Benchmark détaillé'!AX5 | F50: ='Benchmark détaillé'!AX15 | G50: ='Benchmark détaillé'!AX13 | H50: ='Benchmark détaillé'!AX21 | I50: ='Benchmark détaillé'!AX22 | J50: ='Benchmark détaillé'!AX23 | K50: =IFERROR((H50-I50)/H50*100,"") | L50: =IFERROR((I50-J50)/I50*100,"") | M50: =IFERROR(I50/(E50/1000),"") | N50: =IFERROR(I50/(F50*G50),"") | O50: ='Benchmark détaillé'!AX31 | P50: ='Benchmark détaillé'!AX32 | Q50: =IFERROR(VLOOKUP(A50,'Discounts par marque'!$A:$G,4,FALSE),0) | R50: =IFERROR(VLOOKUP(A50,'Discounts par marque'!$A:$G,5,FALSE),0) | S50: =IFERROR(I50*(1-Q50/100),"") | T50: =IFERROR(S50/(F50*G50),"") | U50: =IFERROR(I50*(1-R50/100),"") | V50: =IFERROR(U50/(F50*G50),"") | W50: https://shop.biotechusa.fr/products/100-pure-whey-renouvele-1000-g | X50: GROS ÉCART : site marque 54.90€ vs idealo 27.02€ (-51%). Cross-retailers beaucoup moins cher.
A51: ='Benchmark détaillé'!AY1 | B51: 100% Pure Whey 2000g | C51: ='Benchmark détaillé'!AY4 | D51: ='Benchmark détaillé'!AY10 | E51: ='Benchmark détaillé'!AY5 | F51: ='Benchmark détaillé'!AY15 | G51: ='Benchmark détaillé'!AY13 | H51: ='Benchmark détaillé'!AY21 | I51: ='Benchmark détaillé'!AY22 | J51: ='Benchmark détaillé'!AY23 | K51: =IFERROR((H51-I51)/H51*100,"") | L51: =IFERROR((I51-J51)/I51*100,"") | M51: =IFERROR(I51/(E51/1000),"") | N51: =IFERROR(I51/(F51*G51),"") | O51: ='Benchmark détaillé'!AY31 | P51: ='Benchmark détaillé'!AY32 | Q51: =IFERROR(VLOOKUP(A51,'Discounts par marque'!$A:$G,4,FALSE),0) | R51: =IFERROR(VLOOKUP(A51,'Discounts par marque'!$A:$G,5,FALSE),0) | S51: =IFERROR(I51*(1-Q51/100),"") | T51: =IFERROR(S51/(F51*G51),"") | U51: =IFERROR(I51*(1-R51/100),"") | V51: =IFERROR(U51/(F51*G51),"") | W51: https://shop.biotechusa.fr/products/100-pure-whey-2000-g | X51: Cohérent avec 1kg : site marque surcoté vs cross-retailers (~-40-50%)

Sheet Discounts par marque
A1: Marque | B1: 1ère cmd (%) | C1: Remise bas fourchette (%) | D1: Remise client standard (%) | E1: Remise client averti (%) | F1: Remise plafond observé (%) | G1: % prix réel vs catalogue | H1: Fréquence promo | I1: Codes (top 5) | J1: N codes sourcés | K1: Règles stacking | L1: Note | M1: Sources
A2: IMPULSE | B2: 10 | C2: 15 | D2: 15 | E2: 15 | F2: 15 | G2: 85 | H2: ponctuel | I2: LORENA 15% (@lorena) | J2: 1 | K2: 10% première commande ne stacke pas avec code ambassadeur; parrainage 15% sur 1ère commande + 10% parrain | L2: Politique -10% bienvenue homepage; codes ambassadeurs typiquement 15%. Pas de promo quasi-permanente publique. | M2: https://impulse-nutrition.fr https://impulse-nutrition.fr/pages/refer https://fr.hotdeals.com/code-promo/impulse-nutrition
A3: NUTRIPURE | B3: 10 | H3: aucun | J3: 0 | K3: Pas de cumul; 10% fidélité + 10% packs intégré | L3: Politique anti-promo délibérée. Pas de Black Friday, pas de codes influenceurs >10%. Seuls le parrainage (10%) et les packs (10-25% intégrés) existent. Le prix catalogue est le vrai prix. | M3: https://www.nutripure.fr/fr/info/29-code-promo-nutripure https://www.edp-nutrition.fr/code-promo-nutripure-influenceur/
A4: NUTRIMUSCLE | C4: 10 | D4: 10 | E4: 10 | F4: 10 | G4: 90 | H4: ponctuel | I4: NMA_HYBRIDX5 10% (@valentingenest) NME_NABFIT 5% (@nabfit) NME_NUTRITION5 5% (générique) | J4: 3 | K4: Codes 5-10% cumulables avec packs réduits; ventes -20% saisonnières | L4: Politique codes influenceurs très modérés (5-10%, rarement 15%). Promos -20% uniquement en périodes soldes/Black Friday. | M4: https://www.dealabs.com/codes-promo/nutrimuscle.com https://eu.nutrimuscle.com/pages/nos-offres https://www.influenceur.promo/marques/nutrimuscle/
A5: NUTRI&CO | B5: 10 | C5: 10 | D5: 10 | E5: 10 | F5: 10 | G5: 90 | H5: ponctuel | I5: LESAVISDEMILIE10 10% (@lesavisdemilie) FITBYALEXIA 10% (@fitbyalexia) | J5: 2 | K5: Codes plafonnés à 10%, durée limitée | L5: Politique codes influenceurs plafonnée à 10%. Positionnement santé/premium, promos modérées. | M5: https://www.influenceur.promo/marques/nutrico/ https://www.edp-nutrition.fr/code-promo-nutri-and-co-influenceur/
A6: AQEELAB | B6: 15 | C6: 12 | D6: 12 | E6: 12 | F6: 12 | G6: 88 | H6: quasi-permanent | I6: LEVAND 20% (@alex.levand) TRISTAN15 15% (@tristan) CREATINATOR 10% (@creatinator) | J6: 3 | K6: Codes sans minimum, sans date d'expiration, année entière | L6: Page officielle liste tous les codes (-5/-10/-15%/-25€). Politique transparente, codes stables toute l'année. | M6: https://www.aqeelab-nutrition.fr/pages/des-conseils-des-infos-et-des-reductions https://nabfit.fr/complements-alimentaires-musculation/pas-chers/codes-promo/aqeelab-nutrition/
A7: ERIC FAVRE | B7: 10 | C7: 10 | D7: 10 | E7: 15 | F7: 20 | G7: 85 | H7: quasi-permanent | I7: SUPER20 20% (code site (>=120€)) NPNG20 20% (code événementiel) BODY15 15% (code partenaire) EFNFC10 10% (@essan_nfc) FAVRE10 10% (code site générique) | J7: 6 | K7: Programme influenceur limité (~5 ambassadeurs identifiés). Codes site 10% no-min, 20% SUPER20 avec min 120€. Pas de cumul. | L7: Programme ambassadeur très modeste — Eric Favre est positionné plus pharmacie/pro-sport que fitness mass-market. Essan NFC est le seul vrai ambassadeur agrégé avec 1087 utilisations. P50=10%, P90=15%. Client averti paye ~85% du catalogue. | M7: https://www.ericfavre.com/fr_fr/reductions-codes-promo https://www.influenceur.promo/marques/eric-favre/ https://fr.hotdeals.com/store/code-promo-eric-favre
A8: EAFIT | B8: 30 | C8: 20 | D8: 32 | E8: 32 | F8: 35 | G8: 68 | H8: quasi-permanent | I8: CPS32 32% (@tamara.awada) MARION32 32% (@mrsmariont) MATHILDE32 32% (@mathildegros) TATIANA32 32% (@tatianamembre) ILONA32 32% (@ilonafrigout) | J8: 10 | K8: Programme français standardisé à 32% (suffixe *32 sur 8+ codes récents). Ancien programme 20% résiduel (EMILIE20). Code site FIT25=25% + pack offert dès 60€. Pas de cumul code influenceur + FIT25. | L8: Programme ambassadeur UPGRADÉ à 32% (vs 20% historique). Client averti paye ~68% du catalogue via code CPS32/MARION32. Plus agressif qu'attendu pour une marque française. | M8: https://www.eafit.com/deals-du-moment.html https://www.influenceur.promo/marques/ea-fit/ https://www.lesavisdemilie.fr/code-promo-eafit/
A9: DECATHLON | H9: ponctuel | J9: 0 | L9: Corength / Aptonia sans programme d'affiliation influenceur structuré. Prix catalogue stables, promos seulement lors soldes Decathlon globales. | M9: https://www.decathlon.fr/nutrition-sante/whey-proteines https://www.lareduction.fr/s/decathlon.fr
A10: BULK | B10: 15 | C10: 25 | D10: 45 | E10: 45 | F10: 45 | G10: 55 | H10: quasi-permanent | I10: BUDDY45 45% (@tristandefeuilletvang) TWINS 45% (@twinsb_fit) ARTHUR 45% (@arthurbenedetti) LIFTIT 45% (@hugophilip) ALIX 45% (@alixmhd) | J10: 10 | K10: Distribution quasi monolithique à 45% (codes récents 2024-2026) + reliquat 20-25% (codes anciens). Site affiche 'jusqu'à -75%' en homepage (cumul produit-promo + code). Flash sales 'Bulk Week' -50/-70% ponctuelles. Code influenceur ne stacke pas avec flash sale. | L10: Programme ULTRA-STANDARDISÉ : 20+ ambassadeurs au même code 45%. Tes 30% initiaux étaient largement sous-estimés — P50 réel = 45%. Site-wide banner '-75%' atteint via cumul. Client averti paye ~55% du catalogue. | M10: https://www.influenceur.promo/marques/bulk-powders/ https://www.lesavisdemilie.fr/code-promo-bulk/ https://www.savoo.fr/marques/codes-promo-bulk
A11: MYPROTEIN | B11: 40 | C11: 20 | D11: 42 | E11: 50 | F11: 55 | G11: 52 | H11: quasi-permanent | I11: MELISSAT 55% (@melissathiebaut) BUDDY 50% (@tristandefeuilletvang) PAUL 50% (@pauldenisnavero) TURBOTIFF 50% (@tiffanychapon) TDYPARKER 50% (@tdyparker) | J11: 12 | K11: Site affiche en permanence 'up to 55% off' en bandeau homepage. Codes influenceurs NE se cumulent PAS avec flash sale site — le plus élevé s'applique, typiquement code influenceur 42-50% remplace promo 30-40% base. | L11: PRIX CATALOGUE TOTALEMENT FICTIF. Promo permanente 30-55% en bandeau site. P50 codes influenceurs = 42%, P90 = 50%, max = 55%. Le client averti applique systématiquement un code 50% → paye ~50% du catalogue. Les 35% initiaux étaient largement sous-estimés (~P25). | M11: https://www.influenceur.promo/marques/myprotein/ https://kotag.co/marques/codes-promo-myprotein/ https://www.codes-promo-influenceurs.fr/marques/myprotein https://fr.myprotein.com/c/nouveaux-clients/
A12: PROZIS | B12: 10 | C12: 10 | D12: 10 | E12: 20 | F12: 50 | G12: 65 | H12: quasi-permanent | I12: 19YEARS 50% (flash sale anniversaire) MADNESS 40% (flash sale site) KEONII 10% (@keonii) LAURAPETARD 10% (@laurapetard) QFITLIFE 10% (@quentin-fitlife) | J12: 10 | K12: Codes influenceurs standardisés à 10% — cumul PARTIEL avec promos produit (pack, outlet) mais PAS avec flash sales (MADNESS, 19YEARS, BLACKWEEK à 40-50%). Site en permanence avec produits -30 à -50% en outlet. | L12: Très modéré côté influenceurs (10% dominant) mais les flash sales saisonnières (MADNESS, 19YEARS) vont jusqu'à 50%. Client averti attend une flash sale pour commander. P50 codes quotidiens = 10%, P90 = 20% (outlet), max = 50% (flash sale). | M12: https://www.influenceur.promo/marques/prozis/ https://fr.promocodie.com/code/code-promo-prozis-influenceur
A13: FOODSPRING | B13: 10 | C13: 15 | D13: 15 | E13: 20 | F13: 30 | G13: 85 | H13: quasi-permanent | I13: FOODSPRING30 30% (site code évènementiel) FS20SALE 20% (@yamina_niya) ALIZOUFSG 20% (@alizeeandreani) JUJUFSG 20% (@juliecfs) JESSICA15 15% (@jessicathivenin) | J13: 10 | K13: Programme ultra-standardisé à 15% (60+ codes suffixe *FSG). Remontées ponctuelles à 20% (Black Week, SummerSale). Code site FOODSPRING30 = 30% évènementiel. Pas de cumul entre code influenceur et flash sale. | L13: Très conservateur (15% dominant, ~85% des codes). Stratégie Foodspring = premium, moins de guerre des prix que MyProtein/Bulk. P50 = 15% fiable, P90 = 20%. Client averti paye ~85% du catalogue. | M13: https://www.influenceur.promo/marques/foodspring/ https://vivremoinscher.fr/stores/foodspring-coupons/
A14: ESN | B14: 10 | C14: 15 | D14: 20 | E14: 25 | F14: 30 | G14: 80 | H14: quasi-permanent | I14: ELENA 20% (@elena.ntns) KIMMIE 20% (@kimmieous) LEON 20% (@leonidas_arkona) LARA 20% (@laraemilia) KEVIN 20% (@wolterkevin) | J14: 8 | K14: Programme allemand standardisé à 20%. 'Performance Week' et flash sales site jusqu'à 40-50%, pas de cumul. Discounts site ciblés par catégorie (10% outlet, 20% selected, 50% certains variants). | L14: Distribution très uniforme à 20% (tous ambassadeurs). Max 25% sur promos saisonales. Moins agressif que MyProtein/Bulk. Client paye ~80% du catalogue. | M14: https://www.influencercodes.de/marken/esn/ https://suppwiser.de/rabattcodes/esn-rabattcode/ https://fr.coupert.com/codes-promo/esn-com
A15: BIOTECHUSA | B15: 10 | C15: 15 | D15: 15 | E15: 20 | F15: 30 | G15: 82 | H15: quasi-permanent | I15: SUPER1225 30% (site code évènementiel) GYM33 20% (@gym33) JENZO15 15% (@jeanneetenzo) ANA15 15% (@anastasiyabury) REMI15 15% (@remi_ragnar) | J15: 6 | K15: Programme ambassadeurs à 15% fixe (TRND + partenariats directs). Codes site évènementiels jusqu'à 30-40%. Programme de fidélité cumulable avec code influenceur selon ambassadeur. | L15: Programme modeste : 15% standard, rarement au-delà de 20%. BiotechUSA = marque hongroise low-cost de base. P50 = 15% très fiable. Client paye ~82% du catalogue. | M15: https://shop.biotechusa.fr/collections/promotion-mensuelle-automatique https://shop.biotechusa.fr/pages/loyalty-program https://kotag.co/marques/codes-promo-biotechusa/

Sheet Classement €⁄g protéine
A1: Classement par 'Prix client standard / g protéine' croissant (#1 = meilleur rapport qualité/prix pour un client avec un code ambassadeur typique). Les valeurs chiffrées sont des formules live référençant l'onglet 'Synthèse prix'. Seul l'ordre de tri est figé au build. Si tu modifies un prix/remise dans Synthèse ou Discounts, les valeurs ici se mettent à jour. Pour réordonner le classement après une modif majeure, regénère le xlsx.
A2: Rang | B2: Marque | C2: Produit | D2: Format | E2: Prix nominal | F2: Prix actuel | G2: Prix marché | H2: Prix actuel /g prot | I2: Prix client standard | J2: Prix client standard /g prot | K2: Prix client averti | L2: Prix client averti /g prot | M2: Remise standard (%)
A3: 1 | B3: ='Synthèse prix'!A44 | C3: Impact Whey Protein 2,5kg | D3: 2.5kg | E3: ='Synthèse prix'!H44 | F3: ='Synthèse prix'!I44 | G3: ='Synthèse prix'!J44 | H3: ='Synthèse prix'!N44 | I3: ='Synthèse prix'!S44 | J3: ='Synthèse prix'!T44 | K3: ='Synthèse prix'!U44 | L3: ='Synthèse prix'!V44 | M3: ='Synthèse prix'!Q44
A4: 2 | B4: ='Synthèse prix'!A43 | C4: Impact Whey Protein 1kg | D4: 1kg | E4: ='Synthèse prix'!H43 | F4: ='Synthèse prix'!I43 | G4: ='Synthèse prix'!J43 | H4: ='Synthèse prix'!N43 | I4: ='Synthèse prix'!S43 | J4: ='Synthèse prix'!T43 | K4: ='Synthèse prix'!U43 | L4: ='Synthèse prix'!V43 | M4: ='Synthèse prix'!Q43
A5: 3 | B5: ='Synthèse prix'!A45 | C5: Impact Whey Protein 5kg (Sans arôme) | D5: 5kg | E5: ='Synthèse prix'!H45 | F5: ='Synthèse prix'!I45 | G5: ='Synthèse prix'!J45 | H5: ='Synthèse prix'!N45 | I5: ='Synthèse prix'!S45 | J5: ='Synthèse prix'!T45 | K5: ='Synthèse prix'!U45 | L5: ='Synthèse prix'!V45 | M5: ='Synthèse prix'!Q45
A6: 4 | B6: ='Synthèse prix'!A38 | C6: Pure Whey Protein 2,5kg | D6: 2.5kg | E6: ='Synthèse prix'!H38 | F6: ='Synthèse prix'!I38 | G6: ='Synthèse prix'!J38 | H6: ='Synthèse prix'!N38 | I6: ='Synthèse prix'!S38 | J6: ='Synthèse prix'!T38 | K6: ='Synthèse prix'!U38 | L6: ='Synthèse prix'!V38 | M6: ='Synthèse prix'!Q38
A7: 5 | B7: ='Synthèse prix'!A39 | C7: Pure Whey Protein 5kg | D7: 5kg | E7: ='Synthèse prix'!H39 | F7: ='Synthèse prix'!I39 | G7: ='Synthèse prix'!J39 | H7: ='Synthèse prix'!N39 | I7: ='Synthèse prix'!S39 | J7: ='Synthèse prix'!T39 | K7: ='Synthèse prix'!U39 | L7: ='Synthèse prix'!V39 | M7: ='Synthèse prix'!Q39
A8: 6 | B8: ='Synthèse prix'!A37 | C8: Pure Whey Protein 1kg | D8: 1kg | E8: ='Synthèse prix'!H37 | F8: ='Synthèse prix'!I37 | G8: ='Synthèse prix'!J37 | H8: ='Synthèse prix'!N37 | I8: ='Synthèse prix'!S37 | J8: ='Synthèse prix'!T37 | K8: ='Synthèse prix'!U37 | L8: ='Synthèse prix'!V37 | M8: ='Synthèse prix'!Q37
A9: 7 | B9: ='Synthèse prix'!A36 | C9: Pure Whey Isolate 2,5kg | D9: 2.5kg | E9: ='Synthèse prix'!H36 | F9: ='Synthèse prix'!I36 | G9: ='Synthèse prix'!J36 | H9: ='Synthèse prix'!N36 | I9: ='Synthèse prix'!S36 | J9: ='Synthèse prix'!T36 | K9: ='Synthèse prix'!U36 | L9: ='Synthèse prix'!V36 | M9: ='Synthèse prix'!Q36
A10: 9 | B10: ='Synthèse prix'!A35 | C10: Pure Whey Isolate 1kg | D10: 1kg | E10: ='Synthèse prix'!H35 | F10: ='Synthèse prix'!I35 | G10: ='Synthèse prix'!J35 | H10: ='Synthèse prix'!N35 | I10: ='Synthèse prix'!S35 | J10: ='Synthèse prix'!T35 | K10: ='Synthèse prix'!U35 | L10: ='Synthèse prix'!V35 | M10: ='Synthèse prix'!Q35
A11: 10 | B11: ='Synthèse prix'!A42 | C11: Impact Whey Isolate 2,5kg | D11: 2.5kg | E11: ='Synthèse prix'!H42 | F11: ='Synthèse prix'!I42 | G11: ='Synthèse prix'!J42 | H11: ='Synthèse prix'!N42 | I11: ='Synthèse prix'!S42 | J11: ='Synthèse prix'!T42 | K11: ='Synthèse prix'!U42 | L11: ='Synthèse prix'!V42 | M11: ='Synthèse prix'!Q42
A12: 12 | B12: ='Synthèse prix'!A34 | C12: Pure Whey Protein 2.2kg | D12: 2.2kg | E12: ='Synthèse prix'!H34 | F12: ='Synthèse prix'!I34 | G12: ='Synthèse prix'!J34 | H12: ='Synthèse prix'!N34 | I12: ='Synthèse prix'!S34 | J12: ='Synthèse prix'!T34 | K12: ='Synthèse prix'!U34 | L12: ='Synthèse prix'!V34 | M12: ='Synthèse prix'!Q34
A13: 13 | B13: ='Synthèse prix'!A41 | C13: Impact Whey Isolate 1kg | D13: 1kg | E13: ='Synthèse prix'!H41 | F13: ='Synthèse prix'!I41 | G13: ='Synthèse prix'!J41 | H13: ='Synthèse prix'!N41 | I13: ='Synthèse prix'!S41 | J13: ='Synthèse prix'!T41 | K13: ='Synthèse prix'!U41 | L13: ='Synthèse prix'!V41 | M13: ='Synthèse prix'!Q41
A14: 14 | B14: ='Synthèse prix'!A28 | C14: Iso Fusion Protein Complex 2kg | D14: 2kg | E14: ='Synthèse prix'!H28 | F14: ='Synthèse prix'!I28 | G14: ='Synthèse prix'!J28 | H14: ='Synthèse prix'!N28 | I14: ='Synthèse prix'!S28 | J14: ='Synthèse prix'!T28 | K14: ='Synthèse prix'!U28 | L14: ='Synthèse prix'!V28 | M14: ='Synthèse prix'!Q28
A15: 15 | B15: ='Synthèse prix'!A17 | C15: Whey Native Concentrat 4kg | D15: 4kg | E15: ='Synthèse prix'!H17 | F15: ='Synthèse prix'!I17 | G15: ='Synthèse prix'!J17 | H15: ='Synthèse prix'!N17 | I15: ='Synthèse prix'!S17 | J15: ='Synthèse prix'!T17 | K15: ='Synthèse prix'!U17 | L15: ='Synthèse prix'!V17 | M15: ='Synthèse prix'!Q17
A16: 16 | B16: ='Synthèse prix'!A31 | C16: Pure Whey Protein 750g | D16: 750g | E16: ='Synthèse prix'!H31 | F16: ='Synthèse prix'!I31 | G16: ='Synthèse prix'!J31 | H16: ='Synthèse prix'!N31 | I16: ='Synthèse prix'!S31 | J16: ='Synthèse prix'!T31 | K16: ='Synthèse prix'!U31 | L16: ='Synthèse prix'!V31 | M16: ='Synthèse prix'!Q31
A17: 18 | B17: ='Synthèse prix'!A16 | C17: Whey Native Concentrat 2,25kg | D17: 2.25kg | E17: ='Synthèse prix'!H16 | F17: ='Synthèse prix'!I16 | G17: ='Synthèse prix'!J16 | H17: ='Synthèse prix'!N16 | I17: ='Synthèse prix'!S16 | J17: ='Synthèse prix'!T16 | K17: ='Synthèse prix'!U16 | L17: ='Synthèse prix'!V16 | M17: ='Synthèse prix'!Q16
A18: 19 | B18: ='Synthèse prix'!A33 | C18: Pure Whey Protein 850g | D18: 850g | E18: ='Synthèse prix'!H33 | F18: ='Synthèse prix'!I33 | G18: ='Synthèse prix'!J33 | H18: ='Synthèse prix'!N33 | I18: ='Synthèse prix'!S33 | J18: ='Synthèse prix'!T33 | K18: ='Synthèse prix'!U33 | L18: ='Synthèse prix'!V33 | M18: ='Synthèse prix'!Q33
A19: 20 | B19: ='Synthèse prix'!A46 | C19: Clear Whey Isolate 875g | D19: 875g | E19: ='Synthèse prix'!H46 | F19: ='Synthèse prix'!I46 | G19: ='Synthèse prix'!J46 | H19: ='Synthèse prix'!N46 | I19: ='Synthèse prix'!S46 | J19: ='Synthèse prix'!T46 | K19: ='Synthèse prix'!U46 | L19: ='Synthèse prix'!V46 | M19: ='Synthèse prix'!Q46
A20: 22 | B20: ='Synthèse prix'!A15 | C20: Whey Native Concentrat | D20: 1kg | E20: ='Synthèse prix'!H15 | F20: ='Synthèse prix'!I15 | G20: ='Synthèse prix'!J15 | H20: ='Synthèse prix'!N15 | I20: ='Synthèse prix'!S15 | J20: ='Synthèse prix'!T15 | K20: ='Synthèse prix'!U15 | L20: ='Synthèse prix'!V15 | M20: ='Synthèse prix'!Q15
A21: 23 | B21: ='Synthèse prix'!A40 | C21: Clear Whey Isolate 500g | D21: 500g | E21: ='Synthèse prix'!H40 | F21: ='Synthèse prix'!I40 | G21: ='Synthèse prix'!J40 | H21: ='Synthèse prix'!N40 | I21: ='Synthèse prix'!S40 | J21: ='Synthèse prix'!T40 | K21: ='Synthèse prix'!U40 | L21: ='Synthèse prix'!V40 | M21: ='Synthèse prix'!Q40
A22: 26 | B22: ='Synthèse prix'!A14 | C22: Whey Native Concentrat 500g | D22: 500g | E22: ='Synthèse prix'!H14 | F22: ='Synthèse prix'!I14 | G22: ='Synthèse prix'!J14 | H22: ='Synthèse prix'!N14 | I22: ='Synthèse prix'!S14 | J22: ='Synthèse prix'!T14 | K22: ='Synthèse prix'!U14 | L22: ='Synthèse prix'!V14 | M22: ='Synthèse prix'!Q14
A23: 28 | B23: ='Synthèse prix'!A25 | C23: Whey Optimax Protein 1,5kg | D23: 1.5kg | E23: ='Synthèse prix'!H25 | F23: ='Synthèse prix'!I25 | G23: ='Synthèse prix'!J25 | H23: ='Synthèse prix'!N25 | I23: ='Synthèse prix'!S25 | J23: ='Synthèse prix'!T25 | K23: ='Synthèse prix'!U25 | L23: ='Synthèse prix'!V25 | M23: ='Synthèse prix'!Q25
A24: 30 | B24: ='Synthèse prix'!A29 | C24: Pure Isolate 750g | D24: 750g | E24: ='Synthèse prix'!H29 | F24: ='Synthèse prix'!I29 | G24: ='Synthèse prix'!J29 | H24: ='Synthèse prix'!N29 | I24: ='Synthèse prix'!S29 | J24: ='Synthèse prix'!T29 | K24: ='Synthèse prix'!U29 | L24: ='Synthèse prix'!V29 | M24: ='Synthèse prix'!Q29
A25: 31 | B25: ='Synthèse prix'!A26 | C25: Whey Zero Protéine 2kg | D25: 2kg | E25: ='Synthèse prix'!H26 | F25: ='Synthèse prix'!I26 | G25: ='Synthèse prix'!J26 | H25: ='Synthèse prix'!N26 | I25: ='Synthèse prix'!S26 | J25: ='Synthèse prix'!T26 | K25: ='Synthèse prix'!U26 | L25: ='Synthèse prix'!V26 | M25: ='Synthèse prix'!Q26
A26: 32 | B26: ='Synthèse prix'!A4 | C26: Whey Isolate | D26: 750g | E26: ='Synthèse prix'!H4 | F26: ='Synthèse prix'!I4 | G26: ='Synthèse prix'!J4 | H26: ='Synthèse prix'!N4 | I26: ='Synthèse prix'!S4 | J26: ='Synthèse prix'!T4 | K26: ='Synthèse prix'!U4 | L26: ='Synthèse prix'!V4 | M26: ='Synthèse prix'!Q4
A27: 34 | B27: ='Synthèse prix'!A32 | C27: Mega Whey Creatine Complex 750g | D27: 750g | E27: ='Synthèse prix'!H32 | F27: ='Synthèse prix'!I32 | G27: ='Synthèse prix'!J32 | H27: ='Synthèse prix'!N32 | I27: ='Synthèse prix'!S32 | J27: ='Synthèse prix'!T32 | K27: ='Synthèse prix'!U32 | L27: ='Synthèse prix'!V32 | M27: ='Synthèse prix'!Q32
A28: 35 | B28: ='Synthèse prix'!A13 | C28: Whey Native Isolate 4kg | D28: 4kg | E28: ='Synthèse prix'!H13 | F28: ='Synthèse prix'!I13 | G28: ='Synthèse prix'!J13 | H28: ='Synthèse prix'!N13 | I28: ='Synthèse prix'!S13 | J28: ='Synthèse prix'!T13 | K28: ='Synthèse prix'!U13 | L28: ='Synthèse prix'!V13 | M28: ='Synthèse prix'!Q13
A29: 36 | B29: ='Synthèse prix'!A23 | C29: Iso Zero 100% Whey Protéine 2kg | D29: 2kg | E29: ='Synthèse prix'!H23 | F29: ='Synthèse prix'!I23 | G29: ='Synthèse prix'!J23 | H29: ='Synthèse prix'!N23 | I29: ='Synthèse prix'!S23 | J29: ='Synthèse prix'!T23 | K29: ='Synthèse prix'!U23 | L29: ='Synthèse prix'!V23 | M29: ='Synthèse prix'!Q23
A30: 37 | B30: ='Synthèse prix'!A30 | C30: Pure Isolate Premium 750g | D30: 750g | E30: ='Synthèse prix'!H30 | F30: ='Synthèse prix'!I30 | G30: ='Synthèse prix'!J30 | H30: ='Synthèse prix'!N30 | I30: ='Synthèse prix'!S30 | J30: ='Synthèse prix'!T30 | K30: ='Synthèse prix'!U30 | L30: ='Synthèse prix'!V30 | M30: ='Synthèse prix'!Q30
A31: 39 | B31: ='Synthèse prix'!A20 | C31: Whey Native 810g | D31: 810g | E31: ='Synthèse prix'!H20 | F31: ='Synthèse prix'!I20 | G31: ='Synthèse prix'!J20 | H31: ='Synthèse prix'!N20 | I31: ='Synthèse prix'!S20 | J31: ='Synthèse prix'!T20 | K31: ='Synthèse prix'!U20 | L31: ='Synthèse prix'!V20 | M31: ='Synthèse prix'!Q20
A32: 40 | B32: ='Synthèse prix'!A2 | C32: Whey Isolate | D32: 750g | E32: ='Synthèse prix'!H2 | F32: ='Synthèse prix'!I2 | G32: ='Synthèse prix'!J2 | H32: ='Synthèse prix'!N2 | I32: ='Synthèse prix'!S2 | J32: ='Synthèse prix'!T2 | K32: ='Synthèse prix'!U2 | L32: ='Synthèse prix'!V2 | M32: ='Synthèse prix'!Q2
A33: 41 | B33: ='Synthèse prix'!A3 | C33: Whey Isolate | D33: 750g | E33: ='Synthèse prix'!H3 | F33: ='Synthèse prix'!I3 | G33: ='Synthèse prix'!J3 | H33: ='Synthèse prix'!N3 | I33: ='Synthèse prix'!S3 | J33: ='Synthèse prix'!T3 | K33: ='Synthèse prix'!U3 | L33: ='Synthèse prix'!V3 | M33: ='Synthèse prix'!Q3
A34: 43 | B34: ='Synthèse prix'!A9 | C34: Whey Isolat Native 4kg | D34: 4kg | E34: ='Synthèse prix'!H9 | F34: ='Synthèse prix'!I9 | G34: ='Synthèse prix'!J9 | H34: ='Synthèse prix'!N9 | I34: ='Synthèse prix'!S9 | J34: ='Synthèse prix'!T9 | K34: ='Synthèse prix'!U9 | L34: ='Synthèse prix'!V9 | M34: ='Synthèse prix'!Q9
A35: 44 | B35: ='Synthèse prix'!A19 | C35: Whey Concentrée Native 900g | D35: 900g | E35: ='Synthèse prix'!H19 | F35: ='Synthèse prix'!I19 | G35: ='Synthèse prix'!J19 | H35: ='Synthèse prix'!N19 | I35: ='Synthèse prix'!S19 | J35: ='Synthèse prix'!T19 | K35: ='Synthèse prix'!U19 | L35: ='Synthèse prix'!V19 | M35: ='Synthèse prix'!Q19
A36: 45 | B36: ='Synthèse prix'!A51 | C36: 100% Pure Whey 2000g | D36: 2kg | E36: ='Synthèse prix'!H51 | F36: ='Synthèse prix'!I51 | G36: ='Synthèse prix'!J51 | H36: ='Synthèse prix'!N51 | I36: ='Synthèse prix'!S51 | J36: ='Synthèse prix'!T51 | K36: ='Synthèse prix'!U51 | L36: ='Synthèse prix'!V51 | M36: ='Synthèse prix'!Q51
A37: 46 | B37: ='Synthèse prix'!A12 | C37: Whey Native Isolate 2,25kg | D37: 2.25kg | E37: ='Synthèse prix'!H12 | F37: ='Synthèse prix'!I12 | G37: ='Synthèse prix'!J12 | H37: ='Synthèse prix'!N12 | I37: ='Synthèse prix'!S12 | J37: ='Synthèse prix'!T12 | K37: ='Synthèse prix'!U12 | L37: ='Synthèse prix'!V12 | M37: ='Synthèse prix'!Q12
A38: 49 | B38: ='Synthèse prix'!A22 | C38: Iso Zero 100% Whey Protéine 1,5kg | D38: 1.5kg | E38: ='Synthèse prix'!H22 | F38: ='Synthèse prix'!I22 | G38: ='Synthèse prix'!J22 | H38: ='Synthèse prix'!N22 | I38: ='Synthèse prix'!S22 | J38: ='Synthèse prix'!T22 | K38: ='Synthèse prix'!U22 | L38: ='Synthèse prix'!V22 | M38: ='Synthèse prix'!Q22
A39: 50 | B39: ='Synthèse prix'!A18 | C39: Whey Isolate Native 900g | D39: 900g | E39: ='Synthèse prix'!H18 | F39: ='Synthèse prix'!I18 | G39: ='Synthèse prix'!J18 | H39: ='Synthèse prix'!N18 | I39: ='Synthèse prix'!S18 | J39: ='Synthèse prix'!T18 | K39: ='Synthèse prix'!U18 | L39: ='Synthèse prix'!V18 | M39: ='Synthèse prix'!Q18
A40: 51 | B40: ='Synthèse prix'!A48 | C40: Iso Whey Zero 1816g | D40: 1.816kg | E40: ='Synthèse prix'!H48 | F40: ='Synthèse prix'!I48 | G40: ='Synthèse prix'!J48 | H40: ='Synthèse prix'!N48 | I40: ='Synthèse prix'!S48 | J40: ='Synthèse prix'!T48 | K40: ='Synthèse prix'!U48 | L40: ='Synthèse prix'!V48 | M40: ='Synthèse prix'!Q48
A41: 52 | B41: ='Synthèse prix'!A27 | C41: Iso Fusion Protein Complex 750g | D41: 750g | E41: ='Synthèse prix'!H27 | F41: ='Synthèse prix'!I27 | G41: ='Synthèse prix'!J27 | H41: ='Synthèse prix'!N27 | I41: ='Synthèse prix'!S27 | J41: ='Synthèse prix'!T27 | K41: ='Synthèse prix'!U27 | L41: ='Synthèse prix'!V27 | M41: ='Synthèse prix'!Q27
A42: 53 | B42: ='Synthèse prix'!A8 | C42: Whey Isolat Native 2kg | D42: 2kg | E42: ='Synthèse prix'!H8 | F42: ='Synthèse prix'!I8 | G42: ='Synthèse prix'!J8 | H42: ='Synthèse prix'!N8 | I42: ='Synthèse prix'!S8 | J42: ='Synthèse prix'!T8 | K42: ='Synthèse prix'!U8 | L42: ='Synthèse prix'!V8 | M42: ='Synthèse prix'!Q8
A43: 54 | B43: ='Synthèse prix'!A7 | C43: Whey Isolat Native 750g | D43: 750g | E43: ='Synthèse prix'!H7 | F43: ='Synthèse prix'!I7 | G43: ='Synthèse prix'!J7 | H43: ='Synthèse prix'!N7 | I43: ='Synthèse prix'!S7 | J43: ='Synthèse prix'!T7 | K43: ='Synthèse prix'!U7 | L43: ='Synthèse prix'!V7 | M43: ='Synthèse prix'!Q7
A44: 55 | B44: ='Synthèse prix'!A11 | C44: Whey Native Isolate | D44: 1kg | E44: ='Synthèse prix'!H11 | F44: ='Synthèse prix'!I11 | G44: ='Synthèse prix'!J11 | H44: ='Synthèse prix'!N11 | I44: ='Synthèse prix'!S11 | J44: ='Synthèse prix'!T11 | K44: ='Synthèse prix'!U11 | L44: ='Synthèse prix'!V11 | M44: ='Synthèse prix'!Q11
A45: 56 | B45: ='Synthèse prix'!A50 | C45: 100% Pure Whey 1000g | D45: 1kg | E45: ='Synthèse prix'!H50 | F45: ='Synthèse prix'!I50 | G45: ='Synthèse prix'!J50 | H45: ='Synthèse prix'!N50 | I45: ='Synthèse prix'!S50 | J45: ='Synthèse prix'!T50 | K45: ='Synthèse prix'!U50 | L45: ='Synthèse prix'!V50 | M45: ='Synthèse prix'!Q50
A46: 57 | B46: ='Synthèse prix'!A10 | C46: Whey Native Isolate 500g | D46: 500g | E46: ='Synthèse prix'!H10 | F46: ='Synthèse prix'!I10 | G46: ='Synthèse prix'!J10 | H46: ='Synthèse prix'!N10 | I46: ='Synthèse prix'!S10 | J46: ='Synthèse prix'!T10 | K46: ='Synthèse prix'!U10 | L46: ='Synthèse prix'!V10 | M46: ='Synthèse prix'!Q10
A47: 58 | B47: ='Synthèse prix'!A21 | C47: Iso Zero 100% Whey Protéine 500g | D47: 500g | E47: ='Synthèse prix'!H21 | F47: ='Synthèse prix'!I21 | G47: ='Synthèse prix'!J21 | H47: ='Synthèse prix'!N21 | I47: ='Synthèse prix'!S21 | J47: ='Synthèse prix'!T21 | K47: ='Synthèse prix'!U21 | L47: ='Synthèse prix'!V21 | M47: ='Synthèse prix'!Q21
A48: 59 | B48: ='Synthèse prix'!A24 | C48: Whey Optimax Protein 500g | D48: 500g | E48: ='Synthèse prix'!H24 | F48: ='Synthèse prix'!I24 | G48: ='Synthèse prix'!J24 | H48: ='Synthèse prix'!N24 | I48: ='Synthèse prix'!S24 | J48: ='Synthèse prix'!T24 | K48: ='Synthèse prix'!U24 | L48: ='Synthèse prix'!V24 | M48: ='Synthèse prix'!Q24
A49: 60 | B49: ='Synthèse prix'!A47 | C49: Iso Whey Zero 908g | D49: 908g | E49: ='Synthèse prix'!H47 | F49: ='Synthèse prix'!I47 | G49: ='Synthèse prix'!J47 | H49: ='Synthèse prix'!N47 | I49: ='Synthèse prix'!S47 | J49: ='Synthèse prix'!T47 | K49: ='Synthèse prix'!U47 | L49: ='Synthèse prix'!V47 | M49: ='Synthèse prix'!Q47
A50: 61 | B50: ='Synthèse prix'!A49 | C50: 100% Pure Whey 400g | D50: 400g | E50: ='Synthèse prix'!H49 | F50: ='Synthèse prix'!I49 | G50: ='Synthèse prix'!J49 | H50: ='Synthèse prix'!N49 | I50: ='Synthèse prix'!S49 | J50: ='Synthèse prix'!T49 | K50: ='Synthèse prix'!U49 | L50: ='Synthèse prix'!V49 | M50: ='Synthèse prix'!Q49
A51: 62 | B51: ='Synthèse prix'!A5 | C51: Whey Recovery | D51: 525g | E51: ='Synthèse prix'!H5 | F51: ='Synthèse prix'!I5 | G51: ='Synthèse prix'!J5 | H51: ='Synthèse prix'!N5 | I51: ='Synthèse prix'!S5 | J51: ='Synthèse prix'!T5 | K51: ='Synthèse prix'!U5 | L51: ='Synthèse prix'!V5 | M51: ='Synthèse prix'!Q5
A52: 63 | B52: ='Synthèse prix'!A6 | C52: Whey Recovery | D52: 525g | E52: ='Synthèse prix'!H6 | F52: ='Synthèse prix'!I6 | G52: ='Synthèse prix'!J6 | H52: ='Synthèse prix'!N6 | I52: ='Synthèse prix'!S6 | J52: ='Synthèse prix'!T6 | K52: ='Synthèse prix'!U6 | L52: ='Synthèse prix'!V6 | M52: ='Synthèse prix'!Q6

Sheet Data
B2: Structure de prix | C2: Whey Concentrat | D2: Whey Concentrat | E2: Whey Isolat | F2: Whey Isolat
C3: Option 1 | D3: Option 2 | E3: Actuellement | F3: Demain
B4: PPTTC | C4: 36.9 | D4: 39.9 | E4: 39.9 | F4: 49.9
B5: TVA | C5: 0.2 | D5: 0.055 | E5: 0.055 | F5: 0.055
B6: PPHT | C6: 30.75 | D6: 37.82 | E6: 37.82 | F6: 47.3
B7: Tarif | C7: 36.9 | D7: 39.9 | E7: 39.9 | F7: 49.9
B8: Taux de remise complet | C8: 0.18 | D8: 0.18 | E8: 0.18 | F8: 0.18
B9: PVM net | C9: 30.26 | D9: 32.72 | E9: 32.72 | F9: 40.92
B10: PR | C10: 21 | D10: 21 | E10: 25 | F10: 25
B11: Marge nette unitaire | C11: 9.26 | D11: 11.72 | E11: 7.72 | F11: 15.92
B12: % marge nette | C12: 0.31 | D12: 0.36 | E12: 0.24 | F12: 0.39
