Workbook

Sheet Benchmark détaillé
A1: MARQUE / PRODUIT | B1: IMPULSE | C1: IMPULSE | D1: IMPULSE | E1: IMPULSE | F1: IMPULSE | G1: NUTRIPURE | H1: NUTRIPURE | I1: NUTRIPURE | J1: NUTRIMUSCLE | K1: NUTRIMUSCLE | L1: NUTRIMUSCLE | M1: NUTRIMUSCLE | N1: NUTRIMUSCLE | O1: NUTRIMUSCLE | P1: NUTRIMUSCLE | Q1: NUTRIMUSCLE | R1: NUTRI&CO | S1: NUTRI&CO | T1: AQEELAB | U1: ERIC FAVRE | V1: ERIC FAVRE | W1: ERIC FAVRE | X1: ERIC FAVRE | Y1: ERIC FAVRE | Z1: ERIC FAVRE | AA1: ERIC FAVRE | AB1: ERIC FAVRE | AC1: EAFIT | AD1: EAFIT | AE1: EAFIT | AF1: EAFIT | AG1: EAFIT | AH1: EAFIT | AI1: DECATHLON | AJ1: DECATHLON | AK1: BULK | AL1: BULK | AM1: BULK | AN1: BULK | AO1: BULK | AP1: BULK | AQ1: MYPROTEIN | AR1: MYPROTEIN | AS1: MYPROTEIN | AT1: MYPROTEIN | AU1: MYPROTEIN | AV1: MYPROTEIN | AW1: PROZIS | AX1: PROZIS | AY1: PROZIS | AZ1: PROZIS | BA1: PROZIS | BB1: FOODSPRING | BC1: ESN | BD1: ESN | BE1: ESN | BF1: ESN | BG1: ESN | BH1: BIOTECHUSA | BI1: BIOTECHUSA | BJ1: BIOTECHUSA | BK1: BIOTECHUSA | BL1: BIOTECHUSA
A2: RÉFÉRENCE | B2: Whey Isolate (750g chocolat) | C2: Whey Isolate (750g vanille) | D2: Whey Isolate (750g nature) | E2: Whey Recovery (525g chocolat) | F2: Whey Recovery (525g vanille) | G2: Whey Isolat Native 750g (750g chocolat) | H2: Whey Isolat Native 2kg (2kg chocolat) | I2: Whey Isolat Native 4kg (4kg chocolat) | J2: Whey Native Isolate 500g (500g chocolat) | K2: Whey Native Isolate (1kg chocolat) | L2: Whey Native Isolate 2,25kg (2.25kg chocolat) | M2: Whey Native Isolate 4kg (4kg chocolat) | N2: Whey Native Concentrat 500g (500g chocolat) | O2: Whey Native Concentrat (1kg chocolat) | P2: Whey Native Concentrat 2,25kg (2.25kg chocolat) | Q2: Whey Native Concentrat 4kg (4kg chocolat) | R2: Whey Isolate Native 900g (900g chocolat) | S2: Whey Concentrée Native 900g (900g chocolat) | T2: Whey Native 810g (810g chocolat) | U2: Iso Zero 100% Whey Protéine 500g (500g cookies cream) | V2: Iso Zero 100% Whey Protéine 1,5kg (1.5kg chocolat) | W2: Iso Zero 100% Whey Protéine 2kg (2kg chocotella) | X2: Whey Optimax Protein 500g (500g biscuit cookie) | Y2: Whey Optimax Protein 1,5kg (1.5kg chocolat) | Z2: Whey Zero Protéine 2kg (2kg chocolat) | AA2: Iso Fusion Protein Complex 750g (750g biscuit cookie) | AB2: Iso Fusion Protein Complex 2kg (2kg biscuit cookie) | AC2: Pure Isolate 750g (750g chocolat) | AD2: Pure Isolate Premium 750g (750g citron) | AE2: Pure Whey Protein 750g (750g double chocolat) | AF2: Mega Whey Creatine Complex 750g (750g chocolat) | AG2: Pure Whey Protein 850g (850g double chocolat) | AH2: Pure Whey Protein 2.2kg (2.2kg double chocolat) | AI2: Pure Whey 100% Isolate 900g (900g chocolat) | AJ2: Whey Protein 900g (Concentrat) (900g chocolat) | AK2: Pure Whey Isolate 1kg (1kg chocolat) | AL2: Pure Whey Isolate 2,5kg (2.5kg chocolat) | AM2: Pure Whey Protein 1kg (1kg chocolat) | AN2: Pure Whey Protein 2,5kg (2.5kg chocolat) | AO2: Pure Whey Protein 5kg (5kg chocolat) | AP2: Clear Whey Isolate 500g (500g fraise) | AQ2: Impact Whey Isolate 1kg (1kg chocolat) | AR2: Impact Whey Isolate 2,5kg (2.5kg chocolat) | AS2: Impact Whey Protein 1kg (1kg chocolat) | AT2: Impact Whey Protein 2,5kg (2.5kg chocolat) | AU2: Impact Whey Protein 5kg (Sans arôme) (5kg sans arôme) | AV2: Clear Whey Isolate 875g (875g fraise) | AW2: Zero Diet Whey 750g (750g brownie au chocolat) | AX2: 100% Real Whey Isolate 1000g (1kg chocolat) | AY2: 100% Real Whey Protein 907g (907g chocolat) | AZ2: 100% Real Whey Protein 2000g (2kg chocolat) | BA2: 100% Whey Hydro Isolate 2000g (2kg chocolat) | BB2: Whey Protein 750g (750g vanille) | BC2: Iso Whey Protein Isolat 908g (908g chocolate) | BD2: Designer Whey Protein 908g (908g salted dark chocolate) | BE2: Basic Whey 1000g (1kg chocolate) | BF2: Designer Whey Protein 2000g (2kg salted dark chocolate) | BG2: Basic Whey 2000g (2kg chocolate) | BH2: Iso Whey Zero 908g (908g chocolat) | BI2: Iso Whey Zero 1816g (1.816kg chocolat) | BJ2: 100% Pure Whey 400g (400g chocolat) | BK2: 100% Pure Whey 1000g (1kg chocolat) | BL2: 100% Pure Whey 2000g (2kg chocolat)
A3: IDENTIFICATION
A4: Type de whey | B4: isolat natif (natif) | C4: isolat natif (natif) | D4: isolat natif (natif) | E4: concentrat fromagere | F4: concentrat fromagere | G4: isolat natif (natif) | H4: isolat natif (natif) | I4: isolat natif (natif) | J4: isolat natif (natif) | K4: isolat natif (natif) | L4: isolat natif (natif) | M4: isolat natif (natif) | N4: concentrat natif (natif) | O4: concentrat natif (natif) | P4: concentrat natif (natif) | Q4: concentrat natif (natif) | R4: isolat natif (natif) | S4: concentrat natif (natif) | T4: concentrat natif (natif) | U4: isolat fromagere | V4: isolat fromagere | W4: isolat fromagere | X4: concentrat fromagere | Y4: concentrat fromagere | Z4: concentrat fromagere | AA4: mix concentrat isolat | AB4: mix concentrat isolat | AC4: isolat fromagere | AD4: isolat fromagere | AE4: concentrat fromagere | AF4: concentrat fromagere | AG4: concentrat fromagere | AH4: concentrat fromagere | AI4: isolat fromagere | AJ4: concentrat fromagere | AK4: isolat fromagere | AL4: isolat fromagere | AM4: concentrat fromagere | AN4: concentrat fromagere | AO4: concentrat fromagere | AP4: clear hydrolysat | AQ4: isolat fromagere | AR4: isolat fromagere | AS4: concentrat fromagere | AT4: concentrat fromagere | AU4: concentrat fromagere | AV4: clear hydrolysat | AW4: isolat fromagere | AX4: isolat fromagere | AY4: concentrat fromagere | AZ4: concentrat fromagere | BA4: clear hydrolysat | BB4: concentrat fromagere | BC4: isolat fromagere | BD4: concentrat fromagere | BE4: concentrat fromagere | BF4: concentrat fromagere | BG4: concentrat fromagere | BH4: isolat fromagere | BI4: isolat fromagere | BJ4: concentrat fromagere | BK4: concentrat fromagere | BL4: concentrat fromagere
A5: Poids net (g) | B5: 750 | C5: 750 | D5: 750 | E5: 525 | F5: 525 | G5: 750 | H5: 2000 | I5: 4000 | J5: 500 | K5: 1000 | L5: 2250 | M5: 4000 | N5: 500 | O5: 1000 | P5: 2250 | Q5: 4000 | R5: 900 | S5: 900 | T5: 810 | U5: 500 | V5: 1500 | W5: 2000 | X5: 500 | Y5: 1500 | Z5: 2000 | AA5: 750 | AB5: 2000 | AC5: 750 | AD5: 750 | AE5: 750 | AF5: 750 | AG5: 850 | AH5: 2200 | AI5: 900 | AJ5: 900 | AK5: 1000 | AL5: 2500 | AM5: 1000 | AN5: 2500 | AO5: 5000 | AP5: 500 | AQ5: 1000 | AR5: 2500 | AS5: 1000 | AT5: 2500 | AU5: 5000 | AV5: 875 | AW5: 750 | AX5: 1000 | AY5: 907 | AZ5: 2000 | BA5: 2000 | BB5: 750 | BC5: 908 | BD5: 908 | BE5: 1000 | BF5: 2000 | BG5: 2000 | BH5: 908 | BI5: 1816 | BJ5: 400 | BK5: 1000 | BL5: 2000
A6: Arôme pivot | B6: chocolat | C6: vanille | D6: nature | E6: chocolat | F6: vanille | G6: chocolat | H6: chocolat | I6: chocolat | J6: chocolat | K6: chocolat | L6: chocolat | M6: chocolat | N6: chocolat | O6: chocolat | P6: chocolat | Q6: chocolat | R6: chocolat | S6: chocolat | T6: chocolat | U6: cookies cream | V6: chocolat | W6: chocotella | X6: biscuit cookie | Y6: chocolat | Z6: chocolat | AA6: biscuit cookie | AB6: biscuit cookie | AC6: chocolat | AD6: citron | AE6: double chocolat | AF6: chocolat | AG6: double chocolat | AH6: double chocolat | AI6: chocolat | AJ6: chocolat | AK6: chocolat | AL6: chocolat | AM6: chocolat | AN6: chocolat | AO6: chocolat | AP6: fraise | AQ6: chocolat | AR6: chocolat | AS6: chocolat | AT6: chocolat | AU6: sans arôme | AV6: fraise | AW6: brownie au chocolat | AX6: chocolat | AY6: chocolat | AZ6: chocolat | BA6: chocolat | BB6: vanille | BC6: chocolate | BD6: salted dark chocolate | BE6: chocolate | BF6: salted dark chocolate | BG6: chocolate | BH6: chocolat | BI6: chocolat | BJ6: chocolat | BK6: chocolat | BL6: chocolat
A7: Arômes disponibles (sample) | B7: chocolat, vanille, nature | C7: chocolat, vanille, nature | D7: chocolat, vanille, nature | E7: chocolat, vanille | F7: chocolat, vanille | G7: Chocolat, Vanille, Neutre, Noisette, Fraise | H7: Chocolat, Vanille, Neutre, Noisette, Fraise | I7: chocolat, vanille, neutre, noisette, fraise | J7: chocolat, nature, vanille, choco cookie, fraise, banane | K7: Chocolat, Vanille, Neutre, Fraise | L7: chocolat, nature, vanille, choco cookie, fraise, banane | M7: chocolat, nature, vanille, choco cookie, fraise, banane | N7: chocolat, vanille, nature | O7: Chocolat, Vanille, Neutre, Fraise | P7: chocolat, vanille, nature | Q7: chocolat, vanille, nature | R7: chocolat, vanille, sans arôme | S7: chocolat, vanille | T7: chocolat, vanille | U7: chocolat, vanille, cookies cream, chocotella, pistache | V7: chocolat, vanille, cookies cream, chocotella, pistache, framboisier, café latte | W7: chocolat, vanille, cookies cream, chocotella, pistache, framboisier, café latte | X7: chocolat, vanille, biscuit cookie | Y7: chocolat, vanille, biscuit cookie, chocotella | Z7: chocolat, vanille, cookies cream | AA7: biscuit cookie, vanille, chocotella | AB7: biscuit cookie, vanille, chocotella | AC7: chocolat, vanille, fruits rouges | AD7: citron | AE7: double chocolat, café, chocolat noisette, vanille intense, caramel, fraise | AF7: chocolat, vanille | AG7: double chocolat, café, chocolat noisette, vanille intense, caramel | AH7: double chocolat, vanille intense, fraise, myrtille, chocolat noisette | AI7: Cacao, Vanille, Café Latte, Neutre | AJ7: Cacao, Vanille | AK7: Choco, Vanille, Fraise, Neutre | AL7: Choco, Vanille, Fraise, Neutre | AM7: +20 saveurs (Choco, Vanille, Fraise, Neutre...) | AN7: +20 saveurs | AO7: +20 saveurs | AP7: Fraise, Pastèque, Pêche, Ananas... | AQ7: +40 saveurs | AR7: +40 saveurs | AS7: +40 saveurs (Choco Brownie, Vanille, Fraise, Neutre...) | AT7: +40 saveurs | AU7: sans arôme | AV7: Fraise, Pastèque, Limonade, Tropical... | AW7: brownie au chocolat, cappuccino, cookies et crème, vanille, chocolat blanc aux framboises | AX7: chocolat, chocolat noir, double chocolat, vanille, cappuccino | AY7: chocolat, chocolat noir, chocolat au lait, brownie au chocolat, vanille, cookies et crème | AZ7: chocolat, chocolat noir, vanille, cookies et crème, brownie au chocolat | BA7: chocolat, brownie au chocolat, chocolat blanc, vanille, fraise | BB7: vanille, chocolat, fraise, cookies et crème | BC7: cinnamon cereal, chocolate, vanilla, strawberry | BD7: salted dark chocolate, vanilla milk, white chocolate pistachio, almond coconut, cinnamon cereal | BE7: vanilla, chocolate, strawberry | BF7: salted dark chocolate, vanilla milk, almond coconut, cinnamon cereal | BG7: vanilla, chocolate, strawberry | BH7: chocolat, chocolat blanc, vanille, caramel catalan, banane, black biscuit | BI7: chocolat, chocolat blanc, vanille, caramel catalan, banane | BJ7: chocolat, vanille bourbon, fraise, noisettes, beurre de cacahuète au chocolat, cookies & cream | BK7: chocolat, vanille bourbon, fraise, noisettes, cookies & cream | BL7: chocolat, vanille bourbon, fraise, noisettes, cookies & cream
A8: Origine lait | B8: France | C8: France | D8: France | E8: UE | F8: UE | G8: France (pâturages) | H8: France (pâturages) | I8: France (pâturages) | J8: France (Lactalis) | K8: France (Lactalis) | L8: France (Lactalis) | M8: France (Lactalis) | N8: France (Lactalis) | O8: France (Lactalis) | P8: France (Lactalis) | Q8: France (Lactalis) | R8: France | S8: France (pâturages) | T8: France | AI8: UE (NL, IE, DK) | AJ8: UE (NL, IE, DK) | AK8: UE | AL8: UE | AM8: UE | AN8: UE | AO8: UE | AP8: UE | AQ8: UE | AR8: UE | AS8: UE (UK, IE, NL...) | AT8: UE | AU8: UE | AV8: UE | BB8: Pâturages (vaches en plein air)
A9: Certifications | E9: Creapure®, Peptan® | F9: Creapure®, Peptan® | G9: EN 17444 | H9: EN 17444 | I9: EN 17444 | J9: Certifié, lait Lactalis FR | K9: Certifié, lait Lactalis FR | L9: Certifié, lait Lactalis FR | M9: Certifié, lait Lactalis FR | N9: Certifié, lait Lactalis FR | O9: Certifié, lait Lactalis FR | P9: Certifié, lait Lactalis FR | Q9: Certifié, lait Lactalis FR | T9: Testée labo indépendant | U9: Nutricontrole | V9: Nutricontrole | W9: Nutricontrole | X9: Nutricontrole | Y9: Nutricontrole | Z9: Nutricontrole | AA9: Nutricontrole | AB9: Nutricontrole | AC9: Marque N°1 en pharmacie | AD9: Marque N°1 en pharmacie | AE9: Marque N°1 en pharmacie | AF9: Marque N°1 en pharmacie | AG9: Marque N°1 en pharmacie | AH9: Marque N°1 en pharmacie | AI9: IFS Food, EN 17444 | AJ9: IFS Food, EN 17444 | AK9: Informed Sport | AL9: Informed Sport | AM9: Informed Sport | AN9: Informed Sport | AO9: Informed Sport | AP9: Informed Sport | AQ9: Informed Choice | AR9: Informed Choice | AS9: Informed Choice | AT9: Informed Choice | AU9: Informed Choice | AV9: Informed Choice | BC9: Laborgeprüft | BD9: Laborgeprüft | BE9: Laborgeprüft | BF9: Laborgeprüft | BG9: Laborgeprüft
A10: Native / Fromagère | B10: native | C10: native | D10: native | E10: fromagere | F10: fromagere | G10: native | H10: native | I10: native | J10: native | K10: native | L10: native | M10: native | N10: native | O10: native | P10: native | Q10: native | R10: native | S10: native | T10: native | U10: fromagere | V10: fromagere | W10: fromagere | X10: fromagere | Y10: fromagere | Z10: fromagere | AA10: fromagere | AB10: fromagere | AC10: fromagere | AD10: fromagere | AE10: fromagere | AF10: fromagere | AG10: fromagere | AH10: fromagere | AI10: fromagere | AJ10: fromagere | AK10: fromagere | AL10: fromagere | AM10: fromagere | AN10: fromagere | AO10: fromagere | AP10: fromagere | AQ10: fromagere | AR10: fromagere | AS10: fromagere | AT10: fromagere | AU10: fromagere | AV10: fromagere | AW10: fromagere | AX10: fromagere | AY10: fromagere | AZ10: fromagere | BA10: fromagere | BB10: fromagere | BC10: fromagere | BD10: fromagere | BE10: fromagere | BF10: fromagere | BG10: fromagere | BH10: fromagere | BI10: fromagere | BJ10: fromagere | BK10: fromagere | BL10: fromagere
A11: FORMULE & NUTRITION
A12: % protéines / 100g | B12: 85 | C12: 85 | D12: 85 | E12: 60 | F12: 60 | G12: 94 | H12: 94 | I12: 85 | J12: 87 | K12: 85 | L12: 87 | M12: 87 | N12: 80 | O12: 80 | P12: 80 | Q12: 80 | R12: 94 | S12: 75 | T12: 94 | U12: 83 | V12: 83 | W12: 83 | X12: 73 | Y12: 73 | Z12: 75 | AA12: 81 | AB12: 81 | AC12: 81 | AD12: 79 | AE12: 77 | AF12: 73 | AG12: 77 | AH12: 77 | AI12: 82 | AJ12: 70 | AK12: 90 | AL12: 90 | AM12: 82 | AN12: 82 | AO12: 82 | AP12: 72 | AQ12: 90 | AR12: 90 | AS12: 82 | AT12: 82 | AU12: 82 | AV12: 68 | AW12: 80 | AX12: 86 | AY12: 71 | AZ12: 71 | BA12: 88 | BB12: 81 | BC12: 84 | BD12: 73 | BE12: 74 | BF12: 73 | BG12: 74 | BH12: 84 | BI12: 84 | BJ12: 76 | BK12: 76 | BL12: 76
A13: Protéines / portion (g) | B13: 25.5 | C13: 25.5 | D13: 25.5 | E13: 21 | F13: 21 | G13: 25 | H13: 25 | I13: 25 | J13: 25 | K13: 24 | L13: 25 | M13: 25 | N13: 24 | O13: 24 | P13: 24 | Q13: 24 | R13: 28 | S13: 22.1 | T13: 28.2 | U13: 25 | V13: 25 | W13: 25 | X13: 22 | Y13: 22 | Z13: 22.5 | AA13: 24.4 | AB13: 24.4 | AC13: 25 | AD13: 24 | AE13: 31 | AF13: 44 | AG13: 31 | AH13: 31 | AI13: 25 | AJ13: 21 | AK13: 26 | AL13: 26 | AM13: 22 | AN13: 22 | AO13: 22 | AP13: 20 | AQ13: 25 | AR13: 25 | AS13: 23 | AT13: 23 | AU13: 23 | AV13: 20 | AW13: 24 | AX13: 25.8 | AY13: 21.3 | AZ13: 21.3 | BA13: 26.4 | BB13: 24.3 | BC13: 25.2 | BD13: 21.9 | BE13: 22.2 | BF13: 21.9 | BG13: 22.2 | BH13: 21 | BI13: 21 | BJ13: 21 | BK13: 21 | BL13: 21
A14: Taille portion (g) | B14: 30 | C14: 30 | D14: 30 | E14: 35 | F14: 35 | G14: 30 | H14: 30 | I14: 30 | J14: 30 | K14: 30 | L14: 30 | M14: 30 | N14: 30 | O14: 30 | P14: 30 | Q14: 30 | R14: 30 | S14: 30 | T14: 30 | U14: 30 | V14: 30 | W14: 30 | X14: 30 | Y14: 30 | Z14: 30 | AA14: 30 | AB14: 30 | AC14: 30 | AD14: 30 | AE14: 40 | AF14: 60 | AG14: 40 | AH14: 40 | AI14: 30 | AJ14: 30 | AK14: 30 | AL14: 30 | AM14: 30 | AN14: 30 | AO14: 30 | AP14: 30 | AQ14: 25 | AR14: 25 | AS14: 25 | AT14: 25 | AU14: 25 | AV14: 25 | AW14: 30 | AX14: 30 | AY14: 30 | AZ14: 30 | BA14: 30 | BB14: 30 | BC14: 30 | BD14: 30 | BE14: 30 | BF14: 30 | BG14: 30 | BH14: 25 | BI14: 25 | BJ14: 30 | BK14: 30 | BL14: 30
A15: Nb portions / format | B15: 25 | C15: 25 | D15: 25 | E15: 15 | F15: 15 | G15: 25 | H15: 66 | I15: 133 | J15: 16 | K15: 33 | L15: 75 | M15: 133 | N15: 16 | O15: 33 | P15: 75 | Q15: 133 | R15: 30 | S15: 30 | T15: 27 | U15: 16 | V15: 50 | W15: 66 | X15: 16 | Y15: 50 | Z15: 66 | AA15: 25 | AB15: 66 | AC15: 25 | AD15: 25 | AE15: 19 | AF15: 12 | AG15: 21 | AH15: 55 | AI15: 30 | AJ15: 30 | AK15: 33 | AL15: 83 | AM15: 33 | AN15: 83 | AO15: 166 | AP15: 16 | AQ15: 40 | AR15: 100 | AS15: 40 | AT15: 100 | AU15: 200 | AV15: 35 | AW15: 25 | AX15: 33 | AY15: 30 | AZ15: 66 | BA15: 66 | BB15: 25 | BC15: 30 | BD15: 30 | BE15: 33 | BF15: 66 | BG15: 66 | BH15: 36 | BI15: 72 | BJ15: 13 | BK15: 33 | BL15: 66
A16: BCAA / portion (g) | B16: 5.3 | C16: 5.3 | D16: 5.3 | G16: 5 | H16: 5 | I16: 5 | J16: 6 | K16: 6 | L16: 6 | M16: 6 | N16: 5 | O16: 5 | P16: 5 | Q16: 5 | R16: 6.9 | S16: 5.1 | T16: 6.6 | U16: 5.66 | V16: 5.66 | W16: 5.66 | X16: 3.74 | Y16: 3.74 | AA16: 4.1 | AB16: 4.1 | AC16: 5.5 | AD16: 5.2 | AE16: 7 | AF16: 10 | AG16: 7 | AH16: 7 | AI16: 6.3 | AJ16: 5.2 | AK16: 5.5 | AL16: 5.5 | AM16: 5 | AN16: 5 | AO16: 5 | AP16: 4 | AQ16: 5.5 | AR16: 5.5 | AS16: 4.5 | AT16: 4.5 | AU16: 4.5 | AV16: 4 | BC16: 6.36 | BD16: 6.93 | BE16: 6.51 | BF16: 6.93 | BG16: 6.51 | BH16: 4.35 | BI16: 4.35
A17: Glucides / portion (g) | B17: 1 | C17: 1 | D17: 1 | G17: 0.3 | H17: 0.3 | I17: 0.3 | J17: 1.5 | K17: 1.5 | L17: 1.5 | M17: 1.5 | N17: 3.5 | O17: 3.5 | P17: 3.5 | Q17: 3.5 | R17: 0.9 | S17: 4 | T17: 0.5 | U17: 0.5 | V17: 0.5 | W17: 0.5 | Z17: 3 | AA17: 1.4 | AB17: 1.4 | AC17: 1.4 | AD17: 0.5 | AE17: 4 | AF17: 4.3 | AG17: 4 | AH17: 4 | AI17: 2.3 | AJ17: 5.1 | AK17: 1.5 | AL17: 1.5 | AM17: 2 | AN17: 2 | AO17: 2 | AP17: 0.5 | AQ17: 1 | AR17: 1 | AS17: 2 | AT17: 2 | AU17: 2 | AV17: 0.5 | AW17: 1.5 | AX17: 1 | AY17: 2 | AZ17: 2 | BA17: 0.8 | BB17: 1.5 | BC17: 1.35 | BD17: 2.1 | BE17: 2.31 | BF17: 2.1 | BG17: 2.31 | BH17: 0.6 | BI17: 0.6 | BJ17: 1.4 | BK17: 1.4 | BL17: 1.4
A18: Lipides / portion (g) | B18: 0.5 | C18: 0.5 | D18: 0.5 | G18: 0.2 | H18: 0.2 | I18: 0.2 | J18: 0.8 | K18: 0.8 | L18: 0.8 | M18: 0.8 | N18: 1.5 | O18: 1.5 | P18: 1.5 | Q18: 1.5 | R18: 0.6 | S18: 0.4 | T18: 0.4 | U18: 0.4 | V18: 0.4 | W18: 0.4 | Z18: 1.4 | AA18: 1.6 | AB18: 1.6 | AC18: 0.5 | AD18: 0.3 | AE18: 1.7 | AF18: 2 | AG18: 1.7 | AH18: 1.7 | AI18: 0.6 | AJ18: 2.1 | AK18: 0.5 | AL18: 0.5 | AM18: 1 | AN18: 1 | AO18: 1 | AP18: 0.1 | AQ18: 0.5 | AR18: 0.5 | AS18: 1 | AT18: 1 | AU18: 1 | AV18: 0.1 | AW18: 0.8 | AX18: 0.5 | AY18: 1.9 | AZ18: 1.9 | BA18: 0.4 | BB18: 1.3 | BC18: 0.45 | BD18: 1.7 | BE18: 2.34 | BF18: 1.7 | BG18: 2.34 | BH18: 0.4 | BI18: 0.4 | BJ18: 1.8 | BK18: 1.8 | BL18: 1.8
A19: Lactose | B19: faible | C19: faible | D19: faible | E19: present | F19: present | G19: tres_faible | H19: tres_faible | I19: tres_faible | J19: faible | K19: faible | L19: faible | M19: faible | N19: present | O19: present | P19: present | Q19: present | R19: tres_faible | S19: faible | T19: faible | U19: tres_faible | V19: tres_faible | W19: tres_faible | AA19: faible | AB19: faible | AC19: tres_faible | AD19: tres_faible | AF19: present | AI19: faible | AJ19: present | AK19: faible | AL19: faible | AM19: present | AN19: present | AO19: present | AP19: tres_faible | AQ19: faible | AR19: faible | AS19: present | AT19: present | AU19: present | AV19: tres_faible | AW19: faible | AX19: tres_faible | AY19: present | AZ19: present | BA19: tres_faible | BB19: faible | BC19: tres_faible | BH19: tres_faible | BI19: tres_faible
A20: PRIX — 3 COUCHES (nominal / current / marché médian)
A21: Prix nominal (site propre, barré) | B21: 39.9 | C21: 39.9 | D21: 37.9 | E21: 39.9 | F21: 39.9 | G21: 39.9 | H21: 104.9 | I21: 179.9 | J21: 31.95 | K21: 57.95 | L21: 116.95 | M21: 190.95 | N21: 19.95 | O21: 37.95 | P21: 80.95 | Q21: 131.95 | R21: 54.9 | S21: 39.9 | T21: 45.95 | U21: 33.9 | V21: 79.9 | W21: 94.9 | X21: 29.9 | Y21: 59.9 | Z21: 82.9 | AA21: 41.9 | AB21: 65.9 | AC21: 45.9 | AD21: 45.9 | AE21: 34.9 | AF21: 39.99 | AG21: 38.9 | AH21: 80.99 | AI21: 39.99 | AJ21: 28.99 | AK21: 69.99 | AL21: 159.99 | AM21: 37.99 | AN21: 84.99 | AO21: 159.99 | AP21: 31.49 | AQ21: 57.99 | AR21: 124.99 | AS21: 41.99 | AT21: 84.99 | AU21: 188.99 | AV21: 49.99 | AW21: 37.99 | AX21: 53.99 | AY21: 34.99 | AZ21: 62.99 | BA21: 89.99 | BB21: 39.9 | BC21: 49.9 | BD21: 41.99 | BE21: 26.9 | BF21: 85.9 | BG21: 49.9 | BH21: 69.9 | BI21: 104.9 | BJ21: 32.9 | BK21: 54.9 | BL21: 89.9
A22: Prix actuel (site propre, affiché) | B22: 39.9 | C22: 39.9 | D22: 37.9 | E22: 39.9 | F22: 39.9 | G22: 39.9 | H22: 104.9 | I22: 179.9 | J22: 31.95 | K22: 57.95 | L22: 116.95 | M22: 190.95 | N22: 19.95 | O22: 37.95 | P22: 80.95 | Q22: 131.95 | R22: 54.9 | S22: 39.9 | T22: 45.95 | U22: 33.9 | V22: 79.9 | W22: 94.9 | X22: 29.9 | Y22: 59.9 | Z22: 82.9 | AA22: 41.9 | AB22: 65.9 | AC22: 45.9 | AD22: 45.9 | AE22: 34.9 | AF22: 39.99 | AG22: 38.9 | AH22: 80.99 | AI22: 39.99 | AJ22: 28.99 | AK22: 44.99 | AL22: 99.99 | AM22: 27.99 | AN22: 64.99 | AO22: 129.99 | AP22: 25.99 | AQ22: 57.99 | AR22: 124.99 | AS22: 17.99 | AT22: 40.99 | AU22: 91.1 | AV22: 49.99 | AW22: 37.99 | AX22: 53.99 | AY22: 34.99 | AZ22: 62.99 | BA22: 89.99 | BB22: 29.96 | BC22: 49.9 | BD22: 41.99 | BE22: 26.9 | BF22: 85.9 | BG22: 49.9 | BH22: 69.9 | BI22: 104.9 | BJ22: 32.9 | BK22: 54.9 | BL22: 89.9
A23: Prix médian marché (idealo/ledenicheur) | AM23: 23.99 | AP23: 22.25 | AQ23: 56.4 | AS23: 34.99 | AT23: 56.4 | AU23: 188.99 | BB23: 22.25 | BD23: 34.9 | BK23: 27.02
A24: Écart nominal → actuel (%) | B24: =IFERROR((B21-B22)/B21*100,"") | C24: =IFERROR((C21-C22)/C21*100,"") | D24: =IFERROR((D21-D22)/D21*100,"") | E24: =IFERROR((E21-E22)/E21*100,"") | F24: =IFERROR((F21-F22)/F21*100,"") | G24: =IFERROR((G21-G22)/G21*100,"") | H24: =IFERROR((H21-H22)/H21*100,"") | I24: =IFERROR((I21-I22)/I21*100,"") | ... BL24: =IFERROR((BL21-BL22)/BL21*100,"")
A25: Écart actuel → marché (%) | B25: =IFERROR((B22-B23)/B22*100,"") | C25: =IFERROR((C22-C23)/C22*100,"") | D25: =IFERROR((D22-D23)/D22*100,"") | E25: =IFERROR((E22-E23)/E22*100,"") | F25: =IFERROR((F22-F23)/F22*100,"") | G25: =IFERROR((G22-G23)/G22*100,"") | H25: =IFERROR((H22-H23)/H22*100,"") | I25: =IFERROR((I22-I23)/I22*100,"") | ... BL25: =IFERROR((BL22-BL23)/BL22*100,"")
A26: PRIX DÉRIVÉS (base = prix actuel site propre)
A27: Prix actuel / kg (€) | B27: =IFERROR(B22/(B5/1000),"") | C27: =IFERROR(C22/(C5/1000),"") | D27: =IFERROR(D22/(D5/1000),"") | E27: =IFERROR(E22/(E5/1000),"") | F27: =IFERROR(F22/(F5/1000),"") | G27: =IFERROR(G22/(G5/1000),"") | H27: =IFERROR(H22/(H5/1000),"") | I27: =IFERROR(I22/(I5/1000),"") | ... BL27: =IFERROR(BL22/(BL5/1000),"")
A28: Prix actuel / portion (€) | B28: =IFERROR(B22/B15,"") | C28: =IFERROR(C22/C15,"") | D28: =IFERROR(D22/D15,"") | E28: =IFERROR(E22/E15,"") | F28: =IFERROR(F22/F15,"") | G28: =IFERROR(G22/G15,"") | H28: =IFERROR(H22/H15,"") | I28: =IFERROR(I22/I15,"") | ... BL28: =IFERROR(BL22/BL15,"")
A29: Prix actuel / g de protéine (€) | B29: =IFERROR(B22/(B15*B13),"") | C29: =IFERROR(C22/(C15*C13),"") | D29: =IFERROR(D22/(D15*D13),"") | E29: =IFERROR(E22/(E15*E13),"") | F29: =IFERROR(F22/(F15*F13),"") | G29: =IFERROR(G22/(G15*G13),"") | H29: =IFERROR(H22/(H15*H13),"") | I29: =IFERROR(I22/(I15*I13),"") | ... BL29: =IFERROR(BL22/(BL15*BL13),"")
A30: Prix marché / g de protéine (€) | B30: =IFERROR(B23/(B15*B13),"") | C30: =IFERROR(C23/(C15*C13),"") | D30: =IFERROR(D23/(D15*D13),"") | E30: =IFERROR(E23/(E15*E13),"") | F30: =IFERROR(F23/(F15*F13),"") | G30: =IFERROR(G23/(G15*G13),"") | H30: =IFERROR(H23/(H15*H13),"") | I30: =IFERROR(I23/(I15*I13),"") | ... BL30: =IFERROR(BL23/(BL15*BL13),"")
A31: Prix abonnement (€ TTC) | T31: 36.76
A32: Remise abo (%) | T32: 20
A33: PRIX EFFECTIF (avec code influenceur appliqué sur prix actuel)
A34: Remise bas fourchette (%) | B34: =IFERROR(VLOOKUP(B1,'Discounts par marque'!$A:$G,3,FALSE),0) | C34: =IFERROR(VLOOKUP(C1,'Discounts par marque'!$A:$G,3,FALSE),0) | D34: =IFERROR(VLOOKUP(D1,'Discounts par marque'!$A:$G,3,FALSE),0) | E34: =IFERROR(VLOOKUP(E1,'Discounts par marque'!$A:$G,3,FALSE),0) | F34: =IFERROR(VLOOKUP(F1,'Discounts par marque'!$A:$G,3,FALSE),0) | G34: =IFERROR(VLOOKUP(G1,'Discounts par marque'!$A:$G,3,FALSE),0) | H34: =IFERROR(VLOOKUP(H1,'Discounts par marque'!$A:$G,3,FALSE),0) | I34: =IFERROR(VLOOKUP(I1,'Discounts par marque'!$A:$G,3,FALSE),0) | ... BL34: =IFERROR(VLOOKUP(BL1,'Discounts par marque'!$A:$G,3,FALSE),0)
A35: Remise client standard (%) | B35: =IFERROR(VLOOKUP(B1,'Discounts par marque'!$A:$G,4,FALSE),0) | C35: =IFERROR(VLOOKUP(C1,'Discounts par marque'!$A:$G,4,FALSE),0) | D35: =IFERROR(VLOOKUP(D1,'Discounts par marque'!$A:$G,4,FALSE),0) | E35: =IFERROR(VLOOKUP(E1,'Discounts par marque'!$A:$G,4,FALSE),0) | F35: =IFERROR(VLOOKUP(F1,'Discounts par marque'!$A:$G,4,FALSE),0) | G35: =IFERROR(VLOOKUP(G1,'Discounts par marque'!$A:$G,4,FALSE),0) | H35: =IFERROR(VLOOKUP(H1,'Discounts par marque'!$A:$G,4,FALSE),0) | I35: =IFERROR(VLOOKUP(I1,'Discounts par marque'!$A:$G,4,FALSE),0) | ... BL35: =IFERROR(VLOOKUP(BL1,'Discounts par marque'!$A:$G,4,FALSE),0)
A36: Remise client averti (%) | B36: =IFERROR(VLOOKUP(B1,'Discounts par marque'!$A:$G,5,FALSE),0) | C36: =IFERROR(VLOOKUP(C1,'Discounts par marque'!$A:$G,5,FALSE),0) | D36: =IFERROR(VLOOKUP(D1,'Discounts par marque'!$A:$G,5,FALSE),0) | E36: =IFERROR(VLOOKUP(E1,'Discounts par marque'!$A:$G,5,FALSE),0) | F36: =IFERROR(VLOOKUP(F1,'Discounts par marque'!$A:$G,5,FALSE),0) | G36: =IFERROR(VLOOKUP(G1,'Discounts par marque'!$A:$G,5,FALSE),0) | H36: =IFERROR(VLOOKUP(H1,'Discounts par marque'!$A:$G,5,FALSE),0) | I36: =IFERROR(VLOOKUP(I1,'Discounts par marque'!$A:$G,5,FALSE),0) | ... BL36: =IFERROR(VLOOKUP(BL1,'Discounts par marque'!$A:$G,5,FALSE),0)
A37: Remise plafond observé (%) | B37: =IFERROR(VLOOKUP(B1,'Discounts par marque'!$A:$G,6,FALSE),0) | C37: =IFERROR(VLOOKUP(C1,'Discounts par marque'!$A:$G,6,FALSE),0) | D37: =IFERROR(VLOOKUP(D1,'Discounts par marque'!$A:$G,6,FALSE),0) | E37: =IFERROR(VLOOKUP(E1,'Discounts par marque'!$A:$G,6,FALSE),0) | F37: =IFERROR(VLOOKUP(F1,'Discounts par marque'!$A:$G,6,FALSE),0) | G37: =IFERROR(VLOOKUP(G1,'Discounts par marque'!$A:$G,6,FALSE),0) | H37: =IFERROR(VLOOKUP(H1,'Discounts par marque'!$A:$G,6,FALSE),0) | I37: =IFERROR(VLOOKUP(I1,'Discounts par marque'!$A:$G,6,FALSE),0) | ... BL37: =IFERROR(VLOOKUP(BL1,'Discounts par marque'!$A:$G,6,FALSE),0)
A38: Prix client standard (€) | B38: =IFERROR(B22*(1-B35/100),"") | C38: =IFERROR(C22*(1-C35/100),"") | D38: =IFERROR(D22*(1-D35/100),"") | E38: =IFERROR(E22*(1-E35/100),"") | F38: =IFERROR(F22*(1-F35/100),"") | G38: =IFERROR(G22*(1-G35/100),"") | H38: =IFERROR(H22*(1-H35/100),"") | I38: =IFERROR(I22*(1-I35/100),"") | ... BL38: =IFERROR(BL22*(1-BL35/100),"")
A39: Prix client averti (€) | B39: =IFERROR(B22*(1-B36/100),"") | C39: =IFERROR(C22*(1-C36/100),"") | D39: =IFERROR(D22*(1-D36/100),"") | E39: =IFERROR(E22*(1-E36/100),"") | F39: =IFERROR(F22*(1-F36/100),"") | G39: =IFERROR(G22*(1-G36/100),"") | H39: =IFERROR(H22*(1-H36/100),"") | I39: =IFERROR(I22*(1-I36/100),"") | ... BL39: =IFERROR(BL22*(1-BL36/100),"")
A40: Prix plafond (€) | B40: =IFERROR(B22*(1-B37/100),"") | C40: =IFERROR(C22*(1-C37/100),"") | D40: =IFERROR(D22*(1-D37/100),"") | E40: =IFERROR(E22*(1-E37/100),"") | F40: =IFERROR(F22*(1-F37/100),"") | G40: =IFERROR(G22*(1-G37/100),"") | H40: =IFERROR(H22*(1-H37/100),"") | I40: =IFERROR(I22*(1-I37/100),"") | ... BL40: =IFERROR(BL22*(1-BL37/100),"")
A41: Prix client standard / kg (€) | B41: =IFERROR(B38/(B5/1000),"") | C41: =IFERROR(C38/(C5/1000),"") | D41: =IFERROR(D38/(D5/1000),"") | E41: =IFERROR(E38/(E5/1000),"") | F41: =IFERROR(F38/(F5/1000),"") | G41: =IFERROR(G38/(G5/1000),"") | H41: =IFERROR(H38/(H5/1000),"") | I41: =IFERROR(I38/(I5/1000),"") | ... BL41: =IFERROR(BL38/(BL5/1000),"")
A42: Prix client standard / g prot (€) | B42: =IFERROR(B38/(B15*B13),"") | C42: =IFERROR(C38/(C15*C13),"") | D42: =IFERROR(D38/(D15*D13),"") | E42: =IFERROR(E38/(E15*E13),"") | F42: =IFERROR(F38/(F15*F13),"") | G42: =IFERROR(G38/(G15*G13),"") | H42: =IFERROR(H38/(H15*H13),"") | I42: =IFERROR(I38/(I15*I13),"") | ... BL42: =IFERROR(BL38/(BL15*BL13),"")
A43: Prix client averti / g prot (€) | B43: =IFERROR(B39/(B15*B13),"") | C43: =IFERROR(C39/(C15*C13),"") | D43: =IFERROR(D39/(D15*D13),"") | E43: =IFERROR(E39/(E15*E13),"") | F43: =IFERROR(F39/(F15*F13),"") | G43: =IFERROR(G39/(G15*G13),"") | H43: =IFERROR(H39/(H15*H13),"") | I43: =IFERROR(I39/(I15*I13),"") | ... BL43: =IFERROR(BL39/(BL15*BL13),"")
A44: DISTRIBUTION & SOURCE
A45: Canaux de vente | B45: site_propre | C45: site_propre | D45: site_propre | E45: Site propre | F45: Site propre | G45: Site propre, Amazon | H45: Site propre, Amazon | I45: Site propre, Amazon | J45: Site propre, Amazon, revendeurs | K45: Site propre, Amazon, revendeurs | L45: Site propre, Amazon, revendeurs | M45: Site propre, Amazon, revendeurs | N45: Site propre, Amazon, revendeurs | O45: Site propre, Amazon, revendeurs | P45: Site propre, Amazon, revendeurs | Q45: Site propre, Amazon, revendeurs | R45: Site propre, Pharmacies, Amazon | S45: Site propre, Pharmacies, Amazon | T45: Site propre | U45: Site propre, Amazon | V45: Site propre, Amazon | W45: Site propre, Amazon | X45: Site propre, Amazon | Y45: Site propre, Amazon | Z45: Site propre, Amazon | AA45: Site propre, Amazon | AB45: Site propre, Amazon | AC45: Site propre, Amazon, Pharmacies | AD45: Site propre, Amazon, Pharmacies | AE45: Site propre, Amazon, Pharmacies | AF45: Site propre, Amazon, Pharmacies | AG45: Site propre, Amazon, Pharmacies | AH45: Site propre, Amazon, Pharmacies | AI45: Magasins Decathlon, Site | AJ45: Magasins Decathlon, Site | AK45: Site propre, Amazon | AL45: Site propre | AM45: Site propre, Amazon | AN45: Site propre | AO45: Site propre | AP45: Site propre | AQ45: Site propre, Amazon | AR45: Site propre, Amazon | AS45: Site propre, Amazon, revendeurs | AT45: Site propre | AU45: Site propre | AV45: Site propre, Amazon | AW45: Site propre, Amazon | AX45: Site propre, Amazon | AY45: Site propre, Amazon | AZ45: Site propre, Amazon | BA45: Site propre, Amazon | BB45: Site propre, Amazon, Pharmacies, GMS | BC45: Site propre, Amazon | BD45: Site propre, Amazon | BE45: Site propre, Amazon | BF45: Site propre, Amazon | BG45: Site propre, Amazon | BH45: Site propre, Amazon | BI45: Site propre, Amazon | BJ45: Site propre, Amazon | BK45: Site propre, Amazon | BL45: Site propre, Amazon
A46: Source URL (principale) | B46: https://impulse-nutrition.fr/products/whey-isolate-saveur-chocolat | C46: https://impulse-nutrition.fr/products/whey-isolate-saveur-vanille | D46: https://impulse-nutrition.fr/products/whey-isolate-nature | E46: https://impulse-nutrition.fr/products/whey-recovery-saveur-chocolat | F46: https://impulse-nutrition.fr/products/whey-recovery-saveur-vanille | G46: https://www.nutripure.fr/produits/whey-isolat-native-chocolat | H46: https://www.nutripure.fr/fr/musculation/147-1115-whey-chocolat-isolate.html#/332-poids_poudre-seau_2kg | I46: https://www.nutripure.fr/fr/musculation/147-674-whey-chocolat-isolate.html#/47-poids_poudre-seau_4kg | J46: https://www.nutrimuscle.com/products/whey-native-isolate | K46: https://www.nutrimuscle.com/products/whey-isolat-native | L46: https://www.nutrimuscle.com/products/whey-native-isolate | M46: https://www.nutrimuscle.com/products/whey-native-isolate | N46: https://www.nutrimuscle.com/products/whey-native | O46: https://www.nutrimuscle.com/products/whey-concentree-native | P46: https://www.nutrimuscle.com/products/whey-native | Q46: https://www.nutrimuscle.com/products/whey-native | R46: https://nutriandco.com/fr/produits/whey-isolate-native | S46: https://nutriandco.com/fr/produits/whey-native | T46: https://www.aqeelab-nutrition.fr/products/whey-native-fabriquee-en-france-lait-francais | U46: https://www.ericfavre.com/fr_fr/proteines/iso-zero-100-whey-proteine-cookies-cream-500g-p-194-o-1216.htm | V46: https://www.ericfavre.com/fr_fr/proteines/iso-zero-100-whey-proteine-choco-intense-1-5kg-p-194-o-1200.htm | W46: https://www.ericfavre.com/fr_fr/proteines/iso-zero-100-whey-proteine-chocotella-2kg-p-194-o-155.htm | X46: https://www.ericfavre.com/fr_fr/proteines/whey-optimax-protein-biscuit-cookie-500g-p-622-o-1369.htm | Y46: https://www.ericfavre.com/fr_fr/proteines/whey-optimax-protein-chocolat-1-5kg-p-622-o-1370.htm | Z46: https://www.ericfavre.com/fr_fr/proteines/whey-zero-chocolat-2kg-p-517-o-1093.htm | AA46: https://www.ericfavre.com/fr_fr/proteines/iso-fusion-biscuit-cookie-750g-p-907-o-1924.htm | AB46: https://www.ericfavre.com/fr_fr/proteines/iso-fusion-biscuit-cookie-2kg-p-907-o-1925.htm | AC46: https://www.eafit.com/eafit-pure-isolate.html | AD46: https://www.eafit.com/eafit-pure-isolate-premium.html | AE46: https://www.eafit.com/eafit-pure-whey.html | AF46: https://www.eafit.com/eafit-megawhey.html | AG46: https://www.eafit.com/eafit-pure-whey.html | AH46: https://www.eafit.com/eafit-pure-whey.html | AI46: https://www.decathlon.fr/p/mp/corength/whey-isolate-chocolat/_/R-p-336438 | AJ46: https://www.decathlon.fr/p/mp/corength/whey-chocolat-corength/_/R-p-336437 | AK46: https://www.bulk.com/fr/pure-whey-isolate-90.html | AL46: https://www.bulk.com/fr/pure-whey-isolate-90.html | AM46: https://www.bulk.com/fr/pure-whey-protein-1.html | AN46: https://www.bulk.com/fr/pure-whey-protein-1.html | AO46: https://www.bulk.com/fr/pure-whey-protein-1.html | AP46: https://www.bulk.com/fr/clear-whey-isolate.html | AQ46: https://fr.myprotein.com/p/nutrition-sportive/impact-whey-isolate/10852482/ | AR46: https://fr.myprotein.com/p/nutrition-sportive/impact-whey-isolate-framboise-poche-2.5-kg/10530927/ | AS46: https://fr.myprotein.com/p/nutrition-sportive/myprotein-impact-whey-protein-chocolate-1kg/11068071/ | AT46: https://fr.myprotein.com/p/nutrition-sportive/myprotein-impact-whey-protein-chocolate-nut-2.5kg/10530969/ | AU46: https://fr.myprotein.com/p/nutrition-sportive/impact-whey-protein/10530943/ | AV46: https://fr.myprotein.com/p/nutrition-sportive/clear-whey-isolate/12081395/ | AW46: https://www.prozis.com/fr/fr/prozis/zero-diet-whey-750-g | AX46: https://www.prozis.com/fr/fr/prozis/100-real-whey-isolate-1000-g | AY46: https://www.prozis.com/fr/fr/prozis/100-real-whey-protein-907g | AZ46: https://www.prozis.com/fr/fr/prozis/100-real-whey-protein-907g | BA46: https://www.prozis.com/fr/fr/prozis/100-whey-hydro-isolate-2000g | BB46: https://www.amazon.fr/foodspring-croissance-musculaire-solubilit%C3%A9-ultra-filtr%C3%A9e/dp/B0CTR3FZ7W | BC46: https://www.esn.com/products/esn-iso-whey-protein | BD46: https://www.esn.com/products/esn-designer-whey-protein | BE46: https://www.esn.com/products/basic-whey | BF46: https://www.esn.com/products/esn-designer-whey-protein | BG46: https://www.esn.com/products/basic-whey | BH46: https://shop.biotechusa.fr/products/iso-whey-zero-908-g | BI46: https://shop.biotechusa.fr/products/iso-whey-zero-poudre-de-proteine-isolat-1816-g | BJ46: https://shop.biotechusa.fr/products/100-pure-whey-400-g | BK46: https://shop.biotechusa.fr/products/100-pure-whey-renouvele-1000-g | BL46: https://shop.biotechusa.fr/products/100-pure-whey-2000-g
A47: Date snapshot | B47: 2026-04-14 | C47: 2026-04-14 | D47: 2026-04-14 | E47: 2026-04-14 | F47: 2026-04-14 | G47: 2026-04-14 | H47: 2026-04-14 | I47: 2026-04-14 | J47: 2026-04-14 | K47: 2026-04-14 | L47: 2026-04-14 | M47: 2026-04-14 | N47: 2026-04-14 | O47: 2026-04-14 | P47: 2026-04-14 | Q47: 2026-04-14 | R47: 2026-04-14 | S47: 2026-04-14 | T47: 2026-04-14 | U47: 2026-04-14 | V47: 2026-04-14 | W47: 2026-04-14 | X47: 2026-04-14 | Y47: 2026-04-14 | Z47: 2026-04-14 | AA47: 2026-04-14 | AB47: 2026-04-14 | AC47: 2026-04-14 | AD47: 2026-04-14 | AE47: 2026-04-14 | AF47: 2026-04-14 | AG47: 2026-04-14 | AH47: 2026-04-14 | AI47: 2026-04-14 | AJ47: 2026-04-14 | AK47: 2026-04-14 | AL47: 2026-04-14 | AM47: 2026-04-14 | AN47: 2026-04-14 | AO47: 2026-04-14 | AP47: 2026-04-14 | AQ47: 2026-04-14 | AR47: 2026-04-14 | AS47: 2026-04-14 | AT47: 2026-04-14 | AU47: 2026-04-14 | AV47: 2026-04-14 | AW47: 2026-04-14 | AX47: 2026-04-14 | AY47: 2026-04-14 | AZ47: 2026-04-14 | BA47: 2026-04-14 | BB47: 2026-04-14 | BC47: 2026-04-14 | BD47: 2026-04-14 | BE47: 2026-04-14 | BF47: 2026-04-14 | BG47: 2026-04-14 | BH47: 2026-04-14 | BI47: 2026-04-14 | BJ47: 2026-04-14 | BK47: 2026-04-14 | BL47: 2026-04-14
A48: Note gap catalogue/marché | E48: Blend recovery (concentrat whey + créatine Creapure 3g + collagène Peptan 5g + magnésium). Pas comparable 1-pour-1 aux whey pures — 60% protéines car le reste = additifs de récupération. | F48: Blend recovery (concentrat whey + créatine Creapure 3g + collagène Peptan 5g + magnésium). Pas comparable 1-pour-1 aux whey pures — 60% protéines car le reste = additifs de récupération. | G48: Prix marché = null (Nutripure vend uniquement sur site propre, pas de cross-retailers significatifs). Ancien 46€ sourcé via robshop.fr était un revendeur cher, pas un vrai marché médian. | H48: Confirmé via Playwright click sur variant radio Seau 2KG (id=332). Page nutripure.fr. Agent v2 avait mal lu '90€' (probablement le 'à partir de' affiché sur la page parent). | I48: Confirmé via Playwright click sur variant radio Seau 4KG (id=47). Prix réel 179,90€ (pas 159,90€ extrapolé). | K48: v1 avait 39.95€ (+45% correction) | O48: v1 avait 25.95€ (+46% correction) | AK48: Catalogue fictif majeur: 69.99€ barré vs 44.99€ réel (-36%) | AL48: Catalogue fictif fort: 159.99€ vs 99.99€ réel (-37%) | AM48: Catalogue partiellement fictif: barré 37.99€ vs current 27.99€ vs marché 23.99€ | AN48: Catalogue fictif: 84.99€ barré vs 64.99€ réel (-23%) | AO48: Catalogue fictif: 159.99€ vs 129.99€ payé (-19%) | AP48: Catalogue 31.49€ barré vs 25.99€ payé (-17%). Marché 22.25€ | AQ48: Isolate EXCLU de la promo -30% MyProtein. Prix current = prix nominal (pas de discount automatique). Revert de l'ancienne estimation ×0.7. | AR48: Confirmé via variant Framboise 2.5kg (10530927) : 124.99€ affiché sans strikethrough. Isolate exclu de la promo -30%. | AS48: Prix actuel = 17.99€ sur fr.myprotein.com/.../11068071/ (scraped Playwright 2026-04-14). Promo site -30% + extra app ramène à 17.99 vs 41.99 nominal (soit -57%). Pattern MyProtein Whey Protein uniquement. | AT48: Prix scrapé via variant Chocolate Nut 2.5kg (10530969) : 84.99€ barré / 40.99€ actuel. Promo -52%. Playwright 2026-04-14. | AU48: 5kg n'existe qu'en 'Sans arôme' (chocolat inexistant). Current price = extrapolation du ratio 2.5kg (40.99/84.99=0.482) : 188.99 × 0.482 ≈ 91.10€. | AV48: Clear Whey exclu de la promo -30% (mention explicite). Format 875g max (pas de 1kg). Confirmé via scraping 12081395. | BB48: Site foodspring.fr = DNS dead (brand pas disponible en FR direct). Prix récupéré via Amazon FR fiche vanille 750g : 29,96€ current (39,90€ RRP affiché). Agent v2 avait 32,95€ via revendeur paraplus.fr, désormais obsolète. | BD48: Prix réel confirmé 41.99€ (vs 42.90€ ancien). Drift mineur sans promo. | BJ48: 8.2€/100g vs 5.5€/100g sur format 1kg (petit format plus cher) | BK48: GROS ÉCART : site marque 54.90€ vs idealo 27.02€ (-51%). Cross-retailers beaucoup moins cher. | BL48: Cohérent avec 1kg : site marque surcoté vs cross-retailers (~-40-50%)

Sheet Synthèse prix
A1: Marque | B1: Produit | C1: Type | D1: Natif/Fromagère | E1: Format (g) | F1: Nb portions | G1: Prot/portion (g) | H1: Prix nominal (€) | I1: Prix actuel (€) | J1: Prix marché (€) | K1: Gap nominal→actuel (%) | L1: Gap actuel→marché (%) | M1: Prix actuel /kg | N1: Prix actuel /g prot | O1: Prix abo (€) | P1: % abo | Q1: Remise client standard (%) | R1: Remise client averti (%) | S1: Prix client standard (€) | T1: Prix client standard /g prot | U1: Prix client averti (€) | V1: Prix client averti /g prot | W1: Source URL | X1: Gap note
A2: ='Benchmark détaillé'!B1 | B2: Whey Isolate | C2: ='Benchmark détaillé'!B4 | D2: ='Benchmark détaillé'!B10 | E2: ='Benchmark détaillé'!B5 | F2: ='Benchmark détaillé'!B15 | G2: ='Benchmark détaillé'!B13 | H2: ='Benchmark détaillé'!B21 | I2: ='Benchmark détaillé'!B22 | J2: ='Benchmark détaillé'!B23 | K2: =IFERROR((H2-I2)/H2*100,"") | L2: =IFERROR((I2-J2)/I2*100,"") | M2: =IFERROR(I2/(E2/1000),"") | N2: =IFERROR(I2/(F2*G2),"") | O2: ='Benchmark détaillé'!B31 | P2: ='Benchmark détaillé'!B32 | Q2: =IFERROR(VLOOKUP(A2,'Discounts par marque'!$A:$G,4,FALSE),0) | R2: =IFERROR(VLOOKUP(A2,'Discounts par marque'!$A:$G,5,FALSE),0) | S2: =IFERROR(I2*(1-Q2/100),"") | T2: =IFERROR(S2/(F2*G2),"") | U2: =IFERROR(I2*(1-R2/100),"") | V2: =IFERROR(U2/(F2*G2),"") | W2: https://impulse-nutrition.fr/products/whey-isolate-saveur-chocolat
A3: ='Benchmark détaillé'!C1 | B3: Whey Isolate | C3: ='Benchmark détaillé'!C4 | D3: ='Benchmark détaillé'!C10 | E3: ='Benchmark détaillé'!C5 | F3: ='Benchmark détaillé'!C15 | G3: ='Benchmark détaillé'!C13 | H3: ='Benchmark détaillé'!C21 | I3: ='Benchmark détaillé'!C22 | J3: ='Benchmark détaillé'!C23 | K3: =IFERROR((H3-I3)/H3*100,"") | L3: =IFERROR((I3-J3)/I3*100,"") | M3: =IFERROR(I3/(E3/1000),"") | N3: =IFERROR(I3/(F3*G3),"") | O3: ='Benchmark détaillé'!C31 | P3: ='Benchmark détaillé'!C32 | Q3: =IFERROR(VLOOKUP(A3,'Discounts par marque'!$A:$G,4,FALSE),0) | R3: =IFERROR(VLOOKUP(A3,'Discounts par marque'!$A:$G,5,FALSE),0) | S3: =IFERROR(I3*(1-Q3/100),"") | T3: =IFERROR(S3/(F3*G3),"") | U3: =IFERROR(I3*(1-R3/100),"") | V3: =IFERROR(U3/(F3*G3),"") | W3: https://impulse-nutrition.fr/products/whey-isolate-saveur-vanille
A4: ='Benchmark détaillé'!D1 | B4: Whey Isolate | C4: ='Benchmark détaillé'!D4 | D4: ='Benchmark détaillé'!D10 | E4: ='Benchmark détaillé'!D5 | F4: ='Benchmark détaillé'!D15 | G4: ='Benchmark détaillé'!D13 | H4: ='Benchmark détaillé'!D21 | I4: ='Benchmark détaillé'!D22 | J4: ='Benchmark détaillé'!D23 | K4: =IFERROR((H4-I4)/H4*100,"") | L4: =IFERROR((I4-J4)/I4*100,"") | M4: =IFERROR(I4/(E4/1000),"") | N4: =IFERROR(I4/(F4*G4),"") | O4: ='Benchmark détaillé'!D31 | P4: ='Benchmark détaillé'!D32 | Q4: =IFERROR(VLOOKUP(A4,'Discounts par marque'!$A:$G,4,FALSE),0) | R4: =IFERROR(VLOOKUP(A4,'Discounts par marque'!$A:$G,5,FALSE),0) | S4: =IFERROR(I4*(1-Q4/100),"") | T4: =IFERROR(S4/(F4*G4),"") | U4: =IFERROR(I4*(1-R4/100),"") | V4: =IFERROR(U4/(F4*G4),"") | W4: https://impulse-nutrition.fr/products/whey-isolate-nature
A5: ='Benchmark détaillé'!E1 | B5: Whey Recovery | C5: ='Benchmark détaillé'!E4 | D5: ='Benchmark détaillé'!E10 | E5: ='Benchmark détaillé'!E5 | F5: ='Benchmark détaillé'!E15 | G5: ='Benchmark détaillé'!E13 | H5: ='Benchmark détaillé'!E21 | I5: ='Benchmark détaillé'!E22 | J5: ='Benchmark détaillé'!E23 | K5: =IFERROR((H5-I5)/H5*100,"") | L5: =IFERROR((I5-J5)/I5*100,"") | M5: =IFERROR(I5/(E5/1000),"") | N5: =IFERROR(I5/(F5*G5),"") | O5: ='Benchmark détaillé'!E31 | P5: ='Benchmark détaillé'!E32 | Q5: =IFERROR(VLOOKUP(A5,'Discounts par marque'!$A:$G,4,FALSE),0) | R5: =IFERROR(VLOOKUP(A5,'Discounts par marque'!$A:$G,5,FALSE),0) | S5: =IFERROR(I5*(1-Q5/100),"") | T5: =IFERROR(S5/(F5*G5),"") | U5: =IFERROR(I5*(1-R5/100),"") | V5: =IFERROR(U5/(F5*G5),"") | W5: https://impulse-nutrition.fr/products/whey-recovery-saveur-chocolat | X5: Blend recovery (concentrat whey + créatine Creapure 3g + collagène Peptan 5g + magnésium). Pas comparable 1-pour-1 aux whey pures — 60% protéines car le reste = additifs de récupération.
A6: ='Benchmark détaillé'!F1 | B6: Whey Recovery | C6: ='Benchmark détaillé'!F4 | D6: ='Benchmark détaillé'!F10 | E6: ='Benchmark détaillé'!F5 | F6: ='Benchmark détaillé'!F15 | G6: ='Benchmark détaillé'!F13 | H6: ='Benchmark détaillé'!F21 | I6: ='Benchmark détaillé'!F22 | J6: ='Benchmark détaillé'!F23 | K6: =IFERROR((H6-I6)/H6*100,"") | L6: =IFERROR((I6-J6)/I6*100,"") | M6: =IFERROR(I6/(E6/1000),"") | N6: =IFERROR(I6/(F6*G6),"") | O6: ='Benchmark détaillé'!F31 | P6: ='Benchmark détaillé'!F32 | Q6: =IFERROR(VLOOKUP(A6,'Discounts par marque'!$A:$G,4,FALSE),0) | R6: =IFERROR(VLOOKUP(A6,'Discounts par marque'!$A:$G,5,FALSE),0) | S6: =IFERROR(I6*(1-Q6/100),"") | T6: =IFERROR(S6/(F6*G6),"") | U6: =IFERROR(I6*(1-R6/100),"") | V6: =IFERROR(U6/(F6*G6),"") | W6: https://impulse-nutrition.fr/products/whey-recovery-saveur-vanille | X6: Blend recovery (concentrat whey + créatine Creapure 3g + collagène Peptan 5g + magnésium). Pas comparable 1-pour-1 aux whey pures — 60% protéines car le reste = additifs de récupération.
A7: ='Benchmark détaillé'!G1 | B7: Whey Isolat Native 750g | C7: ='Benchmark détaillé'!G4 | D7: ='Benchmark détaillé'!G10 | E7: ='Benchmark détaillé'!G5 | F7: ='Benchmark détaillé'!G15 | G7: ='Benchmark détaillé'!G13 | H7: ='Benchmark détaillé'!G21 | I7: ='Benchmark détaillé'!G22 | J7: ='Benchmark détaillé'!G23 | K7: =IFERROR((H7-I7)/H7*100,"") | L7: =IFERROR((I7-J7)/I7*100,"") | M7: =IFERROR(I7/(E7/1000),"") | N7: =IFERROR(I7/(F7*G7),"") | O7: ='Benchmark détaillé'!G31 | P7: ='Benchmark détaillé'!G32 | Q7: =IFERROR(VLOOKUP(A7,'Discounts par marque'!$A:$G,4,FALSE),0) | R7: =IFERROR(VLOOKUP(A7,'Discounts par marque'!$A:$G,5,FALSE),0) | S7: =IFERROR(I7*(1-Q7/100),"") | T7: =IFERROR(S7/(F7*G7),"") | U7: =IFERROR(I7*(1-R7/100),"") | V7: =IFERROR(U7/(F7*G7),"") | W7: https://www.nutripure.fr/produits/whey-isolat-native-chocolat | X7: Prix marché = null (Nutripure vend uniquement sur site propre, pas de cross-retailers significatifs). Ancien 46€ sourcé via robshop.fr était un revendeur cher, pas un vrai marché médian.
A8: ='Benchmark détaillé'!H1 | B8: Whey Isolat Native 2kg | C8: ='Benchmark détaillé'!H4 | D8: ='Benchmark détaillé'!H10 | E8: ='Benchmark détaillé'!H5 | F8: ='Benchmark détaillé'!H15 | G8: ='Benchmark détaillé'!H13 | H8: ='Benchmark détaillé'!H21 | I8: ='Benchmark détaillé'!H22 | J8: ='Benchmark détaillé'!H23 | K8: =IFERROR((H8-I8)/H8*100,"") | L8: =IFERROR((I8-J8)/I8*100,"") | M8: =IFERROR(I8/(E8/1000),"") | N8: =IFERROR(I8/(F8*G8),"") | O8: ='Benchmark détaillé'!H31 | P8: ='Benchmark détaillé'!H32 | Q8: =IFERROR(VLOOKUP(A8,'Discounts par marque'!$A:$G,4,FALSE),0) | R8: =IFERROR(VLOOKUP(A8,'Discounts par marque'!$A:$G,5,FALSE),0) | S8: =IFERROR(I8*(1-Q8/100),"") | T8: =IFERROR(S8/(F8*G8),"") | U8: =IFERROR(I8*(1-R8/100),"") | V8: =IFERROR(U8/(F8*G8),"") | W8: https://www.nutripure.fr/fr/musculation/147-1115-whey-chocolat-isolate.html#/332-poids_poudre-seau_2kg | X8: Confirmé via Playwright click sur variant radio Seau 2KG (id=332). Page nutripure.fr. Agent v2 avait mal lu '90€' (probablement le 'à partir de' affiché sur la page parent).
A9: ='Benchmark détaillé'!I1 | B9: Whey Isolat Native 4kg | C9: ='Benchmark détaillé'!I4 | D9: ='Benchmark détaillé'!I10 | E9: ='Benchmark détaillé'!I5 | F9: ='Benchmark détaillé'!I15 | G9: ='Benchmark détaillé'!I13 | H9: ='Benchmark détaillé'!I21 | I9: ='Benchmark détaillé'!I22 | J9: ='Benchmark détaillé'!I23 | K9: =IFERROR((H9-I9)/H9*100,"") | L9: =IFERROR((I9-J9)/I9*100,"") | M9: =IFERROR(I9/(E9/1000),"") | N9: =IFERROR(I9/(F9*G9),"") | O9: ='Benchmark détaillé'!I31 | P9: ='Benchmark détaillé'!I32 | Q9: =IFERROR(VLOOKUP(A9,'Discounts par marque'!$A:$G,4,FALSE),0) | R9: =IFERROR(VLOOKUP(A9,'Discounts par marque'!$A:$G,5,FALSE),0) | S9: =IFERROR(I9*(1-Q9/100),"") | T9: =IFERROR(S9/(F9*G9),"") | U9: =IFERROR(I9*(1-R9/100),"") | V9: =IFERROR(U9/(F9*G9),"") | W9: https://www.nutripure.fr/fr/musculation/147-674-whey-chocolat-isolate.html#/47-poids_poudre-seau_4kg | X9: Confirmé via Playwright click sur variant radio Seau 4KG (id=47). Prix réel 179,90€ (pas 159,90€ extrapolé).
A10: ='Benchmark détaillé'!J1 | B10: Whey Native Isolate 500g | C10: ='Benchmark détaillé'!J4 | D10: ='Benchmark détaillé'!J10 | E10: ='Benchmark détaillé'!J5 | F10: ='Benchmark détaillé'!J15 | G10: ='Benchmark détaillé'!J13 | H10: ='Benchmark détaillé'!J21 | I10: ='Benchmark détaillé'!J22 | J10: ='Benchmark détaillé'!J23 | K10: =IFERROR((H10-I10)/H10*100,"") | L10: =IFERROR((I10-J10)/I10*100,"") | M10: =IFERROR(I10/(E10/1000),"") | N10: =IFERROR(I10/(F10*G10),"") | O10: ='Benchmark détaillé'!J31 | P10: ='Benchmark détaillé'!J32 | Q10: =IFERROR(VLOOKUP(A10,'Discounts par marque'!$A:$G,4,FALSE),0) | R10: =IFERROR(VLOOKUP(A10,'Discounts par marque'!$A:$G,5,FALSE),0) | S10: =IFERROR(I10*(1-Q10/100),"") | T10: =IFERROR(S10/(F10*G10),"") | U10: =IFERROR(I10*(1-R10/100),"") | V10: =IFERROR(U10/(F10*G10),"") | W10: https://www.nutrimuscle.com/products/whey-native-isolate
A11: ='Benchmark détaillé'!K1 | B11: Whey Native Isolate | C11: ='Benchmark détaillé'!K4 | D11: ='Benchmark détaillé'!K10 | E11: ='Benchmark détaillé'!K5 | F11: ='Benchmark détaillé'!K15 | G11: ='Benchmark détaillé'!K13 | H11: ='Benchmark détaillé'!K21 | I11: ='Benchmark détaillé'!K22 | J11: ='Benchmark détaillé'!K23 | K11: =IFERROR((H11-I11)/H11*100,"") | L11: =IFERROR((I11-J11)/I11*100,"") | M11: =IFERROR(I11/(E11/1000),"") | N11: =IFERROR(I11/(F11*G11),"") | O11: ='Benchmark détaillé'!K31 | P11: ='Benchmark détaillé'!K32 | Q11: =IFERROR(VLOOKUP(A11,'Discounts par marque'!$A:$G,4,FALSE),0) | R11: =IFERROR(VLOOKUP(A11,'Discounts par marque'!$A:$G,5,FALSE),0) | S11: =IFERROR(I11*(1-Q11/100),"") | T11: =IFERROR(S11/(F11*G11),"") | U11: =IFERROR(I11*(1-R11/100),"") | V11: =IFERROR(U11/(F11*G11),"") | W11: https://www.nutrimuscle.com/products/whey-isolat-native | X11: v1 avait 39.95€ (+45% correction)
A12: ='Benchmark détaillé'!L1 | B12: Whey Native Isolate 2,25kg | C12: ='Benchmark détaillé'!L4 | D12: ='Benchmark détaillé'!L10 | E12: ='Benchmark détaillé'!L5 | F12: ='Benchmark détaillé'!L15 | G12: ='Benchmark détaillé'!L13 | H12: ='Benchmark détaillé'!L21 | I12: ='Benchmark détaillé'!L22 | J12: ='Benchmark détaillé'!L23 | K12: =IFERROR((H12-I12)/H12*100,"") | L12: =IFERROR((I12-J12)/I12*100,"") | M12: =IFERROR(I12/(E12/1000),"") | N12: =IFERROR(I12/(F12*G12),"") | O12: ='Benchmark détaillé'!L31 | P12: ='Benchmark détaillé'!L32 | Q12: =IFERROR(VLOOKUP(A12,'Discounts par marque'!$A:$G,4,FALSE),0) | R12: =IFERROR(VLOOKUP(A12,'Discounts par marque'!$A:$G,5,FALSE),0) | S12: =IFERROR(I12*(1-Q12/100),"") | T12: =IFERROR(S12/(F12*G12),"") | U12: =IFERROR(I12*(1-R12/100),"") | V12: =IFERROR(U12/(F12*G12),"") | W12: https://www.nutrimuscle.com/products/whey-native-isolate
A13: ='Benchmark détaillé'!M1 | B13: Whey Native Isolate 4kg | C13: ='Benchmark détaillé'!M4 | D13: ='Benchmark détaillé'!M10 | E13: ='Benchmark détaillé'!M5 | F13: ='Benchmark détaillé'!M15 | G13: ='Benchmark détaillé'!M13 | H13: ='Benchmark détaillé'!M21 | I13: ='Benchmark détaillé'!M22 | J13: ='Benchmark détaillé'!M23 | K13: =IFERROR((H13-I13)/H13*100,"") | L13: =IFERROR((I13-J13)/I13*100,"") | M13: =IFERROR(I13/(E13/1000),"") | N13: =IFERROR(I13/(F13*G13),"") | O13: ='Benchmark détaillé'!M31 | P13: ='Benchmark détaillé'!M32 | Q13: =IFERROR(VLOOKUP(A13,'Discounts par marque'!$A:$G,4,FALSE),0) | R13: =IFERROR(VLOOKUP(A13,'Discounts par marque'!$A:$G,5,FALSE),0) | S13: =IFERROR(I13*(1-Q13/100),"") | T13: =IFERROR(S13/(F13*G13),"") | U13: =IFERROR(I13*(1-R13/100),"") | V13: =IFERROR(U13/(F13*G13),"") | W13: https://www.nutrimuscle.com/products/whey-native-isolate
A14: ='Benchmark détaillé'!N1 | B14: Whey Native Concentrat 500g | C14: ='Benchmark détaillé'!N4 | D14: ='Benchmark détaillé'!N10 | E14: ='Benchmark détaillé'!N5 | F14: ='Benchmark détaillé'!N15 | G14: ='Benchmark détaillé'!N13 | H14: ='Benchmark détaillé'!N21 | I14: ='Benchmark détaillé'!N22 | J14: ='Benchmark détaillé'!N23 | K14: =IFERROR((H14-I14)/H14*100,"") | L14: =IFERROR((I14-J14)/I14*100,"") | M14: =IFERROR(I14/(E14/1000),"") | N14: =IFERROR(I14/(F14*G14),"") | O14: ='Benchmark détaillé'!N31 | P14: ='Benchmark détaillé'!N32 | Q14: =IFERROR(VLOOKUP(A14,'Discounts par marque'!$A:$G,4,FALSE),0) | R14: =IFERROR(VLOOKUP(A14,'Discounts par marque'!$A:$G,5,FALSE),0) | S14: =IFERROR(I14*(1-Q14/100),"") | T14: =IFERROR(S14/(F14*G14),"") | U14: =IFERROR(I14*(1-R14/100),"") | V14: =IFERROR(U14/(F14*G14),"") | W14: https://www.nutrimuscle.com/products/whey-native
A15: ='Benchmark détaillé'!O1 | B15: Whey Native Concentrat | C15: ='Benchmark détaillé'!O4 | D15: ='Benchmark détaillé'!O10 | E15: ='Benchmark détaillé'!O5 | F15: ='Benchmark détaillé'!O15 | G15: ='Benchmark détaillé'!O13 | H15: ='Benchmark détaillé'!O21 | I15: ='Benchmark détaillé'!O22 | J15: ='Benchmark détaillé'!O23 | K15: =IFERROR((H15-I15)/H15*100,"") | L15: =IFERROR((I15-J15)/I15*100,"") | M15: =IFERROR(I15/(E15/1000),"") | N15: =IFERROR(I15/(F15*G15),"") | O15: ='Benchmark détaillé'!O31 | P15: ='Benchmark détaillé'!O32 | Q15: =IFERROR(VLOOKUP(A15,'Discounts par marque'!$A:$G,4,FALSE),0) | R15: =IFERROR(VLOOKUP(A15,'Discounts par marque'!$A:$G,5,FALSE),0) | S15: =IFERROR(I15*(1-Q15/100),"") | T15: =IFERROR(S15/(F15*G15),"") | U15: =IFERROR(I15*(1-R15/100),"") | V15: =IFERROR(U15/(F15*G15),"") | W15: https://www.nutrimuscle.com/products/whey-concentree-native | X15: v1 avait 25.95€ (+46% correction)
A16: ='Benchmark détaillé'!P1 | B16: Whey Native Concentrat 2,25kg | C16: ='Benchmark détaillé'!P4 | D16: ='Benchmark détaillé'!P10 | E16: ='Benchmark détaillé'!P5 | F16: ='Benchmark détaillé'!P15 | G16: ='Benchmark détaillé'!P13 | H16: ='Benchmark détaillé'!P21 | I16: ='Benchmark détaillé'!P22 | J16: ='Benchmark détaillé'!P23 | K16: =IFERROR((H16-I16)/H16*100,"") | L16: =IFERROR((I16-J16)/I16*100,"") | M16: =IFERROR(I16/(E16/1000),"") | N16: =IFERROR(I16/(F16*G16),"") | O16: ='Benchmark détaillé'!P31 | P16: ='Benchmark détaillé'!P32 | Q16: =IFERROR(VLOOKUP(A16,'Discounts par marque'!$A:$G,4,FALSE),0) | R16: =IFERROR(VLOOKUP(A16,'Discounts par marque'!$A:$G,5,FALSE),0) | S16: =IFERROR(I16*(1-Q16/100),"") | T16: =IFERROR(S16/(F16*G16),"") | U16: =IFERROR(I16*(1-R16/100),"") | V16: =IFERROR(U16/(F16*G16),"") | W16: https://www.nutrimuscle.com/products/whey-native
A17: ='Benchmark détaillé'!Q1 | B17: Whey Native Concentrat 4kg | C17: ='Benchmark détaillé'!Q4 | D17: ='Benchmark détaillé'!Q10 | E17: ='Benchmark détaillé'!Q5 | F17: ='Benchmark détaillé'!Q15 | G17: ='Benchmark détaillé'!Q13 | H17: ='Benchmark détaillé'!Q21 | I17: ='Benchmark détaillé'!Q22 | J17: ='Benchmark détaillé'!Q23 | K17: =IFERROR((H17-I17)/H17*100,"") | L17: =IFERROR((I17-J17)/I17*100,"") | M17: =IFERROR(I17/(E17/1000),"") | N17: =IFERROR(I17/(F17*G17),"") | O17: ='Benchmark détaillé'!Q31 | P17: ='Benchmark détaillé'!Q32 | Q17: =IFERROR(VLOOKUP(A17,'Discounts par marque'!$A:$G,4,FALSE),0) | R17: =IFERROR(VLOOKUP(A17,'Discounts par marque'!$A:$G,5,FALSE),0) | S17: =IFERROR(I17*(1-Q17/100),"") | T17: =IFERROR(S17/(F17*G17),"") | U17: =IFERROR(I17*(1-R17/100),"") | V17: =IFERROR(U17/(F17*G17),"") | W17: https://www.nutrimuscle.com/products/whey-native
A18: ='Benchmark détaillé'!R1 | B18: Whey Isolate Native 900g | C18: ='Benchmark détaillé'!R4 | D18: ='Benchmark détaillé'!R10 | E18: ='Benchmark détaillé'!R5 | F18: ='Benchmark détaillé'!R15 | G18: ='Benchmark détaillé'!R13 | H18: ='Benchmark détaillé'!R21 | I18: ='Benchmark détaillé'!R22 | J18: ='Benchmark détaillé'!R23 | K18: =IFERROR((H18-I18)/H18*100,"") | L18: =IFERROR((I18-J18)/I18*100,"") | M18: =IFERROR(I18/(E18/1000),"") | N18: =IFERROR(I18/(F18*G18),"") | O18: ='Benchmark détaillé'!R31 | P18: ='Benchmark détaillé'!R32 | Q18: =IFERROR(VLOOKUP(A18,'Discounts par marque'!$A:$G,4,FALSE),0) | R18: =IFERROR(VLOOKUP(A18,'Discounts par marque'!$A:$G,5,FALSE),0) | S18: =IFERROR(I18*(1-Q18/100),"") | T18: =IFERROR(S18/(F18*G18),"") | U18: =IFERROR(I18*(1-R18/100),"") | V18: =IFERROR(U18/(F18*G18),"") | W18: https://nutriandco.com/fr/produits/whey-isolate-native
A19: ='Benchmark détaillé'!S1 | B19: Whey Concentrée Native 900g | C19: ='Benchmark détaillé'!S4 | D19: ='Benchmark détaillé'!S10 | E19: ='Benchmark détaillé'!S5 | F19: ='Benchmark détaillé'!S15 | G19: ='Benchmark détaillé'!S13 | H19: ='Benchmark détaillé'!S21 | I19: ='Benchmark détaillé'!S22 | J19: ='Benchmark détaillé'!S23 | K19: =IFERROR((H19-I19)/H19*100,"") | L19: =IFERROR((I19-J19)/I19*100,"") | M19: =IFERROR(I19/(E19/1000),"") | N19: =IFERROR(I19/(F19*G19),"") | O19: ='Benchmark détaillé'!S31 | P19: ='Benchmark détaillé'!S32 | Q19: =IFERROR(VLOOKUP(A19,'Discounts par marque'!$A:$G,4,FALSE),0) | R19: =IFERROR(VLOOKUP(A19,'Discounts par marque'!$A:$G,5,FALSE),0) | S19: =IFERROR(I19*(1-Q19/100),"") | T19: =IFERROR(S19/(F19*G19),"") | U19: =IFERROR(I19*(1-R19/100),"") | V19: =IFERROR(U19/(F19*G19),"") | W19: https://nutriandco.com/fr/produits/whey-native
A20: ='Benchmark détaillé'!T1 | B20: Whey Native 810g | C20: ='Benchmark détaillé'!T4 | D20: ='Benchmark détaillé'!T10 | E20: ='Benchmark détaillé'!T5 | F20: ='Benchmark détaillé'!T15 | G20: ='Benchmark détaillé'!T13 | H20: ='Benchmark détaillé'!T21 | I20: ='Benchmark détaillé'!T22 | J20: ='Benchmark détaillé'!T23 | K20: =IFERROR((H20-I20)/H20*100,"") | L20: =IFERROR((I20-J20)/I20*100,"") | M20: =IFERROR(I20/(E20/1000),"") | N20: =IFERROR(I20/(F20*G20),"") | O20: ='Benchmark détaillé'!T31 | P20: ='Benchmark détaillé'!T32 | Q20: =IFERROR(VLOOKUP(A20,'Discounts par marque'!$A:$G,4,FALSE),0) | R20: =IFERROR(VLOOKUP(A20,'Discounts par marque'!$A:$G,5,FALSE),0) | S20: =IFERROR(I20*(1-Q20/100),"") | T20: =IFERROR(S20/(F20*G20),"") | U20: =IFERROR(I20*(1-R20/100),"") | V20: =IFERROR(U20/(F20*G20),"") | W20: https://www.aqeelab-nutrition.fr/products/whey-native-fabriquee-en-france-lait-francais
A21: ='Benchmark détaillé'!U1 | B21: Iso Zero 100% Whey Protéine 500g | C21: ='Benchmark détaillé'!U4 | D21: ='Benchmark détaillé'!U10 | E21: ='Benchmark détaillé'!U5 | F21: ='Benchmark détaillé'!U15 | G21: ='Benchmark détaillé'!U13 | H21: ='Benchmark détaillé'!U21 | I21: ='Benchmark détaillé'!U22 | J21: ='Benchmark détaillé'!U23 | K21: =IFERROR((H21-I21)/H21*100,"") | L21: =IFERROR((I21-J21)/I21*100,"") | M21: =IFERROR(I21/(E21/1000),"") | N21: =IFERROR(I21/(F21*G21),"") | O21: ='Benchmark détaillé'!U31 | P21: ='Benchmark détaillé'!U32 | Q21: =IFERROR(VLOOKUP(A21,'Discounts par marque'!$A:$G,4,FALSE),0) | R21: =IFERROR(VLOOKUP(A21,'Discounts par marque'!$A:$G,5,FALSE),0) | S21: =IFERROR(I21*(1-Q21/100),"") | T21: =IFERROR(S21/(F21*G21),"") | U21: =IFERROR(I21*(1-R21/100),"") | V21: =IFERROR(U21/(F21*G21),"") | W21: https://www.ericfavre.com/fr_fr/proteines/iso-zero-100-whey-proteine-cookies-cream-500g-p-194-o-1216.htm
A22: ='Benchmark détaillé'!V1 | B22: Iso Zero 100% Whey Protéine 1,5kg | C22: ='Benchmark détaillé'!V4 | D22: ='Benchmark détaillé'!V10 | E22: ='Benchmark détaillé'!V5 | F22: ='Benchmark détaillé'!V15 | G22: ='Benchmark détaillé'!V13 | H22: ='Benchmark détaillé'!V21 | I22: ='Benchmark détaillé'!V22 | J22: ='Benchmark détaillé'!V23 | K22: =IFERROR((H22-I22)/H22*100,"") | L22: =IFERROR((I22-J22)/I22*100,"") | M22: =IFERROR(I22/(E22/1000),"") | N22: =IFERROR(I22/(F22*G22),"") | O22: ='Benchmark détaillé'!V31 | P22: ='Benchmark détaillé'!V32 | Q22: =IFERROR(VLOOKUP(A22,'Discounts par marque'!$A:$G,4,FALSE),0) | R22: =IFERROR(VLOOKUP(A22,'Discounts par marque'!$A:$G,5,FALSE),0) | S22: =IFERROR(I22*(1-Q22/100),"") | T22: =IFERROR(S22/(F22*G22),"") | U22: =IFERROR(I22*(1-R22/100),"") | V22: =IFERROR(U22/(F22*G22),"") | W22: https://www.ericfavre.com/fr_fr/proteines/iso-zero-100-whey-proteine-choco-intense-1-5kg-p-194-o-1200.htm
A23: ='Benchmark détaillé'!W1 | B23: Iso Zero 100% Whey Protéine 2kg | C23: ='Benchmark détaillé'!W4 | D23: ='Benchmark détaillé'!W10 | E23: ='Benchmark détaillé'!W5 | F23: ='Benchmark détaillé'!W15 | G23: ='Benchmark détaillé'!W13 | H23: ='Benchmark détaillé'!W21 | I23: ='Benchmark détaillé'!W22 | J23: ='Benchmark détaillé'!W23 | K23: =IFERROR((H23-I23)/H23*100,"") | L23: =IFERROR((I23-J23)/I23*100,"") | M23: =IFERROR(I23/(E23/1000),"") | N23: =IFERROR(I23/(F23*G23),"") | O23: ='Benchmark détaillé'!W31 | P23: ='Benchmark détaillé'!W32 | Q23: =IFERROR(VLOOKUP(A23,'Discounts par marque'!$A:$G,4,FALSE),0) | R23: =IFERROR(VLOOKUP(A23,'Discounts par marque'!$A:$G,5,FALSE),0) | S23: =IFERROR(I23*(1-Q23/100),"") | T23: =IFERROR(S23/(F23*G23),"") | U23: =IFERROR(I23*(1-R23/100),"") | V23: =IFERROR(U23/(F23*G23),"") | W23: https://www.ericfavre.com/fr_fr/proteines/iso-zero-100-whey-proteine-chocotella-2kg-p-194-o-155.htm
A24: ='Benchmark détaillé'!X1 | B24: Whey Optimax Protein 500g | C24: ='Benchmark détaillé'!X4 | D24: ='Benchmark détaillé'!X10 | E24: ='Benchmark détaillé'!X5 | F24: ='Benchmark détaillé'!X15 | G24: ='Benchmark détaillé'!X13 | H24: ='Benchmark détaillé'!X21 | I24: ='Benchmark détaillé'!X22 | J24: ='Benchmark détaillé'!X23 | K24: =IFERROR((H24-I24)/H24*100,"") | L24: =IFERROR((I24-J24)/I24*100,"") | M24: =IFERROR(I24/(E24/1000),"") | N24: =IFERROR(I24/(F24*G24),"") | O24: ='Benchmark détaillé'!X31 | P24: ='Benchmark détaillé'!X32 | Q24: =IFERROR(VLOOKUP(A24,'Discounts par marque'!$A:$G,4,FALSE),0) | R24: =IFERROR(VLOOKUP(A24,'Discounts par marque'!$A:$G,5,FALSE),0) | S24: =IFERROR(I24*(1-Q24/100),"") | T24: =IFERROR(S24/(F24*G24),"") | U24: =IFERROR(I24*(1-R24/100),"") | V24: =IFERROR(U24/(F24*G24),"") | W24: https://www.ericfavre.com/fr_fr/proteines/whey-optimax-protein-biscuit-cookie-500g-p-622-o-1369.htm
A25: ='Benchmark détaillé'!Y1 | B25: Whey Optimax Protein 1,5kg | C25: ='Benchmark détaillé'!Y4 | D25: ='Benchmark détaillé'!Y10 | E25: ='Benchmark détaillé'!Y5 | F25: ='Benchmark détaillé'!Y15 | G25: ='Benchmark détaillé'!Y13 | H25: ='Benchmark détaillé'!Y21 | I25: ='Benchmark détaillé'!Y22 | J25: ='Benchmark détaillé'!Y23 | K25: =IFERROR((H25-I25)/H25*100,"") | L25: =IFERROR((I25-J25)/I25*100,"") | M25: =IFERROR(I25/(E25/1000),"") | N25: =IFERROR(I25/(F25*G25),"") | O25: ='Benchmark détaillé'!Y31 | P25: ='Benchmark détaillé'!Y32 | Q25: =IFERROR(VLOOKUP(A25,'Discounts par marque'!$A:$G,4,FALSE),0) | R25: =IFERROR(VLOOKUP(A25,'Discounts par marque'!$A:$G,5,FALSE),0) | S25: =IFERROR(I25*(1-Q25/100),"") | T25: =IFERROR(S25/(F25*G25),"") | U25: =IFERROR(I25*(1-R25/100),"") | V25: =IFERROR(U25/(F25*G25),"") | W25: https://www.ericfavre.com/fr_fr/proteines/whey-optimax-protein-chocolat-1-5kg-p-622-o-1370.htm
A26: ='Benchmark détaillé'!Z1 | B26: Whey Zero Protéine 2kg | C26: ='Benchmark détaillé'!Z4 | D26: ='Benchmark détaillé'!Z10 | E26: ='Benchmark détaillé'!Z5 | F26: ='Benchmark détaillé'!Z15 | G26: ='Benchmark détaillé'!Z13 | H26: ='Benchmark détaillé'!Z21 | I26: ='Benchmark détaillé'!Z22 | J26: ='Benchmark détaillé'!Z23 | K26: =IFERROR((H26-I26)/H26*100,"") | L26: =IFERROR((I26-J26)/I26*100,"") | M26: =IFERROR(I26/(E26/1000),"") | N26: =IFERROR(I26/(F26*G26),"") | O26: ='Benchmark détaillé'!Z31 | P26: ='Benchmark détaillé'!Z32 | Q26: =IFERROR(VLOOKUP(A26,'Discounts par marque'!$A:$G,4,FALSE),0) | R26: =IFERROR(VLOOKUP(A26,'Discounts par marque'!$A:$G,5,FALSE),0) | S26: =IFERROR(I26*(1-Q26/100),"") | T26: =IFERROR(S26/(F26*G26),"") | U26: =IFERROR(I26*(1-R26/100),"") | V26: =IFERROR(U26/(F26*G26),"") | W26: https://www.ericfavre.com/fr_fr/proteines/whey-zero-chocolat-2kg-p-517-o-1093.htm
A27: ='Benchmark détaillé'!AA1 | B27: Iso Fusion Protein Complex 750g | C27: ='Benchmark détaillé'!AA4 | D27: ='Benchmark détaillé'!AA10 | E27: ='Benchmark détaillé'!AA5 | F27: ='Benchmark détaillé'!AA15 | G27: ='Benchmark détaillé'!AA13 | H27: ='Benchmark détaillé'!AA21 | I27: ='Benchmark détaillé'!AA22 | J27: ='Benchmark détaillé'!AA23 | K27: =IFERROR((H27-I27)/H27*100,"") | L27: =IFERROR((I27-J27)/I27*100,"") | M27: =IFERROR(I27/(E27/1000),"") | N27: =IFERROR(I27/(F27*G27),"") | O27: ='Benchmark détaillé'!AA31 | P27: ='Benchmark détaillé'!AA32 | Q27: =IFERROR(VLOOKUP(A27,'Discounts par marque'!$A:$G,4,FALSE),0) | R27: =IFERROR(VLOOKUP(A27,'Discounts par marque'!$A:$G,5,FALSE),0) | S27: =IFERROR(I27*(1-Q27/100),"") | T27: =IFERROR(S27/(F27*G27),"") | U27: =IFERROR(I27*(1-R27/100),"") | V27: =IFERROR(U27/(F27*G27),"") | W27: https://www.ericfavre.com/fr_fr/proteines/iso-fusion-biscuit-cookie-750g-p-907-o-1924.htm
A28: ='Benchmark détaillé'!AB1 | B28: Iso Fusion Protein Complex 2kg | C28: ='Benchmark détaillé'!AB4 | D28: ='Benchmark détaillé'!AB10 | E28: ='Benchmark détaillé'!AB5 | F28: ='Benchmark détaillé'!AB15 | G28: ='Benchmark détaillé'!AB13 | H28: ='Benchmark détaillé'!AB21 | I28: ='Benchmark détaillé'!AB22 | J28: ='Benchmark détaillé'!AB23 | K28: =IFERROR((H28-I28)/H28*100,"") | L28: =IFERROR((I28-J28)/I28*100,"") | M28: =IFERROR(I28/(E28/1000),"") | N28: =IFERROR(I28/(F28*G28),"") | O28: ='Benchmark détaillé'!AB31 | P28: ='Benchmark détaillé'!AB32 | Q28: =IFERROR(VLOOKUP(A28,'Discounts par marque'!$A:$G,4,FALSE),0) | R28: =IFERROR(VLOOKUP(A28,'Discounts par marque'!$A:$G,5,FALSE),0) | S28: =IFERROR(I28*(1-Q28/100),"") | T28: =IFERROR(S28/(F28*G28),"") | U28: =IFERROR(I28*(1-R28/100),"") | V28: =IFERROR(U28/(F28*G28),"") | W28: https://www.ericfavre.com/fr_fr/proteines/iso-fusion-biscuit-cookie-2kg-p-907-o-1925.htm
A29: ='Benchmark détaillé'!AC1 | B29: Pure Isolate 750g | C29: ='Benchmark détaillé'!AC4 | D29: ='Benchmark détaillé'!AC10 | E29: ='Benchmark détaillé'!AC5 | F29: ='Benchmark détaillé'!AC15 | G29: ='Benchmark détaillé'!AC13 | H29: ='Benchmark détaillé'!AC21 | I29: ='Benchmark détaillé'!AC22 | J29: ='Benchmark détaillé'!AC23 | K29: =IFERROR((H29-I29)/H29*100,"") | L29: =IFERROR((I29-J29)/I29*100,"") | M29: =IFERROR(I29/(E29/1000),"") | N29: =IFERROR(I29/(F29*G29),"") | O29: ='Benchmark détaillé'!AC31 | P29: ='Benchmark détaillé'!AC32 | Q29: =IFERROR(VLOOKUP(A29,'Discounts par marque'!$A:$G,4,FALSE),0) | R29: =IFERROR(VLOOKUP(A29,'Discounts par marque'!$A:$G,5,FALSE),0) | S29: =IFERROR(I29*(1-Q29/100),"") | T29: =IFERROR(S29/(F29*G29),"") | U29: =IFERROR(I29*(1-R29/100),"") | V29: =IFERROR(U29/(F29*G29),"") | W29: https://www.eafit.com/eafit-pure-isolate.html
A30: ='Benchmark détaillé'!AD1 | B30: Pure Isolate Premium 750g | C30: ='Benchmark détaillé'!AD4 | D30: ='Benchmark détaillé'!AD10 | E30: ='Benchmark détaillé'!AD5 | F30: ='Benchmark détaillé'!AD15 | G30: ='Benchmark détaillé'!AD13 | H30: ='Benchmark détaillé'!AD21 | I30: ='Benchmark détaillé'!AD22 | J30: ='Benchmark détaillé'!AD23 | K30: =IFERROR((H30-I30)/H30*100,"") | L30: =IFERROR((I30-J30)/I30*100,"") | M30: =IFERROR(I30/(E30/1000),"") | N30: =IFERROR(I30/(F30*G30),"") | O30: ='Benchmark détaillé'!AD31 | P30: ='Benchmark détaillé'!AD32 | Q30: =IFERROR(VLOOKUP(A30,'Discounts par marque'!$A:$G,4,FALSE),0) | R30: =IFERROR(VLOOKUP(A30,'Discounts par marque'!$A:$G,5,FALSE),0) | S30: =IFERROR(I30*(1-Q30/100),"") | T30: =IFERROR(S30/(F30*G30),"") | U30: =IFERROR(I30*(1-R30/100),"") | V30: =IFERROR(U30/(F30*G30),"") | W30: https://www.eafit.com/eafit-pure-isolate-premium.html
A31: ='Benchmark détaillé'!AE1 | B31: Pure Whey Protein 750g | C31: ='Benchmark détaillé'!AE4 | D31: ='Benchmark détaillé'!AE10 | E31: ='Benchmark détaillé'!AE5 | F31: ='Benchmark détaillé'!AE15 | G31: ='Benchmark détaillé'!AE13 | H31: ='Benchmark détaillé'!AE21 | I31: ='Benchmark détaillé'!AE22 | J31: ='Benchmark détaillé'!AE23 | K31: =IFERROR((H31-I31)/H31*100,"") | L31: =IFERROR((I31-J31)/I31*100,"") | M31: =IFERROR(I31/(E31/1000),"") | N31: =IFERROR(I31/(F31*G31),"") | O31: ='Benchmark détaillé'!AE31 | P31: ='Benchmark détaillé'!AE32 | Q31: =IFERROR(VLOOKUP(A31,'Discounts par marque'!$A:$G,4,FALSE),0) | R31: =IFERROR(VLOOKUP(A31,'Discounts par marque'!$A:$G,5,FALSE),0) | S31: =IFERROR(I31*(1-Q31/100),"") | T31: =IFERROR(S31/(F31*G31),"") | U31: =IFERROR(I31*(1-R31/100),"") | V31: =IFERROR(U31/(F31*G31),"") | W31: https://www.eafit.com/eafit-pure-whey.html
A32: ='Benchmark détaillé'!AF1 | B32: Mega Whey Creatine Complex 750g | C32: ='Benchmark détaillé'!AF4 | D32: ='Benchmark détaillé'!AF10 | E32: ='Benchmark détaillé'!AF5 | F32: ='Benchmark détaillé'!AF15 | G32: ='Benchmark détaillé'!AF13 | H32: ='Benchmark détaillé'!AF21 | I32: ='Benchmark détaillé'!AF22 | J32: ='Benchmark détaillé'!AF23 | K32: =IFERROR((H32-I32)/H32*100,"") | L32: =IFERROR((I32-J32)/I32*100,"") | M32: =IFERROR(I32/(E32/1000),"") | N32: =IFERROR(I32/(F32*G32),"") | O32: ='Benchmark détaillé'!AF31 | P32: ='Benchmark détaillé'!AF32 | Q32: =IFERROR(VLOOKUP(A32,'Discounts par marque'!$A:$G,4,FALSE),0) | R32: =IFERROR(VLOOKUP(A32,'Discounts par marque'!$A:$G,5,FALSE),0) | S32: =IFERROR(I32*(1-Q32/100),"") | T32: =IFERROR(S32/(F32*G32),"") | U32: =IFERROR(I32*(1-R32/100),"") | V32: =IFERROR(U32/(F32*G32),"") | W32: https://www.eafit.com/eafit-megawhey.html
A33: ='Benchmark détaillé'!AG1 | B33: Pure Whey Protein 850g | C33: ='Benchmark détaillé'!AG4 | D33: ='Benchmark détaillé'!AG10 | E33: ='Benchmark détaillé'!AG5 | F33: ='Benchmark détaillé'!AG15 | G33: ='Benchmark détaillé'!AG13 | H33: ='Benchmark détaillé'!AG21 | I33: ='Benchmark détaillé'!AG22 | J33: ='Benchmark détaillé'!AG23 | K33: =IFERROR((H33-I33)/H33*100,"") | L33: =IFERROR((I33-J33)/I33*100,"") | M33: =IFERROR(I33/(E33/1000),"") | N33: =IFERROR(I33/(F33*G33),"") | O33: ='Benchmark détaillé'!AG31 | P33: ='Benchmark détaillé'!AG32 | Q33: =IFERROR(VLOOKUP(A33,'Discounts par marque'!$A:$G,4,FALSE),0) | R33: =IFERROR(VLOOKUP(A33,'Discounts par marque'!$A:$G,5,FALSE),0) | S33: =IFERROR(I33*(1-Q33/100),"") | T33: =IFERROR(S33/(F33*G33),"") | U33: =IFERROR(I33*(1-R33/100),"") | V33: =IFERROR(U33/(F33*G33),"") | W33: https://www.eafit.com/eafit-pure-whey.html
A34: ='Benchmark détaillé'!AH1 | B34: Pure Whey Protein 2.2kg | C34: ='Benchmark détaillé'!AH4 | D34: ='Benchmark détaillé'!AH10 | E34: ='Benchmark détaillé'!AH5 | F34: ='Benchmark détaillé'!AH15 | G34: ='Benchmark détaillé'!AH13 | H34: ='Benchmark détaillé'!AH21 | I34: ='Benchmark détaillé'!AH22 | J34: ='Benchmark détaillé'!AH23 | K34: =IFERROR((H34-I34)/H34*100,"") | L34: =IFERROR((I34-J34)/I34*100,"") | M34: =IFERROR(I34/(E34/1000),"") | N34: =IFERROR(I34/(F34*G34),"") | O34: ='Benchmark détaillé'!AH31 | P34: ='Benchmark détaillé'!AH32 | Q34: =IFERROR(VLOOKUP(A34,'Discounts par marque'!$A:$G,4,FALSE),0) | R34: =IFERROR(VLOOKUP(A34,'Discounts par marque'!$A:$G,5,FALSE),0) | S34: =IFERROR(I34*(1-Q34/100),"") | T34: =IFERROR(S34/(F34*G34),"") | U34: =IFERROR(I34*(1-R34/100),"") | V34: =IFERROR(U34/(F34*G34),"") | W34: https://www.eafit.com/eafit-pure-whey.html
A35: ='Benchmark détaillé'!AI1 | B35: Pure Whey 100% Isolate 900g | C35: ='Benchmark détaillé'!AI4 | D35: ='Benchmark détaillé'!AI10 | E35: ='Benchmark détaillé'!AI5 | F35: ='Benchmark détaillé'!AI15 | G35: ='Benchmark détaillé'!AI13 | H35: ='Benchmark détaillé'!AI21 | I35: ='Benchmark détaillé'!AI22 | J35: ='Benchmark détaillé'!AI23 | K35: =IFERROR((H35-I35)/H35*100,"") | L35: =IFERROR((I35-J35)/I35*100,"") | M35: =IFERROR(I35/(E35/1000),"") | N35: =IFERROR(I35/(F35*G35),"") | O35: ='Benchmark détaillé'!AI31 | P35: ='Benchmark détaillé'!AI32 | Q35: =IFERROR(VLOOKUP(A35,'Discounts par marque'!$A:$G,4,FALSE),0) | R35: =IFERROR(VLOOKUP(A35,'Discounts par marque'!$A:$G,5,FALSE),0) | S35: =IFERROR(I35*(1-Q35/100),"") | T35: =IFERROR(S35/(F35*G35),"") | U35: =IFERROR(I35*(1-R35/100),"") | V35: =IFERROR(U35/(F35*G35),"") | W35: https://www.decathlon.fr/p/mp/corength/whey-isolate-chocolat/_/R-p-336438
A36: ='Benchmark détaillé'!AJ1 | B36: Whey Protein 900g (Concentrat) | C36: ='Benchmark détaillé'!AJ4 | D36: ='Benchmark détaillé'!AJ10 | E36: ='Benchmark détaillé'!AJ5 | F36: ='Benchmark détaillé'!AJ15 | G36: ='Benchmark détaillé'!AJ13 | H36: ='Benchmark détaillé'!AJ21 | I36: ='Benchmark détaillé'!AJ22 | J36: ='Benchmark détaillé'!AJ23 | K36: =IFERROR((H36-I36)/H36*100,"") | L36: =IFERROR((I36-J36)/I36*100,"") | M36: =IFERROR(I36/(E36/1000),"") | N36: =IFERROR(I36/(F36*G36),"") | O36: ='Benchmark détaillé'!AJ31 | P36: ='Benchmark détaillé'!AJ32 | Q36: =IFERROR(VLOOKUP(A36,'Discounts par marque'!$A:$G,4,FALSE),0) | R36: =IFERROR(VLOOKUP(A36,'Discounts par marque'!$A:$G,5,FALSE),0) | S36: =IFERROR(I36*(1-Q36/100),"") | T36: =IFERROR(S36/(F36*G36),"") | U36: =IFERROR(I36*(1-R36/100),"") | V36: =IFERROR(U36/(F36*G36),"") | W36: https://www.decathlon.fr/p/mp/corength/whey-chocolat-corength/_/R-p-336437
A37: ='Benchmark détaillé'!AK1 | B37: Pure Whey Isolate 1kg | C37: ='Benchmark détaillé'!AK4 | D37: ='Benchmark détaillé'!AK10 | E37: ='Benchmark détaillé'!AK5 | F37: ='Benchmark détaillé'!AK15 | G37: ='Benchmark détaillé'!AK13 | H37: ='Benchmark détaillé'!AK21 | I37: ='Benchmark détaillé'!AK22 | J37: ='Benchmark détaillé'!AK23 | K37: =IFERROR((H37-I37)/H37*100,"") | L37: =IFERROR((I37-J37)/I37*100,"") | M37: =IFERROR(I37/(E37/1000),"") | N37: =IFERROR(I37/(F37*G37),"") | O37: ='Benchmark détaillé'!AK31 | P37: ='Benchmark détaillé'!AK32 | Q37: =IFERROR(VLOOKUP(A37,'Discounts par marque'!$A:$G,4,FALSE),0) | R37: =IFERROR(VLOOKUP(A37,'Discounts par marque'!$A:$G,5,FALSE),0) | S37: =IFERROR(I37*(1-Q37/100),"") | T37: =IFERROR(S37/(F37*G37),"") | U37: =IFERROR(I37*(1-R37/100),"") | V37: =IFERROR(U37/(F37*G37),"") | W37: https://www.bulk.com/fr/pure-whey-isolate-90.html | X37: Catalogue fictif majeur: 69.99€ barré vs 44.99€ réel (-36%)
A38: ='Benchmark détaillé'!AL1 | B38: Pure Whey Isolate 2,5kg | C38: ='Benchmark détaillé'!AL4 | D38: ='Benchmark détaillé'!AL10 | E38: ='Benchmark détaillé'!AL5 | F38: ='Benchmark détaillé'!AL15 | G38: ='Benchmark détaillé'!AL13 | H38: ='Benchmark détaillé'!AL21 | I38: ='Benchmark détaillé'!AL22 | J38: ='Benchmark détaillé'!AL23 | K38: =IFERROR((H38-I38)/H38*100,"") | L38: =IFERROR((I38-J38)/I38*100,"") | M38: =IFERROR(I38/(E38/1000),"") | N38: =IFERROR(I38/(F38*G38),"") | O38: ='Benchmark détaillé'!AL31 | P38: ='Benchmark détaillé'!AL32 | Q38: =IFERROR(VLOOKUP(A38,'Discounts par marque'!$A:$G,4,FALSE),0) | R38: =IFERROR(VLOOKUP(A38,'Discounts par marque'!$A:$G,5,FALSE),0) | S38: =IFERROR(I38*(1-Q38/100),"") | T38: =IFERROR(S38/(F38*G38),"") | U38: =IFERROR(I38*(1-R38/100),"") | V38: =IFERROR(U38/(F38*G38),"") | W38: https://www.bulk.com/fr/pure-whey-isolate-90.html | X38: Catalogue fictif fort: 159.99€ vs 99.99€ réel (-37%)
A39: ='Benchmark détaillé'!AM1 | B39: Pure Whey Protein 1kg | C39: ='Benchmark détaillé'!AM4 | D39: ='Benchmark détaillé'!AM10 | E39: ='Benchmark détaillé'!AM5 | F39: ='Benchmark détaillé'!AM15 | G39: ='Benchmark détaillé'!AM13 | H39: ='Benchmark détaillé'!AM21 | I39: ='Benchmark détaillé'!AM22 | J39: ='Benchmark détaillé'!AM23 | K39: =IFERROR((H39-I39)/H39*100,"") | L39: =IFERROR((I39-J39)/I39*100,"") | M39: =IFERROR(I39/(E39/1000),"") | N39: =IFERROR(I39/(F39*G39),"") | O39: ='Benchmark détaillé'!AM31 | P39: ='Benchmark détaillé'!AM32 | Q39: =IFERROR(VLOOKUP(A39,'Discounts par marque'!$A:$G,4,FALSE),0) | R39: =IFERROR(VLOOKUP(A39,'Discounts par marque'!$A:$G,5,FALSE),0) | S39: =IFERROR(I39*(1-Q39/100),"") | T39: =IFERROR(S39/(F39*G39),"") | U39: =IFERROR(I39*(1-R39/100),"") | V39: =IFERROR(U39/(F39*G39),"") | W39: https://www.bulk.com/fr/pure-whey-protein-1.html | X39: Catalogue partiellement fictif: barré 37.99€ vs current 27.99€ vs marché 23.99€
A40: ='Benchmark détaillé'!AN1 | B40: Pure Whey Protein 2,5kg | C40: ='Benchmark détaillé'!AN4 | D40: ='Benchmark détaillé'!AN10 | E40: ='Benchmark détaillé'!AN5 | F40: ='Benchmark détaillé'!AN15 | G40: ='Benchmark détaillé'!AN13 | H40: ='Benchmark détaillé'!AN21 | I40: ='Benchmark détaillé'!AN22 | J40: ='Benchmark détaillé'!AN23 | K40: =IFERROR((H40-I40)/H40*100,"") | L40: =IFERROR((I40-J40)/I40*100,"") | M40: =IFERROR(I40/(E40/1000),"") | N40: =IFERROR(I40/(F40*G40),"") | O40: ='Benchmark détaillé'!AN31 | P40: ='Benchmark détaillé'!AN32 | Q40: =IFERROR(VLOOKUP(A40,'Discounts par marque'!$A:$G,4,FALSE),0) | R40: =IFERROR(VLOOKUP(A40,'Discounts par marque'!$A:$G,5,FALSE),0) | S40: =IFERROR(I40*(1-Q40/100),"") | T40: =IFERROR(S40/(F40*G40),"") | U40: =IFERROR(I40*(1-R40/100),"") | V40: =IFERROR(U40/(F40*G40),"") | W40: https://www.bulk.com/fr/pure-whey-protein-1.html | X40: Catalogue fictif: 84.99€ barré vs 64.99€ réel (-23%)
A41: ='Benchmark détaillé'!AO1 | B41: Pure Whey Protein 5kg | C41: ='Benchmark détaillé'!AO4 | D41: ='Benchmark détaillé'!AO10 | E41: ='Benchmark détaillé'!AO5 | F41: ='Benchmark détaillé'!AO15 | G41: ='Benchmark détaillé'!AO13 | H41: ='Benchmark détaillé'!AO21 | I41: ='Benchmark détaillé'!AO22 | J41: ='Benchmark détaillé'!AO23 | K41: =IFERROR((H41-I41)/H41*100,"") | L41: =IFERROR((I41-J41)/I41*100,"") | M41: =IFERROR(I41/(E41/1000),"") | N41: =IFERROR(I41/(F41*G41),"") | O41: ='Benchmark détaillé'!AO31 | P41: ='Benchmark détaillé'!AO32 | Q41: =IFERROR(VLOOKUP(A41,'Discounts par marque'!$A:$G,4,FALSE),0) | R41: =IFERROR(VLOOKUP(A41,'Discounts par marque'!$A:$G,5,FALSE),0) | S41: =IFERROR(I41*(1-Q41/100),"") | T41: =IFERROR(S41/(F41*G41),"") | U41: =IFERROR(I41*(1-R41/100),"") | V41: =IFERROR(U41/(F41*G41),"") | W41: https://www.bulk.com/fr/pure-whey-protein-1.html | X41: Catalogue fictif: 159.99€ vs 129.99€ payé (-19%)
A42: ='Benchmark détaillé'!AP1 | B42: Clear Whey Isolate 500g | C42: ='Benchmark détaillé'!AP4 | D42: ='Benchmark détaillé'!AP10 | E42: ='Benchmark détaillé'!AP5 | F42: ='Benchmark détaillé'!AP15 | G42: ='Benchmark détaillé'!AP13 | H42: ='Benchmark détaillé'!AP21 | I42: ='Benchmark détaillé'!AP22 | J42: ='Benchmark détaillé'!AP23 | K42: =IFERROR((H42-I42)/H42*100,"") | L42: =IFERROR((I42-J42)/I42*100,"") | M42: =IFERROR(I42/(E42/1000),"") | N42: =IFERROR(I42/(F42*G42),"") | O42: ='Benchmark détaillé'!AP31 | P42: ='Benchmark détaillé'!AP32 | Q42: =IFERROR(VLOOKUP(A42,'Discounts par marque'!$A:$G,4,FALSE),0) | R42: =IFERROR(VLOOKUP(A42,'Discounts par marque'!$A:$G,5,FALSE),0) | S42: =IFERROR(I42*(1-Q42/100),"") | T42: =IFERROR(S42/(F42*G42),"") | U42: =IFERROR(I42*(1-R42/100),"") | V42: =IFERROR(U42/(F42*G42),"") | W42: https://www.bulk.com/fr/clear-whey-isolate.html | X42: Catalogue 31.49€ barré vs 25.99€ payé (-17%). Marché 22.25€
A43: ='Benchmark détaillé'!AQ1 | B43: Impact Whey Isolate 1kg | C43: ='Benchmark détaillé'!AQ4 | D43: ='Benchmark détaillé'!AQ10 | E43: ='Benchmark détaillé'!AQ5 | F43: ='Benchmark détaillé'!AQ15 | G43: ='Benchmark détaillé'!AQ13 | H43: ='Benchmark détaillé'!AQ21 | I43: ='Benchmark détaillé'!AQ22 | J43: ='Benchmark détaillé'!AQ23 | K43: =IFERROR((H43-I43)/H43*100,"") | L43: =IFERROR((I43-J43)/I43*100,"") | M43: =IFERROR(I43/(E43/1000),"") | N43: =IFERROR(I43/(F43*G43),"") | O43: ='Benchmark détaillé'!AQ31 | P43: ='Benchmark détaillé'!AQ32 | Q43: =IFERROR(VLOOKUP(A43,'Discounts par marque'!$A:$G,4,FALSE),0) | R43: =IFERROR(VLOOKUP(A43,'Discounts par marque'!$A:$G,5,FALSE),0) | S43: =IFERROR(I43*(1-Q43/100),"") | T43: =IFERROR(S43/(F43*G43),"") | U43: =IFERROR(I43*(1-R43/100),"") | V43: =IFERROR(U43/(F43*G43),"") | W43: https://fr.myprotein.com/p/nutrition-sportive/impact-whey-isolate/10852482/ | X43: Isolate EXCLU de la promo -30% MyProtein. Prix current = prix nominal (pas de discount automatique). Revert de l'ancienne estimation ×0.7.
A44: ='Benchmark détaillé'!AR1 | B44: Impact Whey Isolate 2,5kg | C44: ='Benchmark détaillé'!AR4 | D44: ='Benchmark détaillé'!AR10 | E44: ='Benchmark détaillé'!AR5 | F44: ='Benchmark détaillé'!AR15 | G44: ='Benchmark détaillé'!AR13 | H44: ='Benchmark détaillé'!AR21 | I44: ='Benchmark détaillé'!AR22 | J44: ='Benchmark détaillé'!AR23 | K44: =IFERROR((H44-I44)/H44*100,"") | L44: =IFERROR((I44-J44)/I44*100,"") | M44: =IFERROR(I44/(E44/1000),"") | N44: =IFERROR(I44/(F44*G44),"") | O44: ='Benchmark détaillé'!AR31 | P44: ='Benchmark détaillé'!AR32 | Q44: =IFERROR(VLOOKUP(A44,'Discounts par marque'!$A:$G,4,FALSE),0) | R44: =IFERROR(VLOOKUP(A44,'Discounts par marque'!$A:$G,5,FALSE),0) | S44: =IFERROR(I44*(1-Q44/100),"") | T44: =IFERROR(S44/(F44*G44),"") | U44: =IFERROR(I44*(1-R44/100),"") | V44: =IFERROR(U44/(F44*G44),"") | W44: https://fr.myprotein.com/p/nutrition-sportive/impact-whey-isolate-framboise-poche-2.5-kg/10530927/ | X44: Confirmé via variant Framboise 2.5kg (10530927) : 124.99€ affiché sans strikethrough. Isolate exclu de la promo -30%.
A45: ='Benchmark détaillé'!AS1 | B45: Impact Whey Protein 1kg | C45: ='Benchmark détaillé'!AS4 | D45: ='Benchmark détaillé'!AS10 | E45: ='Benchmark détaillé'!AS5 | F45: ='Benchmark détaillé'!AS15 | G45: ='Benchmark détaillé'!AS13 | H45: ='Benchmark détaillé'!AS21 | I45: ='Benchmark détaillé'!AS22 | J45: ='Benchmark détaillé'!AS23 | K45: =IFERROR((H45-I45)/H45*100,"") | L45: =IFERROR((I45-J45)/I45*100,"") | M45: =IFERROR(I45/(E45/1000),"") | N45: =IFERROR(I45/(F45*G45),"") | O45: ='Benchmark détaillé'!AS31 | P45: ='Benchmark détaillé'!AS32 | Q45: =IFERROR(VLOOKUP(A45,'Discounts par marque'!$A:$G,4,FALSE),0) | R45: =IFERROR(VLOOKUP(A45,'Discounts par marque'!$A:$G,5,FALSE),0) | S45: =IFERROR(I45*(1-Q45/100),"") | T45: =IFERROR(S45/(F45*G45),"") | U45: =IFERROR(I45*(1-R45/100),"") | V45: =IFERROR(U45/(F45*G45),"") | W45: https://fr.myprotein.com/p/nutrition-sportive/myprotein-impact-whey-protein-chocolate-1kg/11068071/ | X45: Prix actuel = 17.99€ sur fr.myprotein.com/.../11068071/ (scraped Playwright 2026-04-14). Promo site -30% + extra app ramène à 17.99 vs 41.99 nominal (soit -57%). Pattern MyProtein Whey Protein uniquement.
A46: ='Benchmark détaillé'!AT1 | B46: Impact Whey Protein 2,5kg | C46: ='Benchmark détaillé'!AT4 | D46: ='Benchmark détaillé'!AT10 | E46: ='Benchmark détaillé'!AT5 | F46: ='Benchmark détaillé'!AT15 | G46: ='Benchmark détaillé'!AT13 | H46: ='Benchmark détaillé'!AT21 | I46: ='Benchmark détaillé'!AT22 | J46: ='Benchmark détaillé'!AT23 | K46: =IFERROR((H46-I46)/H46*100,"") | L46: =IFERROR((I46-J46)/I46*100,"") | M46: =IFERROR(I46/(E46/1000),"") | N46: =IFERROR(I46/(F46*G46),"") | O46: ='Benchmark détaillé'!AT31 | P46: ='Benchmark détaillé'!AT32 | Q46: =IFERROR(VLOOKUP(A46,'Discounts par marque'!$A:$G,4,FALSE),0) | R46: =IFERROR(VLOOKUP(A46,'Discounts par marque'!$A:$G,5,FALSE),0) | S46: =IFERROR(I46*(1-Q46/100),"") | T46: =IFERROR(S46/(F46*G46),"") | U46: =IFERROR(I46*(1-R46/100),"") | V46: =IFERROR(U46/(F46*G46),"") | W46: https://fr.myprotein.com/p/nutrition-sportive/myprotein-impact-whey-protein-chocolate-nut-2.5kg/10530969/ | X46: Prix scrapé via variant Chocolate Nut 2.5kg (10530969) : 84.99€ barré / 40.99€ actuel. Promo -52%. Playwright 2026-04-14.
A47: ='Benchmark détaillé'!AU1 | B47: Impact Whey Protein 5kg (Sans arôme) | C47: ='Benchmark détaillé'!AU4 | D47: ='Benchmark détaillé'!AU10 | E47: ='Benchmark détaillé'!AU5 | F47: ='Benchmark détaillé'!AU15 | G47: ='Benchmark détaillé'!AU13 | H47: ='Benchmark détaillé'!AU21 | I47: ='Benchmark détaillé'!AU22 | J47: ='Benchmark détaillé'!AU23 | K47: =IFERROR((H47-I47)/H47*100,"") | L47: =IFERROR((I47-J47)/I47*100,"") | M47: =IFERROR(I47/(E47/1000),"") | N47: =IFERROR(I47/(F47*G47),"") | O47: ='Benchmark détaillé'!AU31 | P47: ='Benchmark détaillé'!AU32 | Q47: =IFERROR(VLOOKUP(A47,'Discounts par marque'!$A:$G,4,FALSE),0) | R47: =IFERROR(VLOOKUP(A47,'Discounts par marque'!$A:$G,5,FALSE),0) | S47: =IFERROR(I47*(1-Q47/100),"") | T47: =IFERROR(S47/(F47*G47),"") | U47: =IFERROR(I47*(1-R47/100),"") | V47: =IFERROR(U47/(F47*G47),"") | W47: https://fr.myprotein.com/p/nutrition-sportive/impact-whey-protein/10530943/ | X47: 5kg n'existe qu'en 'Sans arôme' (chocolat inexistant). Current price = extrapolation du ratio 2.5kg (40.99/84.99=0.482) : 188.99 × 0.482 ≈ 91.10€.
A48: ='Benchmark détaillé'!AV1 | B48: Clear Whey Isolate 875g | C48: ='Benchmark détaillé'!AV4 | D48: ='Benchmark détaillé'!AV10 | E48: ='Benchmark détaillé'!AV5 | F48: ='Benchmark détaillé'!AV15 | G48: ='Benchmark détaillé'!AV13 | H48: ='Benchmark détaillé'!AV21 | I48: ='Benchmark détaillé'!AV22 | J48: ='Benchmark détaillé'!AV23 | K48: =IFERROR((H48-I48)/H48*100,"") | L48: =IFERROR((I48-J48)/I48*100,"") | M48: =IFERROR(I48/(E48/1000),"") | N48: =IFERROR(I48/(F48*G48),"") | O48: ='Benchmark détaillé'!AV31 | P48: ='Benchmark détaillé'!AV32 | Q48: =IFERROR(VLOOKUP(A48,'Discounts par marque'!$A:$G,4,FALSE),0) | R48: =IFERROR(VLOOKUP(A48,'Discounts par marque'!$A:$G,5,FALSE),0) | S48: =IFERROR(I48*(1-Q48/100),"") | T48: =IFERROR(S48/(F48*G48),"") | U48: =IFERROR(I48*(1-R48/100),"") | V48: =IFERROR(U48/(F48*G48),"") | W48: https://fr.myprotein.com/p/nutrition-sportive/clear-whey-isolate/12081395/ | X48: Clear Whey exclu de la promo -30% (mention explicite). Format 875g max (pas de 1kg). Confirmé via scraping 12081395.
A49: ='Benchmark détaillé'!AW1 | B49: Zero Diet Whey 750g | C49: ='Benchmark détaillé'!AW4 | D49: ='Benchmark détaillé'!AW10 | E49: ='Benchmark détaillé'!AW5 | F49: ='Benchmark détaillé'!AW15 | G49: ='Benchmark détaillé'!AW13 | H49: ='Benchmark détaillé'!AW21 | I49: ='Benchmark détaillé'!AW22 | J49: ='Benchmark détaillé'!AW23 | K49: =IFERROR((H49-I49)/H49*100,"") | L49: =IFERROR((I49-J49)/I49*100,"") | M49: =IFERROR(I49/(E49/1000),"") | N49: =IFERROR(I49/(F49*G49),"") | O49: ='Benchmark détaillé'!AW31 | P49: ='Benchmark détaillé'!AW32 | Q49: =IFERROR(VLOOKUP(A49,'Discounts par marque'!$A:$G,4,FALSE),0) | R49: =IFERROR(VLOOKUP(A49,'Discounts par marque'!$A:$G,5,FALSE),0) | S49: =IFERROR(I49*(1-Q49/100),"") | T49: =IFERROR(S49/(F49*G49),"") | U49: =IFERROR(I49*(1-R49/100),"") | V49: =IFERROR(U49/(F49*G49),"") | W49: https://www.prozis.com/fr/fr/prozis/zero-diet-whey-750-g
A50: ='Benchmark détaillé'!AX1 | B50: 100% Real Whey Isolate 1000g | C50: ='Benchmark détaillé'!AX4 | D50: ='Benchmark détaillé'!AX10 | E50: ='Benchmark détaillé'!AX5 | F50: ='Benchmark détaillé'!AX15 | G50: ='Benchmark détaillé'!AX13 | H50: ='Benchmark détaillé'!AX21 | I50: ='Benchmark détaillé'!AX22 | J50: ='Benchmark détaillé'!AX23 | K50: =IFERROR((H50-I50)/H50*100,"") | L50: =IFERROR((I50-J50)/I50*100,"") | M50: =IFERROR(I50/(E50/1000),"") | N50: =IFERROR(I50/(F50*G50),"") | O50: ='Benchmark détaillé'!AX31 | P50: ='Benchmark détaillé'!AX32 | Q50: =IFERROR(VLOOKUP(A50,'Discounts par marque'!$A:$G,4,FALSE),0) | R50: =IFERROR(VLOOKUP(A50,'Discounts par marque'!$A:$G,5,FALSE),0) | S50: =IFERROR(I50*(1-Q50/100),"") | T50: =IFERROR(S50/(F50*G50),"") | U50: =IFERROR(I50*(1-R50/100),"") | V50: =IFERROR(U50/(F50*G50),"") | W50: https://www.prozis.com/fr/fr/prozis/100-real-whey-isolate-1000-g
A51: ='Benchmark détaillé'!AY1 | B51: 100% Real Whey Protein 907g | C51: ='Benchmark détaillé'!AY4 | D51: ='Benchmark détaillé'!AY10 | E51: ='Benchmark détaillé'!AY5 | F51: ='Benchmark détaillé'!AY15 | G51: ='Benchmark détaillé'!AY13 | H51: ='Benchmark détaillé'!AY21 | I51: ='Benchmark détaillé'!AY22 | J51: ='Benchmark détaillé'!AY23 | K51: =IFERROR((H51-I51)/H51*100,"") | L51: =IFERROR((I51-J51)/I51*100,"") | M51: =IFERROR(I51/(E51/1000),"") | N51: =IFERROR(I51/(F51*G51),"") | O51: ='Benchmark détaillé'!AY31 | P51: ='Benchmark détaillé'!AY32 | Q51: =IFERROR(VLOOKUP(A51,'Discounts par marque'!$A:$G,4,FALSE),0) | R51: =IFERROR(VLOOKUP(A51,'Discounts par marque'!$A:$G,5,FALSE),0) | S51: =IFERROR(I51*(1-Q51/100),"") | T51: =IFERROR(S51/(F51*G51),"") | U51: =IFERROR(I51*(1-R51/100),"") | V51: =IFERROR(U51/(F51*G51),"") | W51: https://www.prozis.com/fr/fr/prozis/100-real-whey-protein-907g
A52: ='Benchmark détaillé'!AZ1 | B52: 100% Real Whey Protein 2000g | C52: ='Benchmark détaillé'!AZ4 | D52: ='Benchmark détaillé'!AZ10 | E52: ='Benchmark détaillé'!AZ5 | F52: ='Benchmark détaillé'!AZ15 | G52: ='Benchmark détaillé'!AZ13 | H52: ='Benchmark détaillé'!AZ21 | I52: ='Benchmark détaillé'!AZ22 | J52: ='Benchmark détaillé'!AZ23 | K52: =IFERROR((H52-I52)/H52*100,"") | L52: =IFERROR((I52-J52)/I52*100,"") | M52: =IFERROR(I52/(E52/1000),"") | N52: =IFERROR(I52/(F52*G52),"") | O52: ='Benchmark détaillé'!AZ31 | P52: ='Benchmark détaillé'!AZ32 | Q52: =IFERROR(VLOOKUP(A52,'Discounts par marque'!$A:$G,4,FALSE),0) | R52: =IFERROR(VLOOKUP(A52,'Discounts par marque'!$A:$G,5,FALSE),0) | S52: =IFERROR(I52*(1-Q52/100),"") | T52: =IFERROR(S52/(F52*G52),"") | U52: =IFERROR(I52*(1-R52/100),"") | V52: =IFERROR(U52/(F52*G52),"") | W52: https://www.prozis.com/fr/fr/prozis/100-real-whey-protein-907g
A53: ='Benchmark détaillé'!BA1 | B53: 100% Whey Hydro Isolate 2000g | C53: ='Benchmark détaillé'!BA4 | D53: ='Benchmark détaillé'!BA10 | E53: ='Benchmark détaillé'!BA5 | F53: ='Benchmark détaillé'!BA15 | G53: ='Benchmark détaillé'!BA13 | H53: ='Benchmark détaillé'!BA21 | I53: ='Benchmark détaillé'!BA22 | J53: ='Benchmark détaillé'!BA23 | K53: =IFERROR((H53-I53)/H53*100,"") | L53: =IFERROR((I53-J53)/I53*100,"") | M53: =IFERROR(I53/(E53/1000),"") | N53: =IFERROR(I53/(F53*G53),"") | O53: ='Benchmark détaillé'!BA31 | P53: ='Benchmark détaillé'!BA32 | Q53: =IFERROR(VLOOKUP(A53,'Discounts par marque'!$A:$G,4,FALSE),0) | R53: =IFERROR(VLOOKUP(A53,'Discounts par marque'!$A:$G,5,FALSE),0) | S53: =IFERROR(I53*(1-Q53/100),"") | T53: =IFERROR(S53/(F53*G53),"") | U53: =IFERROR(I53*(1-R53/100),"") | V53: =IFERROR(U53/(F53*G53),"") | W53: https://www.prozis.com/fr/fr/prozis/100-whey-hydro-isolate-2000g
A54: ='Benchmark détaillé'!BB1 | B54: Whey Protein 750g | C54: ='Benchmark détaillé'!BB4 | D54: ='Benchmark détaillé'!BB10 | E54: ='Benchmark détaillé'!BB5 | F54: ='Benchmark détaillé'!BB15 | G54: ='Benchmark détaillé'!BB13 | H54: ='Benchmark détaillé'!BB21 | I54: ='Benchmark détaillé'!BB22 | J54: ='Benchmark détaillé'!BB23 | K54: =IFERROR((H54-I54)/H54*100,"") | L54: =IFERROR((I54-J54)/I54*100,"") | M54: =IFERROR(I54/(E54/1000),"") | N54: =IFERROR(I54/(F54*G54),"") | O54: ='Benchmark détaillé'!BB31 | P54: ='Benchmark détaillé'!BB32 | Q54: =IFERROR(VLOOKUP(A54,'Discounts par marque'!$A:$G,4,FALSE),0) | R54: =IFERROR(VLOOKUP(A54,'Discounts par marque'!$A:$G,5,FALSE),0) | S54: =IFERROR(I54*(1-Q54/100),"") | T54: =IFERROR(S54/(F54*G54),"") | U54: =IFERROR(I54*(1-R54/100),"") | V54: =IFERROR(U54/(F54*G54),"") | W54: https://www.amazon.fr/foodspring-croissance-musculaire-solubilit%C3%A9-ultra-filtr%C3%A9e/dp/B0CTR3FZ7W | X54: Site foodspring.fr = DNS dead (brand pas disponible en FR direct). Prix récupéré via Amazon FR fiche vanille 750g : 29,96€ current (39,90€ RRP affiché). Agent v2 avait 32,95€ via revendeur paraplus.fr, désormais obsolète.
A55: ='Benchmark détaillé'!BC1 | B55: Iso Whey Protein Isolat 908g | C55: ='Benchmark détaillé'!BC4 | D55: ='Benchmark détaillé'!BC10 | E55: ='Benchmark détaillé'!BC5 | F55: ='Benchmark détaillé'!BC15 | G55: ='Benchmark détaillé'!BC13 | H55: ='Benchmark détaillé'!BC21 | I55: ='Benchmark détaillé'!BC22 | J55: ='Benchmark détaillé'!BC23 | K55: =IFERROR((H55-I55)/H55*100,"") | L55: =IFERROR((I55-J55)/I55*100,"") | M55: =IFERROR(I55/(E55/1000),"") | N55: =IFERROR(I55/(F55*G55),"") | O55: ='Benchmark détaillé'!BC31 | P55: ='Benchmark détaillé'!BC32 | Q55: =IFERROR(VLOOKUP(A55,'Discounts par marque'!$A:$G,4,FALSE),0) | R55: =IFERROR(VLOOKUP(A55,'Discounts par marque'!$A:$G,5,FALSE),0) | S55: =IFERROR(I55*(1-Q55/100),"") | T55: =IFERROR(S55/(F55*G55),"") | U55: =IFERROR(I55*(1-R55/100),"") | V55: =IFERROR(U55/(F55*G55),"") | W55: https://www.esn.com/products/esn-iso-whey-protein
A56: ='Benchmark détaillé'!BD1 | B56: Designer Whey Protein 908g | C56: ='Benchmark détaillé'!BD4 | D56: ='Benchmark détaillé'!BD10 | E56: ='Benchmark détaillé'!BD5 | F56: ='Benchmark détaillé'!BD15 | G56: ='Benchmark détaillé'!BD13 | H56: ='Benchmark détaillé'!BD21 | I56: ='Benchmark détaillé'!BD22 | J56: ='Benchmark détaillé'!BD23 | K56: =IFERROR((H56-I56)/H56*100,"") | L56: =IFERROR((I56-J56)/I56*100,"") | M56: =IFERROR(I56/(E56/1000),"") | N56: =IFERROR(I56/(F56*G56),"") | O56: ='Benchmark détaillé'!BD31 | P56: ='Benchmark détaillé'!BD32 | Q56: =IFERROR(VLOOKUP(A56,'Discounts par marque'!$A:$G,4,FALSE),0) | R56: =IFERROR(VLOOKUP(A56,'Discounts par marque'!$A:$G,5,FALSE),0) | S56: =IFERROR(I56*(1-Q56/100),"") | T56: =IFERROR(S56/(F56*G56),"") | U56: =IFERROR(I56*(1-R56/100),"") | V56: =IFERROR(U56/(F56*G56),"") | W56: https://www.esn.com/products/esn-designer-whey-protein | X56: Prix réel confirmé 41.99€ (vs 42.90€ ancien). Drift mineur sans promo.
A57: ='Benchmark détaillé'!BE1 | B57: Basic Whey 1000g | C57: ='Benchmark détaillé'!BE4 | D57: ='Benchmark détaillé'!BE10 | E57: ='Benchmark détaillé'!BE5 | F57: ='Benchmark détaillé'!BE15 | G57: ='Benchmark détaillé'!BE13 | H57: ='Benchmark détaillé'!BE21 | I57: ='Benchmark détaillé'!BE22 | J57: ='Benchmark détaillé'!BE23 | K57: =IFERROR((H57-I57)/H57*100,"") | L57: =IFERROR((I57-J57)/I57*100,"") | M57: =IFERROR(I57/(E57/1000),"") | N57: =IFERROR(I57/(F57*G57),"") | O57: ='Benchmark détaillé'!BE31 | P57: ='Benchmark détaillé'!BE32 | Q57: =IFERROR(VLOOKUP(A57,'Discounts par marque'!$A:$G,4,FALSE),0) | R57: =IFERROR(VLOOKUP(A57,'Discounts par marque'!$A:$G,5,FALSE),0) | S57: =IFERROR(I57*(1-Q57/100),"") | T57: =IFERROR(S57/(F57*G57),"") | U57: =IFERROR(I57*(1-R57/100),"") | V57: =IFERROR(U57/(F57*G57),"") | W57: https://www.esn.com/products/basic-whey
A58: ='Benchmark détaillé'!BF1 | B58: Designer Whey Protein 2000g | C58: ='Benchmark détaillé'!BF4 | D58: ='Benchmark détaillé'!BF10 | E58: ='Benchmark détaillé'!BF5 | F58: ='Benchmark détaillé'!BF15 | G58: ='Benchmark détaillé'!BF13 | H58: ='Benchmark détaillé'!BF21 | I58: ='Benchmark détaillé'!BF22 | J58: ='Benchmark détaillé'!BF23 | K58: =IFERROR((H58-I58)/H58*100,"") | L58: =IFERROR((I58-J58)/I58*100,"") | M58: =IFERROR(I58/(E58/1000),"") | N58: =IFERROR(I58/(F58*G58),"") | O58: ='Benchmark détaillé'!BF31 | P58: ='Benchmark détaillé'!BF32 | Q58: =IFERROR(VLOOKUP(A58,'Discounts par marque'!$A:$G,4,FALSE),0) | R58: =IFERROR(VLOOKUP(A58,'Discounts par marque'!$A:$G,5,FALSE),0) | S58: =IFERROR(I58*(1-Q58/100),"") | T58: =IFERROR(S58/(F58*G58),"") | U58: =IFERROR(I58*(1-R58/100),"") | V58: =IFERROR(U58/(F58*G58),"") | W58: https://www.esn.com/products/esn-designer-whey-protein
A59: ='Benchmark détaillé'!BG1 | B59: Basic Whey 2000g | C59: ='Benchmark détaillé'!BG4 | D59: ='Benchmark détaillé'!BG10 | E59: ='Benchmark détaillé'!BG5 | F59: ='Benchmark détaillé'!BG15 | G59: ='Benchmark détaillé'!BG13 | H59: ='Benchmark détaillé'!BG21 | I59: ='Benchmark détaillé'!BG22 | J59: ='Benchmark détaillé'!BG23 | K59: =IFERROR((H59-I59)/H59*100,"") | L59: =IFERROR((I59-J59)/I59*100,"") | M59: =IFERROR(I59/(E59/1000),"") | N59: =IFERROR(I59/(F59*G59),"") | O59: ='Benchmark détaillé'!BG31 | P59: ='Benchmark détaillé'!BG32 | Q59: =IFERROR(VLOOKUP(A59,'Discounts par marque'!$A:$G,4,FALSE),0) | R59: =IFERROR(VLOOKUP(A59,'Discounts par marque'!$A:$G,5,FALSE),0) | S59: =IFERROR(I59*(1-Q59/100),"") | T59: =IFERROR(S59/(F59*G59),"") | U59: =IFERROR(I59*(1-R59/100),"") | V59: =IFERROR(U59/(F59*G59),"") | W59: https://www.esn.com/products/basic-whey
A60: ='Benchmark détaillé'!BH1 | B60: Iso Whey Zero 908g | C60: ='Benchmark détaillé'!BH4 | D60: ='Benchmark détaillé'!BH10 | E60: ='Benchmark détaillé'!BH5 | F60: ='Benchmark détaillé'!BH15 | G60: ='Benchmark détaillé'!BH13 | H60: ='Benchmark détaillé'!BH21 | I60: ='Benchmark détaillé'!BH22 | J60: ='Benchmark détaillé'!BH23 | K60: =IFERROR((H60-I60)/H60*100,"") | L60: =IFERROR((I60-J60)/I60*100,"") | M60: =IFERROR(I60/(E60/1000),"") | N60: =IFERROR(I60/(F60*G60),"") | O60: ='Benchmark détaillé'!BH31 | P60: ='Benchmark détaillé'!BH32 | Q60: =IFERROR(VLOOKUP(A60,'Discounts par marque'!$A:$G,4,FALSE),0) | R60: =IFERROR(VLOOKUP(A60,'Discounts par marque'!$A:$G,5,FALSE),0) | S60: =IFERROR(I60*(1-Q60/100),"") | T60: =IFERROR(S60/(F60*G60),"") | U60: =IFERROR(I60*(1-R60/100),"") | V60: =IFERROR(U60/(F60*G60),"") | W60: https://shop.biotechusa.fr/products/iso-whey-zero-908-g
A61: ='Benchmark détaillé'!BI1 | B61: Iso Whey Zero 1816g | C61: ='Benchmark détaillé'!BI4 | D61: ='Benchmark détaillé'!BI10 | E61: ='Benchmark détaillé'!BI5 | F61: ='Benchmark détaillé'!BI15 | G61: ='Benchmark détaillé'!BI13 | H61: ='Benchmark détaillé'!BI21 | I61: ='Benchmark détaillé'!BI22 | J61: ='Benchmark détaillé'!BI23 | K61: =IFERROR((H61-I61)/H61*100,"") | L61: =IFERROR((I61-J61)/I61*100,"") | M61: =IFERROR(I61/(E61/1000),"") | N61: =IFERROR(I61/(F61*G61),"") | O61: ='Benchmark détaillé'!BI31 | P61: ='Benchmark détaillé'!BI32 | Q61: =IFERROR(VLOOKUP(A61,'Discounts par marque'!$A:$G,4,FALSE),0) | R61: =IFERROR(VLOOKUP(A61,'Discounts par marque'!$A:$G,5,FALSE),0) | S61: =IFERROR(I61*(1-Q61/100),"") | T61: =IFERROR(S61/(F61*G61),"") | U61: =IFERROR(I61*(1-R61/100),"") | V61: =IFERROR(U61/(F61*G61),"") | W61: https://shop.biotechusa.fr/products/iso-whey-zero-poudre-de-proteine-isolat-1816-g
A62: ='Benchmark détaillé'!BJ1 | B62: 100% Pure Whey 400g | C62: ='Benchmark détaillé'!BJ4 | D62: ='Benchmark détaillé'!BJ10 | E62: ='Benchmark détaillé'!BJ5 | F62: ='Benchmark détaillé'!BJ15 | G62: ='Benchmark détaillé'!BJ13 | H62: ='Benchmark détaillé'!BJ21 | I62: ='Benchmark détaillé'!BJ22 | J62: ='Benchmark détaillé'!BJ23 | K62: =IFERROR((H62-I62)/H62*100,"") | L62: =IFERROR((I62-J62)/I62*100,"") | M62: =IFERROR(I62/(E62/1000),"") | N62: =IFERROR(I62/(F62*G62),"") | O62: ='Benchmark détaillé'!BJ31 | P62: ='Benchmark détaillé'!BJ32 | Q62: =IFERROR(VLOOKUP(A62,'Discounts par marque'!$A:$G,4,FALSE),0) | R62: =IFERROR(VLOOKUP(A62,'Discounts par marque'!$A:$G,5,FALSE),0) | S62: =IFERROR(I62*(1-Q62/100),"") | T62: =IFERROR(S62/(F62*G62),"") | U62: =IFERROR(I62*(1-R62/100),"") | V62: =IFERROR(U62/(F62*G62),"") | W62: https://shop.biotechusa.fr/products/100-pure-whey-400-g | X62: 8.2€/100g vs 5.5€/100g sur format 1kg (petit format plus cher)
A63: ='Benchmark détaillé'!BK1 | B63: 100% Pure Whey 1000g | C63: ='Benchmark détaillé'!BK4 | D63: ='Benchmark détaillé'!BK10 | E63: ='Benchmark détaillé'!BK5 | F63: ='Benchmark détaillé'!BK15 | G63: ='Benchmark détaillé'!BK13 | H63: ='Benchmark détaillé'!BK21 | I63: ='Benchmark détaillé'!BK22 | J63: ='Benchmark détaillé'!BK23 | K63: =IFERROR((H63-I63)/H63*100,"") | L63: =IFERROR((I63-J63)/I63*100,"") | M63: =IFERROR(I63/(E63/1000),"") | N63: =IFERROR(I63/(F63*G63),"") | O63: ='Benchmark détaillé'!BK31 | P63: ='Benchmark détaillé'!BK32 | Q63: =IFERROR(VLOOKUP(A63,'Discounts par marque'!$A:$G,4,FALSE),0) | R63: =IFERROR(VLOOKUP(A63,'Discounts par marque'!$A:$G,5,FALSE),0) | S63: =IFERROR(I63*(1-Q63/100),"") | T63: =IFERROR(S63/(F63*G63),"") | U63: =IFERROR(I63*(1-R63/100),"") | V63: =IFERROR(U63/(F63*G63),"") | W63: https://shop.biotechusa.fr/products/100-pure-whey-renouvele-1000-g | X63: GROS ÉCART : site marque 54.90€ vs idealo 27.02€ (-51%). Cross-retailers beaucoup moins cher.
A64: ='Benchmark détaillé'!BL1 | B64: 100% Pure Whey 2000g | C64: ='Benchmark détaillé'!BL4 | D64: ='Benchmark détaillé'!BL10 | E64: ='Benchmark détaillé'!BL5 | F64: ='Benchmark détaillé'!BL15 | G64: ='Benchmark détaillé'!BL13 | H64: ='Benchmark détaillé'!BL21 | I64: ='Benchmark détaillé'!BL22 | J64: ='Benchmark détaillé'!BL23 | K64: =IFERROR((H64-I64)/H64*100,"") | L64: =IFERROR((I64-J64)/I64*100,"") | M64: =IFERROR(I64/(E64/1000),"") | N64: =IFERROR(I64/(F64*G64),"") | O64: ='Benchmark détaillé'!BL31 | P64: ='Benchmark détaillé'!BL32 | Q64: =IFERROR(VLOOKUP(A64,'Discounts par marque'!$A:$G,4,FALSE),0) | R64: =IFERROR(VLOOKUP(A64,'Discounts par marque'!$A:$G,5,FALSE),0) | S64: =IFERROR(I64*(1-Q64/100),"") | T64: =IFERROR(S64/(F64*G64),"") | U64: =IFERROR(I64*(1-R64/100),"") | V64: =IFERROR(U64/(F64*G64),"") | W64: https://shop.biotechusa.fr/products/100-pure-whey-2000-g | X64: Cohérent avec 1kg : site marque surcoté vs cross-retailers (~-40-50%)

Sheet Discounts par marque
A1: Marque | B1: 1ère cmd (%) | C1: Remise bas fourchette (%) | D1: Remise client standard (%) | E1: Remise client averti (%) | F1: Remise plafond observé (%) | G1: % prix réel vs catalogue | H1: Fréquence promo | I1: Codes (top 5) | J1: N codes sourcés | K1: Règles stacking | L1: Note | M1: Sources
A2: IMPULSE | B2: 10 | C2: 15 | D2: 15 | E2: 15 | F2: 15 | G2: 85 | H2: ponctuel | I2: LORENA 15% (@lorena) | J2: 1 | K2: 10% première commande ne stacke pas avec code ambassadeur; parrainage 15% sur 1ère commande + 10% parrain | L2: Politique -10% bienvenue homepage; codes ambassadeurs typiquement 15%. Pas de promo quasi-permanente publique. | M2: https://impulse-nutrition.fr https://impulse-nutrition.fr/pages/refer https://fr.hotdeals.com/code-promo/impulse-nutrition
A3: NUTRIPURE | B3: 10 | H3: aucun | J3: 0 | K3: Pas de cumul; 10% fidélité + 10% packs intégré | L3: Politique anti-promo délibérée. Pas de Black Friday, pas de codes influenceurs >10%. Seuls le parrainage (10%) et les packs (10-25% intégrés) existent. Le prix catalogue est le vrai prix. | M3: https://www.nutripure.fr/fr/info/29-code-promo-nutripure https://www.edp-nutrition.fr/code-promo-nutripure-influenceur/
A4: NUTRIMUSCLE | C4: 10 | D4: 10 | E4: 10 | F4: 10 | G4: 90 | H4: ponctuel | I4: NMA_HYBRIDX5 10% (@valentingenest) NME_NABFIT 5% (@nabfit) NME_NUTRITION5 5% (générique) | J4: 3 | K4: Codes 5-10% cumulables avec packs réduits; ventes -20% saisonnières | L4: Politique codes influenceurs très modérés (5-10%, rarement 15%). Promos -20% uniquement en périodes soldes/Black Friday. | M4: https://www.dealabs.com/codes-promo/nutrimuscle.com https://eu.nutrimuscle.com/pages/nos-offres https://www.influenceur.promo/marques/nutrimuscle/
A5: NUTRI&CO | B5: 10 | C5: 10 | D5: 10 | E5: 10 | F5: 10 | G5: 90 | H5: ponctuel | I5: LESAVISDEMILIE10 10% (@lesavisdemilie) FITBYALEXIA 10% (@fitbyalexia) | J5: 2 | K5: Codes plafonnés à 10%, durée limitée | L5: Politique codes influenceurs plafonnée à 10%. Positionnement santé/premium, promos modérées. | M5: https://www.influenceur.promo/marques/nutrico/ https://www.edp-nutrition.fr/code-promo-nutri-and-co-influenceur/
A6: AQEELAB | B6: 15 | C6: 12 | D6: 12 | E6: 12 | F6: 12 | G6: 88 | H6: quasi-permanent | I6: LEVAND 20% (@alex.levand) TRISTAN15 15% (@tristan) CREATINATOR 10% (@creatinator) | J6: 3 | K6: Codes sans minimum, sans date d'expiration, année entière | L6: Page officielle liste tous les codes (-5/-10/-15%/-25€). Politique transparente, codes stables toute l'année. | M6: https://www.aqeelab-nutrition.fr/pages/des-conseils-des-infos-et-des-reductions https://nabfit.fr/complements-alimentaires-musculation/pas-chers/codes-promo/aqeelab-nutrition/
A7: ERIC FAVRE | B7: 10 | C7: 10 | D7: 10 | E7: 15 | F7: 20 | G7: 85 | H7: quasi-permanent | I7: SUPER20 20% (code site (>=120€)) NPNG20 20% (code événementiel) BODY15 15% (code partenaire) EFNFC10 10% (@essan_nfc) FAVRE10 10% (code site générique) | J7: 6 | K7: Programme influenceur limité (~5 ambassadeurs identifiés). Codes site 10% no-min, 20% SUPER20 avec min 120€. Pas de cumul. | L7: Programme ambassadeur très modeste — Eric Favre est positionné plus pharmacie/pro-sport que fitness mass-market. Essan NFC est le seul vrai ambassadeur agrégé avec 1087 utilisations. P50=10%, P90=15%. Client averti paye ~85% du catalogue. | M7: https://www.ericfavre.com/fr_fr/reductions-codes-promo https://www.influenceur.promo/marques/eric-favre/ https://fr.hotdeals.com/store/code-promo-eric-favre
A8: EAFIT | B8: 30 | C8: 20 | D8: 32 | E8: 32 | F8: 35 | G8: 68 | H8: quasi-permanent | I8: CPS32 32% (@tamara.awada) MARION32 32% (@mrsmariont) MATHILDE32 32% (@mathildegros) TATIANA32 32% (@tatianamembre) ILONA32 32% (@ilonafrigout) | J8: 10 | K8: Programme français standardisé à 32% (suffixe *32 sur 8+ codes récents). Ancien programme 20% résiduel (EMILIE20). Code site FIT25=25% + pack offert dès 60€. Pas de cumul code influenceur + FIT25. | L8: Programme ambassadeur UPGRADÉ à 32% (vs 20% historique). Client averti paye ~68% du catalogue via code CPS32/MARION32. Plus agressif qu'attendu pour une marque française. | M8: https://www.eafit.com/deals-du-moment.html https://www.influenceur.promo/marques/ea-fit/ https://www.lesavisdemilie.fr/code-promo-eafit/
A9: DECATHLON | H9: ponctuel | J9: 0 | L9: Corength / Aptonia sans programme d'affiliation influenceur structuré. Prix catalogue stables, promos seulement lors soldes Decathlon globales. | M9: https://www.decathlon.fr/nutrition-sante/whey-proteines https://www.lareduction.fr/s/decathlon.fr
A10: BULK | B10: 15 | C10: 25 | D10: 45 | E10: 45 | F10: 45 | G10: 55 | H10: quasi-permanent | I10: BUDDY45 45% (@tristandefeuilletvang) TWINS 45% (@twinsb_fit) ARTHUR 45% (@arthurbenedetti) LIFTIT 45% (@hugophilip) ALIX 45% (@alixmhd) | J10: 10 | K10: Distribution quasi monolithique à 45% (codes récents 2024-2026) + reliquat 20-25% (codes anciens). Site affiche 'jusqu'à -75%' en homepage (cumul produit-promo + code). Flash sales 'Bulk Week' -50/-70% ponctuelles. Code influenceur ne stacke pas avec flash sale. | L10: Programme ULTRA-STANDARDISÉ : 20+ ambassadeurs au même code 45%. Tes 30% initiaux étaient largement sous-estimés — P50 réel = 45%. Site-wide banner '-75%' atteint via cumul. Client averti paye ~55% du catalogue. | M10: https://www.influenceur.promo/marques/bulk-powders/ https://www.lesavisdemilie.fr/code-promo-bulk/ https://www.savoo.fr/marques/codes-promo-bulk
A11: MYPROTEIN | B11: 40 | C11: 20 | D11: 42 | E11: 50 | F11: 55 | G11: 52 | H11: quasi-permanent | I11: MELISSAT 55% (@melissathiebaut) BUDDY 50% (@tristandefeuilletvang) PAUL 50% (@pauldenisnavero) TURBOTIFF 50% (@tiffanychapon) TDYPARKER 50% (@tdyparker) | J11: 12 | K11: Site affiche en permanence 'up to 55% off' en bandeau homepage. Codes influenceurs NE se cumulent PAS avec flash sale site — le plus élevé s'applique, typiquement code influenceur 42-50% remplace promo 30-40% base. | L11: PRIX CATALOGUE TOTALEMENT FICTIF. Promo permanente 30-55% en bandeau site. P50 codes influenceurs = 42%, P90 = 50%, max = 55%. Le client averti applique systématiquement un code 50% → paye ~50% du catalogue. Les 35% initiaux étaient largement sous-estimés (~P25). | M11: https://www.influenceur.promo/marques/myprotein/ https://kotag.co/marques/codes-promo-myprotein/ https://www.codes-promo-influenceurs.fr/marques/myprotein https://fr.myprotein.com/c/nouveaux-clients/
A12: PROZIS | B12: 10 | C12: 10 | D12: 10 | E12: 20 | F12: 50 | G12: 65 | H12: quasi-permanent | I12: 19YEARS 50% (flash sale anniversaire) MADNESS 40% (flash sale site) KEONII 10% (@keonii) LAURAPETARD 10% (@laurapetard) QFITLIFE 10% (@quentin-fitlife) | J12: 10 | K12: Codes influenceurs standardisés à 10% — cumul PARTIEL avec promos produit (pack, outlet) mais PAS avec flash sales (MADNESS, 19YEARS, BLACKWEEK à 40-50%). Site en permanence avec produits -30 à -50% en outlet. | L12: Très modéré côté influenceurs (10% dominant) mais les flash sales saisonnières (MADNESS, 19YEARS) vont jusqu'à 50%. Client averti attend une flash sale pour commander. P50 codes quotidiens = 10%, P90 = 20% (outlet), max = 50% (flash sale). | M12: https://www.influenceur.promo/marques/prozis/ https://fr.promocodie.com/code/code-promo-prozis-influenceur
A13: FOODSPRING | B13: 10 | C13: 15 | D13: 15 | E13: 20 | F13: 30 | G13: 85 | H13: quasi-permanent | I13: FOODSPRING30 30% (site code évènementiel) FS20SALE 20% (@yamina_niya) ALIZOUFSG 20% (@alizeeandreani) JUJUFSG 20% (@juliecfs) JESSICA15 15% (@jessicathivenin) | J13: 10 | K13: Programme ultra-standardisé à 15% (60+ codes suffixe *FSG). Remontées ponctuelles à 20% (Black Week, SummerSale). Code site FOODSPRING30 = 30% évènementiel. Pas de cumul entre code influenceur et flash sale. | L13: Très conservateur (15% dominant, ~85% des codes). Stratégie Foodspring = premium, moins de guerre des prix que MyProtein/Bulk. P50 = 15% fiable, P90 = 20%. Client averti paye ~85% du catalogue. | M13: https://www.influenceur.promo/marques/foodspring/ https://vivremoinscher.fr/stores/foodspring-coupons/
A14: ESN | B14: 10 | C14: 15 | D14: 20 | E14: 25 | F14: 30 | G14: 80 | H14: quasi-permanent | I14: ELENA 20% (@elena.ntns) KIMMIE 20% (@kimmieous) LEON 20% (@leonidas_arkona) LARA 20% (@laraemilia) KEVIN 20% (@wolterkevin) | J14: 8 | K14: Programme allemand standardisé à 20%. 'Performance Week' et flash sales site jusqu'à 40-50%, pas de cumul. Discounts site ciblés par catégorie (10% outlet, 20% selected, 50% certains variants). | L14: Distribution très uniforme à 20% (tous ambassadeurs). Max 25% sur promos saisonales. Moins agressif que MyProtein/Bulk. Client paye ~80% du catalogue. | M14: https://www.influencercodes.de/marken/esn/ https://suppwiser.de/rabattcodes/esn-rabattcode/ https://fr.coupert.com/codes-promo/esn-com
A15: BIOTECHUSA | B15: 10 | C15: 15 | D15: 15 | E15: 20 | F15: 30 | G15: 82 | H15: quasi-permanent | I15: SUPER1225 30% (site code évènementiel) GYM33 20% (@gym33) JENZO15 15% (@jeanneetenzo) ANA15 15% (@anastasiyabury) REMI15 15% (@remi_ragnar) | J15: 6 | K15: Programme ambassadeurs à 15% fixe (TRND + partenariats directs). Codes site évènementiels jusqu'à 30-40%. Programme de fidélité cumulable avec code influenceur selon ambassadeur. | L15: Programme modeste : 15% standard, rarement au-delà de 20%. BiotechUSA = marque hongroise low-cost de base. P50 = 15% très fiable. Client paye ~82% du catalogue. | M15: https://shop.biotechusa.fr/collections/promotion-mensuelle-automatique https://shop.biotechusa.fr/pages/loyalty-program https://kotag.co/marques/codes-promo-biotechusa/

Sheet Classement €⁄g protéine
A1: Classement par 'Prix client standard / g protéine' croissant (#1 = meilleur rapport qualité/prix pour un client avec un code ambassadeur typique). Les valeurs chiffrées sont des formules live référençant l'onglet 'Synthèse prix'. Seul l'ordre de tri est figé au build. Si tu modifies un prix/remise dans Synthèse ou Discounts, les valeurs ici se mettent à jour. Pour réordonner le classement après une modif majeure, regénère le xlsx.
A2: Rang | B2: Marque | C2: Produit | D2: Format | E2: Prix nominal | F2: Prix actuel | G2: Prix marché | H2: Prix actuel /g prot | I2: Prix client standard | J2: Prix client standard /g prot | K2: Prix client averti | L2: Prix client averti /g prot | M2: Remise standard (%)
A3: 1 | B3: ='Synthèse prix'!A46 | C3: Impact Whey Protein 2,5kg | D3: 2.5kg | E3: ='Synthèse prix'!H46 | F3: ='Synthèse prix'!I46 | G3: ='Synthèse prix'!J46 | H3: ='Synthèse prix'!N46 | I3: ='Synthèse prix'!S46 | J3: ='Synthèse prix'!T46 | K3: ='Synthèse prix'!U46 | L3: ='Synthèse prix'!V46 | M3: ='Synthèse prix'!Q46
A4: 2 | B4: ='Synthèse prix'!A45 | C4: Impact Whey Protein 1kg | D4: 1kg | E4: ='Synthèse prix'!H45 | F4: ='Synthèse prix'!I45 | G4: ='Synthèse prix'!J45 | H4: ='Synthèse prix'!N45 | I4: ='Synthèse prix'!S45 | J4: ='Synthèse prix'!T45 | K4: ='Synthèse prix'!U45 | L4: ='Synthèse prix'!V45 | M4: ='Synthèse prix'!Q45
A5: 3 | B5: ='Synthèse prix'!A47 | C5: Impact Whey Protein 5kg (Sans arôme) | D5: 5kg | E5: ='Synthèse prix'!H47 | F5: ='Synthèse prix'!I47 | G5: ='Synthèse prix'!J47 | H5: ='Synthèse prix'!N47 | I5: ='Synthèse prix'!S47 | J5: ='Synthèse prix'!T47 | K5: ='Synthèse prix'!U47 | L5: ='Synthèse prix'!V47 | M5: ='Synthèse prix'!Q47
A6: 4 | B6: ='Synthèse prix'!A40 | C6: Pure Whey Protein 2,5kg | D6: 2.5kg | E6: ='Synthèse prix'!H40 | F6: ='Synthèse prix'!I40 | G6: ='Synthèse prix'!J40 | H6: ='Synthèse prix'!N40 | I6: ='Synthèse prix'!S40 | J6: ='Synthèse prix'!T40 | K6: ='Synthèse prix'!U40 | L6: ='Synthèse prix'!V40 | M6: ='Synthèse prix'!Q40
A7: 5 | B7: ='Synthèse prix'!A41 | C7: Pure Whey Protein 5kg | D7: 5kg | E7: ='Synthèse prix'!H41 | F7: ='Synthèse prix'!I41 | G7: ='Synthèse prix'!J41 | H7: ='Synthèse prix'!N41 | I7: ='Synthèse prix'!S41 | J7: ='Synthèse prix'!T41 | K7: ='Synthèse prix'!U41 | L7: ='Synthèse prix'!V41 | M7: ='Synthèse prix'!Q41
A8: 6 | B8: ='Synthèse prix'!A39 | C8: Pure Whey Protein 1kg | D8: 1kg | E8: ='Synthèse prix'!H39 | F8: ='Synthèse prix'!I39 | G8: ='Synthèse prix'!J39 | H8: ='Synthèse prix'!N39 | I8: ='Synthèse prix'!S39 | J8: ='Synthèse prix'!T39 | K8: ='Synthèse prix'!U39 | L8: ='Synthèse prix'!V39 | M8: ='Synthèse prix'!Q39
A9: 7 | B9: ='Synthèse prix'!A38 | C9: Pure Whey Isolate 2,5kg | D9: 2.5kg | E9: ='Synthèse prix'!H38 | F9: ='Synthèse prix'!I38 | G9: ='Synthèse prix'!J38 | H9: ='Synthèse prix'!N38 | I9: ='Synthèse prix'!S38 | J9: ='Synthèse prix'!T38 | K9: ='Synthèse prix'!U38 | L9: ='Synthèse prix'!V38 | M9: ='Synthèse prix'!Q38
A10: 8 | B10: ='Synthèse prix'!A59 | C10: Basic Whey 2000g | D10: 2kg | E10: ='Synthèse prix'!H59 | F10: ='Synthèse prix'!I59 | G10: ='Synthèse prix'!J59 | H10: ='Synthèse prix'!N59 | I10: ='Synthèse prix'!S59 | J10: ='Synthèse prix'!T59 | K10: ='Synthèse prix'!U59 | L10: ='Synthèse prix'!V59 | M10: ='Synthèse prix'!Q59
A11: 9 | B11: ='Synthèse prix'!A37 | C11: Pure Whey Isolate 1kg | D11: 1kg | E11: ='Synthèse prix'!H37 | F11: ='Synthèse prix'!I37 | G11: ='Synthèse prix'!J37 | H11: ='Synthèse prix'!N37 | I11: ='Synthèse prix'!S37 | J11: ='Synthèse prix'!T37 | K11: ='Synthèse prix'!U37 | L11: ='Synthèse prix'!V37 | M11: ='Synthèse prix'!Q37
A12: 10 | B12: ='Synthèse prix'!A44 | C12: Impact Whey Isolate 2,5kg | D12: 2.5kg | E12: ='Synthèse prix'!H44 | F12: ='Synthèse prix'!I44 | G12: ='Synthèse prix'!J44 | H12: ='Synthèse prix'!N44 | I12: ='Synthèse prix'!S44 | J12: ='Synthèse prix'!T44 | K12: ='Synthèse prix'!U44 | L12: ='Synthèse prix'!V44 | M12: ='Synthèse prix'!Q44
A13: 11 | B13: ='Synthèse prix'!A57 | C13: Basic Whey 1000g | D13: 1kg | E13: ='Synthèse prix'!H57 | F13: ='Synthèse prix'!I57 | G13: ='Synthèse prix'!J57 | H13: ='Synthèse prix'!N57 | I13: ='Synthèse prix'!S57 | J13: ='Synthèse prix'!T57 | K13: ='Synthèse prix'!U57 | L13: ='Synthèse prix'!V57 | M13: ='Synthèse prix'!Q57
A14: 12 | B14: ='Synthèse prix'!A34 | C14: Pure Whey Protein 2.2kg | D14: 2.2kg | E14: ='Synthèse prix'!H34 | F14: ='Synthèse prix'!I34 | G14: ='Synthèse prix'!J34 | H14: ='Synthèse prix'!N34 | I14: ='Synthèse prix'!S34 | J14: ='Synthèse prix'!T34 | K14: ='Synthèse prix'!U34 | L14: ='Synthèse prix'!V34 | M14: ='Synthèse prix'!Q34
A15: 13 | B15: ='Synthèse prix'!A43 | C15: Impact Whey Isolate 1kg | D15: 1kg | E15: ='Synthèse prix'!H43 | F15: ='Synthèse prix'!I43 | G15: ='Synthèse prix'!J43 | H15: ='Synthèse prix'!N43 | I15: ='Synthèse prix'!S43 | J15: ='Synthèse prix'!T43 | K15: ='Synthèse prix'!U43 | L15: ='Synthèse prix'!V43 | M15: ='Synthèse prix'!Q43
A16: 14 | B16: ='Synthèse prix'!A28 | C16: Iso Fusion Protein Complex 2kg | D16: 2kg | E16: ='Synthèse prix'!H28 | F16: ='Synthèse prix'!I28 | G16: ='Synthèse prix'!J28 | H16: ='Synthèse prix'!N28 | I16: ='Synthèse prix'!S28 | J16: ='Synthèse prix'!T28 | K16: ='Synthèse prix'!U28 | L16: ='Synthèse prix'!V28 | M16: ='Synthèse prix'!Q28
A17: 15 | B17: ='Synthèse prix'!A17 | C17: Whey Native Concentrat 4kg | D17: 4kg | E17: ='Synthèse prix'!H17 | F17: ='Synthèse prix'!I17 | G17: ='Synthèse prix'!J17 | H17: ='Synthèse prix'!N17 | I17: ='Synthèse prix'!S17 | J17: ='Synthèse prix'!T17 | K17: ='Synthèse prix'!U17 | L17: ='Synthèse prix'!V17 | M17: ='Synthèse prix'!Q17
A18: 16 | B18: ='Synthèse prix'!A31 | C18: Pure Whey Protein 750g | D18: 750g | E18: ='Synthèse prix'!H31 | F18: ='Synthèse prix'!I31 | G18: ='Synthèse prix'!J31 | H18: ='Synthèse prix'!N31 | I18: ='Synthèse prix'!S31 | J18: ='Synthèse prix'!T31 | K18: ='Synthèse prix'!U31 | L18: ='Synthèse prix'!V31 | M18: ='Synthèse prix'!Q31
A19: 17 | B19: ='Synthèse prix'!A52 | C19: 100% Real Whey Protein 2000g | D19: 2kg | E19: ='Synthèse prix'!H52 | F19: ='Synthèse prix'!I52 | G19: ='Synthèse prix'!J52 | H19: ='Synthèse prix'!N52 | I19: ='Synthèse prix'!S52 | J19: ='Synthèse prix'!T52 | K19: ='Synthèse prix'!U52 | L19: ='Synthèse prix'!V52 | M19: ='Synthèse prix'!Q52
A20: 18 | B20: ='Synthèse prix'!A16 | C20: Whey Native Concentrat 2,25kg | D20: 2.25kg | E20: ='Synthèse prix'!H16 | F20: ='Synthèse prix'!I16 | G20: ='Synthèse prix'!J16 | H20: ='Synthèse prix'!N16 | I20: ='Synthèse prix'!S16 | J20: ='Synthèse prix'!T16 | K20: ='Synthèse prix'!U16 | L20: ='Synthèse prix'!V16 | M20: ='Synthèse prix'!Q16
A21: 19 | B21: ='Synthèse prix'!A33 | C21: Pure Whey Protein 850g | D21: 850g | E21: ='Synthèse prix'!H33 | F21: ='Synthèse prix'!I33 | G21: ='Synthèse prix'!J33 | H21: ='Synthèse prix'!N33 | I21: ='Synthèse prix'!S33 | J21: ='Synthèse prix'!T33 | K21: ='Synthèse prix'!U33 | L21: ='Synthèse prix'!V33 | M21: ='Synthèse prix'!Q33
A22: 20 | B22: ='Synthèse prix'!A48 | C22: Clear Whey Isolate 875g | D22: 875g | E22: ='Synthèse prix'!H48 | F22: ='Synthèse prix'!I48 | G22: ='Synthèse prix'!J48 | H22: ='Synthèse prix'!N48 | I22: ='Synthèse prix'!S48 | J22: ='Synthèse prix'!T48 | K22: ='Synthèse prix'!U48 | L22: ='Synthèse prix'!V48 | M22: ='Synthèse prix'!Q48
A23: 21 | B23: ='Synthèse prix'!A54 | C23: Whey Protein 750g | D23: 750g | E23: ='Synthèse prix'!H54 | F23: ='Synthèse prix'!I54 | G23: ='Synthèse prix'!J54 | H23: ='Synthèse prix'!N54 | I23: ='Synthèse prix'!S54 | J23: ='Synthèse prix'!T54 | K23: ='Synthèse prix'!U54 | L23: ='Synthèse prix'!V54 | M23: ='Synthèse prix'!Q54
A24: 22 | B24: ='Synthèse prix'!A15 | C24: Whey Native Concentrat | D24: 1kg | E24: ='Synthèse prix'!H15 | F24: ='Synthèse prix'!I15 | G24: ='Synthèse prix'!J15 | H24: ='Synthèse prix'!N15 | I24: ='Synthèse prix'!S15 | J24: ='Synthèse prix'!T15 | K24: ='Synthèse prix'!U15 | L24: ='Synthèse prix'!V15 | M24: ='Synthèse prix'!Q15
A25: 23 | B25: ='Synthèse prix'!A42 | C25: Clear Whey Isolate 500g | D25: 500g | E25: ='Synthèse prix'!H42 | F25: ='Synthèse prix'!I42 | G25: ='Synthèse prix'!J42 | H25: ='Synthèse prix'!N42 | I25: ='Synthèse prix'!S42 | J25: ='Synthèse prix'!T42 | K25: ='Synthèse prix'!U42 | L25: ='Synthèse prix'!V42 | M25: ='Synthèse prix'!Q42
A26: 24 | B26: ='Synthèse prix'!A36 | C26: Whey Protein 900g (Concentrat) | D26: 900g | E26: ='Synthèse prix'!H36 | F26: ='Synthèse prix'!I36 | G26: ='Synthèse prix'!J36 | H26: ='Synthèse prix'!N36 | I26: ='Synthèse prix'!S36 | J26: ='Synthèse prix'!T36 | K26: ='Synthèse prix'!U36 | L26: ='Synthèse prix'!V36 | M26: ='Synthèse prix'!Q36
A27: 25 | B27: ='Synthèse prix'!A53 | C27: 100% Whey Hydro Isolate 2000g | D27: 2kg | E27: ='Synthèse prix'!H53 | F27: ='Synthèse prix'!I53 | G27: ='Synthèse prix'!J53 | H27: ='Synthèse prix'!N53 | I27: ='Synthèse prix'!S53 | J27: ='Synthèse prix'!T53 | K27: ='Synthèse prix'!U53 | L27: ='Synthèse prix'!V53 | M27: ='Synthèse prix'!Q53
A28: 26 | B28: ='Synthèse prix'!A14 | C28: Whey Native Concentrat 500g | D28: 500g | E28: ='Synthèse prix'!H14 | F28: ='Synthèse prix'!I14 | G28: ='Synthèse prix'!J14 | H28: ='Synthèse prix'!N14 | I28: ='Synthèse prix'!S14 | J28: ='Synthèse prix'!T14 | K28: ='Synthèse prix'!U14 | L28: ='Synthèse prix'!V14 | M28: ='Synthèse prix'!Q14
A29: 27 | B29: ='Synthèse prix'!A58 | C29: Designer Whey Protein 2000g | D29: 2kg | E29: ='Synthèse prix'!H58 | F29: ='Synthèse prix'!I58 | G29: ='Synthèse prix'!J58 | H29: ='Synthèse prix'!N58 | I29: ='Synthèse prix'!S58 | J29: ='Synthèse prix'!T58 | K29: ='Synthèse prix'!U58 | L29: ='Synthèse prix'!V58 | M29: ='Synthèse prix'!Q58
A30: 28 | B30: ='Synthèse prix'!A25 | C30: Whey Optimax Protein 1,5kg | D30: 1.5kg | E30: ='Synthèse prix'!H25 | F30: ='Synthèse prix'!I25 | G30: ='Synthèse prix'!J25 | H30: ='Synthèse prix'!N25 | I30: ='Synthèse prix'!S25 | J30: ='Synthèse prix'!T25 | K30: ='Synthèse prix'!U25 | L30: ='Synthèse prix'!V25 | M30: ='Synthèse prix'!Q25
A31: 29 | B31: ='Synthèse prix'!A51 | C31: 100% Real Whey Protein 907g | D31: 907g | E31: ='Synthèse prix'!H51 | F31: ='Synthèse prix'!I51 | G31: ='Synthèse prix'!J51 | H31: ='Synthèse prix'!N51 | I31: ='Synthèse prix'!S51 | J31: ='Synthèse prix'!T51 | K31: ='Synthèse prix'!U51 | L31: ='Synthèse prix'!V51 | M31: ='Synthèse prix'!Q51
A32: 30 | B32: ='Synthèse prix'!A29 | C32: Pure Isolate 750g | D32: 750g | E32: ='Synthèse prix'!H29 | F32: ='Synthèse prix'!I29 | G32: ='Synthèse prix'!J29 | H32: ='Synthèse prix'!N29 | I32: ='Synthèse prix'!S29 | J32: ='Synthèse prix'!T29 | K32: ='Synthèse prix'!U29 | L32: ='Synthèse prix'!V29 | M32: ='Synthèse prix'!Q29
A33: 31 | B33: ='Synthèse prix'!A26 | C33: Whey Zero Protéine 2kg | D33: 2kg | E33: ='Synthèse prix'!H26 | F33: ='Synthèse prix'!I26 | G33: ='Synthèse prix'!J26 | H33: ='Synthèse prix'!N26 | I33: ='Synthèse prix'!S26 | J33: ='Synthèse prix'!T26 | K33: ='Synthèse prix'!U26 | L33: ='Synthèse prix'!V26 | M33: ='Synthèse prix'!Q26
A34: 32 | B34: ='Synthèse prix'!A4 | C34: Whey Isolate | D34: 750g | E34: ='Synthèse prix'!H4 | F34: ='Synthèse prix'!I4 | G34: ='Synthèse prix'!J4 | H34: ='Synthèse prix'!N4 | I34: ='Synthèse prix'!S4 | J34: ='Synthèse prix'!T4 | K34: ='Synthèse prix'!U4 | L34: ='Synthèse prix'!V4 | M34: ='Synthèse prix'!Q4
A35: 33 | B35: ='Synthèse prix'!A56 | C35: Designer Whey Protein 908g | D35: 908g | E35: ='Synthèse prix'!H56 | F35: ='Synthèse prix'!I56 | G35: ='Synthèse prix'!J56 | H35: ='Synthèse prix'!N56 | I35: ='Synthèse prix'!S56 | J35: ='Synthèse prix'!T56 | K35: ='Synthèse prix'!U56 | L35: ='Synthèse prix'!V56 | M35: ='Synthèse prix'!Q56
A36: 34 | B36: ='Synthèse prix'!A32 | C36: Mega Whey Creatine Complex 750g | D36: 750g | E36: ='Synthèse prix'!H32 | F36: ='Synthèse prix'!I32 | G36: ='Synthèse prix'!J32 | H36: ='Synthèse prix'!N32 | I36: ='Synthèse prix'!S32 | J36: ='Synthèse prix'!T32 | K36: ='Synthèse prix'!U32 | L36: ='Synthèse prix'!V32 | M36: ='Synthèse prix'!Q32
A37: 35 | B37: ='Synthèse prix'!A13 | C37: Whey Native Isolate 4kg | D37: 4kg | E37: ='Synthèse prix'!H13 | F37: ='Synthèse prix'!I13 | G37: ='Synthèse prix'!J13 | H37: ='Synthèse prix'!N13 | I37: ='Synthèse prix'!S13 | J37: ='Synthèse prix'!T13 | K37: ='Synthèse prix'!U13 | L37: ='Synthèse prix'!V13 | M37: ='Synthèse prix'!Q13
A38: 36 | B38: ='Synthèse prix'!A23 | C38: Iso Zero 100% Whey Protéine 2kg | D38: 2kg | E38: ='Synthèse prix'!H23 | F38: ='Synthèse prix'!I23 | G38: ='Synthèse prix'!J23 | H38: ='Synthèse prix'!N23 | I38: ='Synthèse prix'!S23 | J38: ='Synthèse prix'!T23 | K38: ='Synthèse prix'!U23 | L38: ='Synthèse prix'!V23 | M38: ='Synthèse prix'!Q23
A39: 37 | B39: ='Synthèse prix'!A30 | C39: Pure Isolate Premium 750g | D39: 750g | E39: ='Synthèse prix'!H30 | F39: ='Synthèse prix'!I30 | G39: ='Synthèse prix'!J30 | H39: ='Synthèse prix'!N30 | I39: ='Synthèse prix'!S30 | J39: ='Synthèse prix'!T30 | K39: ='Synthèse prix'!U30 | L39: ='Synthèse prix'!V30 | M39: ='Synthèse prix'!Q30
A40: 38 | B40: ='Synthèse prix'!A55 | C40: Iso Whey Protein Isolat 908g | D40: 908g | E40: ='Synthèse prix'!H55 | F40: ='Synthèse prix'!I55 | G40: ='Synthèse prix'!J55 | H40: ='Synthèse prix'!N55 | I40: ='Synthèse prix'!S55 | J40: ='Synthèse prix'!T55 | K40: ='Synthèse prix'!U55 | L40: ='Synthèse prix'!V55 | M40: ='Synthèse prix'!Q55
A41: 39 | B41: ='Synthèse prix'!A20 | C41: Whey Native 810g | D41: 810g | E41: ='Synthèse prix'!H20 | F41: ='Synthèse prix'!I20 | G41: ='Synthèse prix'!J20 | H41: ='Synthèse prix'!N20 | I41: ='Synthèse prix'!S20 | J41: ='Synthèse prix'!T20 | K41: ='Synthèse prix'!U20 | L41: ='Synthèse prix'!V20 | M41: ='Synthèse prix'!Q20
A42: 40 | B42: ='Synthèse prix'!A2 | C42: Whey Isolate | D42: 750g | E42: ='Synthèse prix'!H2 | F42: ='Synthèse prix'!I2 | G42: ='Synthèse prix'!J2 | H42: ='Synthèse prix'!N2 | I42: ='Synthèse prix'!S2 | J42: ='Synthèse prix'!T2 | K42: ='Synthèse prix'!U2 | L42: ='Synthèse prix'!V2 | M42: ='Synthèse prix'!Q2
A43: 41 | B43: ='Synthèse prix'!A3 | C43: Whey Isolate | D43: 750g | E43: ='Synthèse prix'!H3 | F43: ='Synthèse prix'!I3 | G43: ='Synthèse prix'!J3 | H43: ='Synthèse prix'!N3 | I43: ='Synthèse prix'!S3 | J43: ='Synthèse prix'!T3 | K43: ='Synthèse prix'!U3 | L43: ='Synthèse prix'!V3 | M43: ='Synthèse prix'!Q3
A44: 42 | B44: ='Synthèse prix'!A35 | C44: Pure Whey 100% Isolate 900g | D44: 900g | E44: ='Synthèse prix'!H35 | F44: ='Synthèse prix'!I35 | G44: ='Synthèse prix'!J35 | H44: ='Synthèse prix'!N35 | I44: ='Synthèse prix'!S35 | J44: ='Synthèse prix'!T35 | K44: ='Synthèse prix'!U35 | L44: ='Synthèse prix'!V35 | M44: ='Synthèse prix'!Q35
A45: 43 | B45: ='Synthèse prix'!A9 | C45: Whey Isolat Native 4kg | D45: 4kg | E45: ='Synthèse prix'!H9 | F45: ='Synthèse prix'!I9 | G45: ='Synthèse prix'!J9 | H45: ='Synthèse prix'!N9 | I45: ='Synthèse prix'!S9 | J45: ='Synthèse prix'!T9 | K45: ='Synthèse prix'!U9 | L45: ='Synthèse prix'!V9 | M45: ='Synthèse prix'!Q9
A46: 44 | B46: ='Synthèse prix'!A19 | C46: Whey Concentrée Native 900g | D46: 900g | E46: ='Synthèse prix'!H19 | F46: ='Synthèse prix'!I19 | G46: ='Synthèse prix'!J19 | H46: ='Synthèse prix'!N19 | I46: ='Synthèse prix'!S19 | J46: ='Synthèse prix'!T19 | K46: ='Synthèse prix'!U19 | L46: ='Synthèse prix'!V19 | M46: ='Synthèse prix'!Q19
A47: 45 | B47: ='Synthèse prix'!A64 | C47: 100% Pure Whey 2000g | D47: 2kg | E47: ='Synthèse prix'!H64 | F47: ='Synthèse prix'!I64 | G47: ='Synthèse prix'!J64 | H47: ='Synthèse prix'!N64 | I47: ='Synthèse prix'!S64 | J47: ='Synthèse prix'!T64 | K47: ='Synthèse prix'!U64 | L47: ='Synthèse prix'!V64 | M47: ='Synthèse prix'!Q64
A48: 46 | B48: ='Synthèse prix'!A12 | C48: Whey Native Isolate 2,25kg | D48: 2.25kg | E48: ='Synthèse prix'!H12 | F48: ='Synthèse prix'!I12 | G48: ='Synthèse prix'!J12 | H48: ='Synthèse prix'!N12 | I48: ='Synthèse prix'!S12 | J48: ='Synthèse prix'!T12 | K48: ='Synthèse prix'!U12 | L48: ='Synthèse prix'!V12 | M48: ='Synthèse prix'!Q12
A49: 47 | B49: ='Synthèse prix'!A49 | C49: Zero Diet Whey 750g | D49: 750g | E49: ='Synthèse prix'!H49 | F49: ='Synthèse prix'!I49 | G49: ='Synthèse prix'!J49 | H49: ='Synthèse prix'!N49 | I49: ='Synthèse prix'!S49 | J49: ='Synthèse prix'!T49 | K49: ='Synthèse prix'!U49 | L49: ='Synthèse prix'!V49 | M49: ='Synthèse prix'!Q49
A50: 48 | B50: ='Synthèse prix'!A50 | C50: 100% Real Whey Isolate 1000g | D50: 1kg | E50: ='Synthèse prix'!H50 | F50: ='Synthèse prix'!I50 | G50: ='Synthèse prix'!J50 | H50: ='Synthèse prix'!N50 | I50: ='Synthèse prix'!S50 | J50: ='Synthèse prix'!T50 | K50: ='Synthèse prix'!U50 | L50: ='Synthèse prix'!V50 | M50: ='Synthèse prix'!Q50
A51: 49 | B51: ='Synthèse prix'!A22 | C51: Iso Zero 100% Whey Protéine 1,5kg | D51: 1.5kg | E51: ='Synthèse prix'!H22 | F51: ='Synthèse prix'!I22 | G51: ='Synthèse prix'!J22 | H51: ='Synthèse prix'!N22 | I51: ='Synthèse prix'!S22 | J51: ='Synthèse prix'!T22 | K51: ='Synthèse prix'!U22 | L51: ='Synthèse prix'!V22 | M51: ='Synthèse prix'!Q22
A52: 50 | B52: ='Synthèse prix'!A18 | C52: Whey Isolate Native 900g | D52: 900g | E52: ='Synthèse prix'!H18 | F52: ='Synthèse prix'!I18 | G52: ='Synthèse prix'!J18 | H52: ='Synthèse prix'!N18 | I52: ='Synthèse prix'!S18 | J52: ='Synthèse prix'!T18 | K52: ='Synthèse prix'!U18 | L52: ='Synthèse prix'!V18 | M52: ='Synthèse prix'!Q18
A53: 51 | B53: ='Synthèse prix'!A61 | C53: Iso Whey Zero 1816g | D53: 1.816kg | E53: ='Synthèse prix'!H61 | F53: ='Synthèse prix'!I61 | G53: ='Synthèse prix'!J61 | H53: ='Synthèse prix'!N61 | I53: ='Synthèse prix'!S61 | J53: ='Synthèse prix'!T61 | K53: ='Synthèse prix'!U61 | L53: ='Synthèse prix'!V61 | M53: ='Synthèse prix'!Q61
A54: 52 | B54: ='Synthèse prix'!A27 | C54: Iso Fusion Protein Complex 750g | D54: 750g | E54: ='Synthèse prix'!H27 | F54: ='Synthèse prix'!I27 | G54: ='Synthèse prix'!J27 | H54: ='Synthèse prix'!N27 | I54: ='Synthèse prix'!S27 | J54: ='Synthèse prix'!T27 | K54: ='Synthèse prix'!U27 | L54: ='Synthèse prix'!V27 | M54: ='Synthèse prix'!Q27
A55: 53 | B55: ='Synthèse prix'!A8 | C55: Whey Isolat Native 2kg | D55: 2kg | E55: ='Synthèse prix'!H8 | F55: ='Synthèse prix'!I8 | G55: ='Synthèse prix'!J8 | H55: ='Synthèse prix'!N8 | I55: ='Synthèse prix'!S8 | J55: ='Synthèse prix'!T8 | K55: ='Synthèse prix'!U8 | L55: ='Synthèse prix'!V8 | M55: ='Synthèse prix'!Q8
A56: 54 | B56: ='Synthèse prix'!A7 | C56: Whey Isolat Native 750g | D56: 750g | E56: ='Synthèse prix'!H7 | F56: ='Synthèse prix'!I7 | G56: ='Synthèse prix'!J7 | H56: ='Synthèse prix'!N7 | I56: ='Synthèse prix'!S7 | J56: ='Synthèse prix'!T7 | K56: ='Synthèse prix'!U7 | L56: ='Synthèse prix'!V7 | M56: ='Synthèse prix'!Q7
A57: 55 | B57: ='Synthèse prix'!A11 | C57: Whey Native Isolate | D57: 1kg | E57: ='Synthèse prix'!H11 | F57: ='Synthèse prix'!I11 | G57: ='Synthèse prix'!J11 | H57: ='Synthèse prix'!N11 | I57: ='Synthèse prix'!S11 | J57: ='Synthèse prix'!T11 | K57: ='Synthèse prix'!U11 | L57: ='Synthèse prix'!V11 | M57: ='Synthèse prix'!Q11
A58: 56 | B58: ='Synthèse prix'!A63 | C58: 100% Pure Whey 1000g | D58: 1kg | E58: ='Synthèse prix'!H63 | F58: ='Synthèse prix'!I63 | G58: ='Synthèse prix'!J63 | H58: ='Synthèse prix'!N63 | I58: ='Synthèse prix'!S63 | J58: ='Synthèse prix'!T63 | K58: ='Synthèse prix'!U63 | L58: ='Synthèse prix'!V63 | M58: ='Synthèse prix'!Q63
A59: 57 | B59: ='Synthèse prix'!A10 | C59: Whey Native Isolate 500g | D59: 500g | E59: ='Synthèse prix'!H10 | F59: ='Synthèse prix'!I10 | G59: ='Synthèse prix'!J10 | H59: ='Synthèse prix'!N10 | I59: ='Synthèse prix'!S10 | J59: ='Synthèse prix'!T10 | K59: ='Synthèse prix'!U10 | L59: ='Synthèse prix'!V10 | M59: ='Synthèse prix'!Q10
A60: 58 | B60: ='Synthèse prix'!A21 | C60: Iso Zero 100% Whey Protéine 500g | D60: 500g | E60: ='Synthèse prix'!H21 | F60: ='Synthèse prix'!I21 | G60: ='Synthèse prix'!J21 | H60: ='Synthèse prix'!N21 | I60: ='Synthèse prix'!S21 | J60: ='Synthèse prix'!T21 | K60: ='Synthèse prix'!U21 | L60: ='Synthèse prix'!V21 | M60: ='Synthèse prix'!Q21
A61: 59 | B61: ='Synthèse prix'!A24 | C61: Whey Optimax Protein 500g | D61: 500g | E61: ='Synthèse prix'!H24 | F61: ='Synthèse prix'!I24 | G61: ='Synthèse prix'!J24 | H61: ='Synthèse prix'!N24 | I61: ='Synthèse prix'!S24 | J61: ='Synthèse prix'!T24 | K61: ='Synthèse prix'!U24 | L61: ='Synthèse prix'!V24 | M61: ='Synthèse prix'!Q24
A62: 60 | B62: ='Synthèse prix'!A60 | C62: Iso Whey Zero 908g | D62: 908g | E62: ='Synthèse prix'!H60 | F62: ='Synthèse prix'!I60 | G62: ='Synthèse prix'!J60 | H62: ='Synthèse prix'!N60 | I62: ='Synthèse prix'!S60 | J62: ='Synthèse prix'!T60 | K62: ='Synthèse prix'!U60 | L62: ='Synthèse prix'!V60 | M62: ='Synthèse prix'!Q60
A63: 61 | B63: ='Synthèse prix'!A62 | C63: 100% Pure Whey 400g | D63: 400g | E63: ='Synthèse prix'!H62 | F63: ='Synthèse prix'!I62 | G63: ='Synthèse prix'!J62 | H63: ='Synthèse prix'!N62 | I63: ='Synthèse prix'!S62 | J63: ='Synthèse prix'!T62 | K63: ='Synthèse prix'!U62 | L63: ='Synthèse prix'!V62 | M63: ='Synthèse prix'!Q62
A64: 62 | B64: ='Synthèse prix'!A5 | C64: Whey Recovery | D64: 525g | E64: ='Synthèse prix'!H5 | F64: ='Synthèse prix'!I5 | G64: ='Synthèse prix'!J5 | H64: ='Synthèse prix'!N5 | I64: ='Synthèse prix'!S5 | J64: ='Synthèse prix'!T5 | K64: ='Synthèse prix'!U5 | L64: ='Synthèse prix'!V5 | M64: ='Synthèse prix'!Q5
A65: 63 | B65: ='Synthèse prix'!A6 | C65: Whey Recovery | D65: 525g | E65: ='Synthèse prix'!H6 | F65: ='Synthèse prix'!I6 | G65: ='Synthèse prix'!J6 | H65: ='Synthèse prix'!N6 | I65: ='Synthèse prix'!S6 | J65: ='Synthèse prix'!T6 | K65: ='Synthèse prix'!U6 | L65: ='Synthèse prix'!V6 | M65: ='Synthèse prix'!Q6
